Workbook

Sheet README
A1: AutoBrain EV data: Mahindra (4 models) + Tata (7 models)
A2: Updated 22 Oct 2026. Specs verified from brochure (S009). All BaaS prices + One battery-included price verified from Mahindra website (S010, S011). Other battery-included prices still need checking.
A3: DECISION LAYER (new):
A4: Assumptions: editable tariffs, daily km, years (yellow cells). Engine_Variants: one clean row per variant, numeric fields, running cost and 5-year cost formulas, watch-outs.
A5: Variant_Ladder: every price step within a model, with exactly what you gain and which gains are factory-only. Engine_Rules: how the engine/LLM must use the data.
A6: Test_Cases: 6 buyer profiles run through the logic as a sanity check. Range-led ranking puts independently tested range ahead of maker claims.
A10: What each tab is for
A11: Variants: one line per variant (trim + battery + pricing type). Core numbers only.
A12: Features: one line per variant per feature. This is where descriptions go. Never make a new tab per variant.
A13: Sources: one line per receipt. Every value in Variants and Features points to a source_id here.
A14: Open_Questions: conflicts and gaps. When two sources disagree, log both here and leave the main cell blank.
A15: Feature_List: the agreed feature names. Use exactly these names in the Features tab so the data stays comparable.
... A35: Progress
A36: Variants in sheet | B36: =COUNTA(Variants!A2:A200) -> 87
A37: Pending | B37: =COUNTIF(Variants!N2:N200,"pending") -> 2
A38: Verified | B38: =COUNTIF(Variants!N2:N200,"verified") -> 65
A39: Corroborated | B39: =COUNTIF(Variants!N2:N200,"corroborated") -> 20
A40: Conflicting | B40: =COUNTIF(Variants!N2:N200,"conflicting") -> 0
A41: Price mismatches found | B41: =COUNTIF(Variants!R2:R200,"MISMATCH") -> 0

Sheet Assumptions
A1: Assumption | B1: Value | C1: Unit | D1: Why this default / source
A2: Home electricity tariff | B2: 8 | C2: ₹/kWh | D2: Typical Delhi residential slab; change for your city/DISCOM
A3: Public DC fast-charging tariff | B3: 22 | C3: ₹/kWh | D3: Typical Indian public DC rate (Tata Power, Statiq, ChargeZone range ~₹18-25); verify locally
A4: Share of charging done on public DC | B4: 0.1 | C4: fraction | D4: Most private owners charge at home
A5: Daily driving | B5: 40 | C5: km/day | D5: Change to buyer's actual use
A6: Ownership period | B6: 5 | C6: years | D6: Typical first-owner horizon
A7: Annual electricity price increase | B7: 0 | C7: fraction | D7: Kept 0 for simplicity; not yet used in formulas
A9: Edit the yellow cells. Engine_Variants running-cost and 5-year cost columns recalculate from these.
A10: 5-year cost INCLUDES: ex-showroom price + home wall charger (if not included) + electricity.
A11: EXCLUDES: registration, insurance, service, tyres, financing, resale value, discounts. Not a full TCO.

Sheet Engine_Variants
A1: variant_key | B1: sheet_id | C1: brand | D1: model | E1: body_type | F1: variant | G1: pricing_type | H1: price_inr | I1: price_status | J1: battery_kwh | K1: drive | L1: seats | M1: seat_options | N1: range_claimed_km | O1: range_standard | P1: range_maker_realworld_km | Q1: range_tested_km | R1: tested_vs_claim_pct | S1: efficiency_km_per_kwh | T1: efficiency_basis | U1: running_cost_inr_per_km | V1: energy_cost_period_inr | W1: charger_included | X1: charger_cost_inr | Y1: charger_basis | Z1: cost_to_own_period_inr | AA1: boot_l | AB1: ground_clearance_mm | AC1: battery_clearance_mm | AD1: airbags | AE1: esp | AF1: adas | AG1: camera | AH1: sunroof | AI1: ventilated_front | AJ1: adaptive_suspension | AK1: dc_max_kw | AL1: dc_avg_kw_est | AM1: minutes_dc_per_100km | AN1: ac_full_hours_7kw | AO1: onboard_ac_kw | AP1: battery_warranty | AQ1: ncap_status | AR1: ncap_adult_32 | AS1: ncap_child_49 | AT1: terrain_modes | AU1: wading_mm | AV1: watch_outs
A2: MAHINDRA-BE6SPORTEQ-ONE-59 | B2: V001 | C2: Mahindra | D2: BE 6 SPORTEQ | E2: SUV | F2: One 59 kWh | G2: battery included | H2: 1945000 | I2: verified | J2: 59 | K2: RWD | L2: 5 | M2: 5 | N2: 573 | O2: MIDC Part 1 + Part 2 | P2: 400 | S2: 6.78 | T2: Maker real-world claim (estimate) | U2: =IF(S2="","",((1-Assumptions!$B$4)*Assumptions!$B$2+Assumptions!$B$4*Assumptions!$B$3)/S2) -> 1.3864307 | V2: =IF(U2="","",U2*Assumptions!$B$5*365*Assumptions!$B$6) -> 101209.44 | W2: No | X2: 60000 | Y2: 7.2 kW wall box ₹60,000 (Mahindra XEV 9e/9S pages); BE 6 price assumed same | Z2: =IF(OR(G2<>"battery included",H2="",V2=""),"",H2+X2+V2) -> 2106209.4 | AA2: 455 | AB2: 207 | AC2: 222 | AD2: 6 | AE2: Yes | AF2: None | AG2: Rear camera | AH2: None | AI2: No | AJ2: No | AK2: 140 | AL2: 106.2 | AM2: =IF(OR(S2="",AL2=""),"",100/S2/AL2*60) -> 8.3329167 | AN2: 8.7 | AO2: 11 | AP2: Lifetime (1st owner) | AQ2: Rated, coverage unconfirmed | AR2: 31.97 | AS2: 45 | AV2: Crash rating may not cover this version; Wall charger not in price (~₹60,000)
A3: MAHINDRA-BE6SPORTEQ-TWO-59 | B3: V003 | C3: Mahindra | D3: BE 6 SPORTEQ | E3: SUV | F3: Two 59 kWh | G3: battery included | H3: 2095000 | I3: corroborated | J3: 59 | K3: RWD | L3: 5 | M3: 5 | N3: 573 | O3: MIDC Part 1 + Part 2 | P3: 400 | S3: 6.78 | T3: Maker real-world claim (estimate) | U3: =IF(S3="","",((1-Assumptions!$B$4)*Assumptions!$B$2+Assumptions!$B$4*Assumptions!$B$3)/S3) -> 1.3864307 | V3: =IF(U3="","",U3*Assumptions!$B$5*365*Assumptions!$B$6) -> 101209.44 | W3: No | X3: 60000 | Y3: 7.2 kW wall box ₹60,000 (Mahindra XEV 9e/9S pages); BE 6 price assumed same | Z3: =IF(OR(G3<>"battery included",H3="",V3=""),"",H3+X3+V3) -> 2256209.4 | AA3: 455 | AB3: 207 | AC3: 222 | AD3: 6 | AE3: Yes | AF3: None | AG3: 540° | AH3: None | AI3: No | AJ3: No | AK3: 140 | AL3: 106.2 | AM3: =IF(OR(S3="",AL3=""),"",100/S3/AL3*60) -> 8.3329167 | AN3: 8.7 | AO3: 11 | AP3: Lifetime (1st owner) | AQ3: Rated, coverage unconfirmed | AR3: 31.97 | AS3: 45 | AV3: Crash rating may not cover this version; Wall charger not in price (~₹60,000); Price corroborated, confirm before buying
A4: MAHINDRA-BE6SPORTEQ-THREE-59 | B4: V005 | C4: Mahindra | D4: BE 6 SPORTEQ | E4: SUV | F4: Three 59 kWh | G4: battery included | H4: 2195000 | I4: corroborated | J4: 59 | K4: RWD | L4: 5 | M4: 5 | N4: 573 | O4: MIDC Part 1 + Part 2 | P4: 400 | S4: 6.78 | T4: Maker real-world claim (estimate) | U4: =IF(S4="","",((1-Assumptions!$B$4)*Assumptions!$B$2+Assumptions!$B$4*Assumptions!$B$3)/S4) -> 1.3864307 | V4: =IF(U4="","",U4*Assumptions!$B$5*365*Assumptions!$B$6) -> 101209.44 | W4: No | X4: 60000 | Y4: 7.2 kW wall box ₹60,000 (Mahindra XEV 9e/9S pages); BE 6 price assumed same | Z4: =IF(OR(G4<>"battery included",H4="",V4=""),"",H4+X4+V4) -> 2356209.4 | AA4: 455 | AB4: 207 | AC4: 222 | AD4: 6 | AE4: Yes | AF4: None | AG4: 540° | AH4: Panoramic | AI4: Yes | AJ4: No | AK4: 140 | AL4: 106.2 | AM4: =IF(OR(S4="",AL4=""),"",100/S4/AL4*60) -> 8.3329167 | AN4: 8.7 | AO4: 11 | AP4: Lifetime (1st owner) | AQ4: Rated, coverage unconfirmed | AR4: 31.97 | AS4: 45 | AV4: Crash rating may not cover this version; Wall charger not in price (~₹60,000); Price corroborated, confirm before buying
A5: MAHINDRA-BE6SPORTEQ-THREE-70 | B5: V007 | C5: Mahindra | D5: BE 6 SPORTEQ | E5: SUV | F5: Three 70 kWh | G5: battery included | H5: 2295000 | I5: corroborated | J5: 70 | K5: RWD | L5: 5 | M5: 5 | N5: 651 | O5: MIDC Part 1 + Part 2 | P5: 450 | S5: 6.43 | T5: Maker real-world claim (estimate) | U5: =IF(S5="","",((1-Assumptions!$B$4)*Assumptions!$B$2+Assumptions!$B$4*Assumptions!$B$3)/S5) -> 1.4618974 | V5: =IF(U5="","",U5*Assumptions!$B$5*365*Assumptions!$B$6) -> 106718.51 | W5: No | X5: 60000 | Y5: 7.2 kW wall box ₹60,000 (Mahindra XEV 9e/9S pages); BE 6 price assumed same | Z5: =IF(OR(G5<>"battery included",H5="",V5=""),"",H5+X5+V5) -> 2461718.5 | AA5: 455 | AB5: 207 | AC5: 222 | AD5: 6 | AE5: Yes | AF5: None | AG5: 540° | AH5: Panoramic | AI5: Yes | AJ5: No | AK5: 160 | AL5: 126 | AM5: =IF(OR(S5="",AL5=""),"",100/S5/AL5*60) -> 7.4057617 | AN5: 10.2 | AO5: 11 | AP5: Lifetime (1st owner) | AQ5: Rated, coverage unconfirmed | AR5: 31.97 | AS5: 45 | AV5: Crash rating may not cover this version; Wall charger not in price (~₹60,000); Price corroborated, confirm before buying
A6: MAHINDRA-BE6SPORTEQ-THREEPLUS-70 | B6: V009 | C6: Mahindra | D6: BE 6 SPORTEQ | E6: SUV | F6: Three+ 70 kWh | G6: battery included | H6: 2395000 | I6: corroborated | J6: 70 | K6: RWD | L6: 5 | M6: 5 | N6: 651 | O6: MIDC Part 1 + Part 2 | P6: 450 | S6: 6.43 | T6: Maker real-world claim (estimate) | U6: =IF(S6="","",((1-Assumptions!$B$4)*Assumptions!$B$2+Assumptions!$B$4*Assumptions!$B$3)/S6) -> 1.4618974 | V6: =IF(U6="","",U6*Assumptions!$B$5*365*Assumptions!$B$6) -> 106718.51 | W6: No | X6: 60000 | Y6: 7.2 kW wall box ₹60,000 (Mahindra XEV 9e/9S pages); BE 6 price assumed same | Z6: =IF(OR(G6<>"battery included",H6="",V6=""),"",H6+X6+V6) -> 2561718.5 | AA6: 455 | AB6: 207 | AC6: 222 | AD6: 6 | AE6: Yes | AF6: L2 | AG6: 540° | AH6: Panoramic | AI6: Yes | AJ6: No | AK6: 160 | AL6: 126 | AM6: =IF(OR(S6="",AL6=""),"",100/S6/AL6*60) -> 7.4057617 | AN6: 10.2 | AO6: 11 | AP6: Lifetime (1st owner) | AQ6: Rated, coverage unconfirmed | AR6: 31.97 | AS6: 45 | AV6: Crash rating may not cover this version; Wall charger not in price (~₹60,000); Price corroborated, confirm before buying
A7: MAHINDRA-BE6SPORTEQ-FE-79 | B7: V013 | C7: Mahindra | D7: BE 6 SPORTEQ | E7: SUV | F7: FE 79 kWh | G7: battery included | H7: 2445000 | I7: corroborated | J7: 79 | K7: RWD | L7: 5 | M7: 5 | N7: 708 | O7: MIDC Part 1 + Part 2 | P7: 500 | Q7: 449 | R7: 63 | S7: 5.68 | T7: Independent test | U7: =IF(S7="","",((1-Assumptions!$B$4)*Assumptions!$B$2+Assumptions!$B$4*Assumptions!$B$3)/S7) -> 1.6549296 | V7: =IF(U7="","",U7*Assumptions!$B$5*365*Assumptions!$B$6) -> 120809.86 | W7: No | X7: 60000 | Y7: 7.2 kW wall box ₹60,000 (Mahindra XEV 9e/9S pages); BE 6 price assumed same | Z7: =IF(OR(G7<>"battery included",H7="",V7=""),"",H7+X7+V7) -> 2625809.9 | AA7: 455 | AB7: 207 | AC7: 222 | AD7: 6 | AE7: Yes | AF7: None | AG7: 540° | AH7: Panoramic | AI7: No | AJ7: Yes | AK7: 180 | AL7: 142.2 | AM7: =IF(OR(S7="",AL7=""),"",100/S7/AL7*60) -> 7.4285375 | AN7: 11.7 | AO7: 11 | AP7: Lifetime (1st owner) | AQ7: Rated, coverage unconfirmed | AR7: 31.97 | AS7: 45 | AV7: Crash rating may not cover this version; Tested range only 63% of claim; Wall charger not in price (~₹60,000); Price corroborated, confirm before buying
A8: MAHINDRA-BE6SPORTEQ-THREEPLUS-79 | B8: V011 | C8: Mahindra | D8: BE 6 SPORTEQ | E8: SUV | F8: Three+ 79 kWh | G8: battery included | H8: 2495000 | I8: corroborated | J8: 79 | K8: RWD | L8: 5 | M8: 5 | N8: 708 | O8: MIDC Part 1 + Part 2 | P8: 500 | Q8: 449 | R8: 63 | S8: 5.68 | T8: Independent test | U8: =IF(S8="","",((1-Assumptions!$B$4)*Assumptions!$B$2+Assumptions!$B$4*Assumptions!$B$3)/S8) -> 1.6549296 | V8: =IF(U8="","",U8*Assumptions!$B$5*365*Assumptions!$B$6) -> 120809.86 | W8: No | X8: 60000 | Y8: 7.2 kW wall box ₹60,000 (Mahindra XEV 9e/9S pages); BE 6 price assumed same | Z8: =IF(OR(G8<>"battery included",H8="",V8=""),"",H8+X8+V8) -> 2675809.9 | AA8: 455 | AB8: 207 | AC8: 222 | AD8: 6 | AE8: Yes | AF8: L2 | AG8: 540° | AH8: Panoramic | AI8: Yes | AJ8: No | AK8: 180 | AL8: 142.2 | AM8: =IF(OR(S8="",AL8=""),"",100/S8/AL8*60) -> 7.4285375 | AN8: 11.7 | AO8: 11 | AP8: Lifetime (1st owner) | AQ8: Rated, coverage unconfirmed | AR8: 31.97 | AS8: 45 | AV8: Crash rating may not cover this version; Tested range only 63% of claim; Wall charger not in price (~₹60,000); Price corroborated, confirm before buying
A9: MAHINDRA-BE6SPORTEQ-FOUR-79 | B9: V015 | C9: Mahindra | D9: BE 6 SPORTEQ | E9: SUV | F9: Four 79 kWh | G9: battery included | H9: 2695000 | I9: corroborated | J9: 79 | K9: RWD | L9: 5 | M9: 5 | N9: 708 | O9: MIDC Part 1 + Part 2 | P9: 500 | Q9: 449 | R9: 63 | S9: 5.68 | T9: Independent test | U9: =IF(S9="","",((1-Assumptions!$B$4)*Assumptions!$B$2+Assumptions!$B$4*Assumptions!$B$3)/S9) -> 1.6549296 | V9: =IF(U9="","",U9*Assumptions!$B$5*365*Assumptions!$B$6) -> 120809.86 | W9: No | X9: 60000 | Y9: 7.2 kW wall box ₹60,000 (Mahindra XEV 9e/9S pages); BE 6 price assumed same | Z9: =IF(OR(G9<>"battery included",H9="",V9=""),"",H9+X9+V9) -> 2875809.9 | AA9: 455 | AB9: 207 | AC9: 222 | AD9: 6 | AE9: Yes | AF9: L2+ | AG9: 540° | AH9: Panoramic | AI9: Yes | AJ9: Yes | AK9: 180 | AL9: 142.2 | AM9: =IF(OR(S9="",AL9=""),"",100/S9/AL9*60) -> 7.4285375 | AN9: 11.7 | AO9: 11 | AP9: Lifetime (1st owner) | AQ9: Rated, coverage unconfirmed | AR9: 31.97 | AS9: 45 | AV9: Crash rating may not cover this version; Tested range only 63% of claim; Wall charger not in price (~₹60,000); Price corroborated, confirm before buying
A10: MAHINDRA-BE6SPORTEQ-FEFOUR-79 | B10: V017 | C10: Mahindra | D10: BE 6 SPORTEQ | E10: SUV | F10: FE Four 79 kWh | G10: battery included | H10: 2695000 | I10: corroborated | J10: 79 | K10: RWD | L10: 5 | M10: 5 | N10: 708 | O10: MIDC Part 1 + Part 2 | P10: 500 | Q10: 449 | R10: 63 | S10: 5.68 | T10: Independent test | U10: =IF(S10="","",((1-Assumptions!$B$4)*Assumptions!$B$2+Assumptions!$B$4*Assumptions!$B$3)/S10) -> 1.6549296 | V10: =IF(U10="","",U10*Assumptions!$B$5*365*Assumptions!$B$6) -> 120809.86 | W10: No | X10: 60000 | Y10: 7.2 kW wall box ₹60,000 (Mahindra XEV 9e/9S pages); BE 6 price assumed same | Z10: =IF(OR(G10<>"battery included",H10="",V10=""),"",H10+X10+V10) -> 2875809.9 | AA10: 455 | AB10: 207 | AC10: 222 | AD10: 6 | AE10: Yes | AF10: L2+ | AG10: 540° | AH10: Panoramic | AI10: Not stated | AJ10: Yes | AK10: 180 | AL10: 142.2 | AM10: =IF(OR(S10="",AL10=""),"",100/S10/AL10*60) -> 7.4285375 | AN10: 11.7 | AO10: 11 | AP10: Lifetime (1st owner) | AQ10: Rated, coverage unconfirmed | AR10: 31.97 | AS10: 45 | AV10: Crash rating may not cover this version; Tested range only 63% of claim; Wall charger not in price (~₹60,000); Price corroborated, confirm before buying
A11: MAHINDRA-BE6SPORTEQ-LAUNCHEDITION-79 | B11: V019 | C11: Mahindra | D11: BE 6 SPORTEQ | E11: SUV | F11: Launch Edition 79 kWh | G11: battery included | H11: 2695000 | I11: corroborated | J11: 79 | K11: RWD | L11: 5 | M11: 5 | N11: 708 | O11: MIDC Part 1 + Part 2 | P11: 500 | Q11: 449 | R11: 63 | S11: 5.68 | T11: Independent test | U11: =IF(S11="","",((1-Assumptions!$B$4)*Assumptions!$B$2+Assumptions!$B$4*Assumptions!$B$3)/S11) -> 1.6549296 | V11: =IF(U11="","",U11*Assumptions!$B$5*365*Assumptions!$B$6) -> 120809.86 | W11: No | X11: 60000 | Y11: 7.2 kW wall box ₹60,000 (Mahindra XEV 9e/9S pages); BE 6 price assumed same | Z11: =IF(OR(G11<>"battery included",H11="",V11=""),"",H11+X11+V11) -> 2875809.9 | AA11: 455 | AB11: 207 | AC11: 222 | AD11: 6 | AE11: Yes | AF11: L2+ | AG11: 540° | AH11: Panoramic | AI11: Yes | AJ11: Yes | AK11: 180 | AL11: 142.2 | AM11: =IF(OR(S11="",AL11=""),"",100/S11/AL11*60) -> 7.4285375 | AN11: 11.7 | AO11: 11 | AP11: Lifetime (1st owner) | AQ11: Rated, coverage unconfirmed | AR11: 31.97 | AS11: 45 | AV11: Crash rating may not cover this version; Tested range only 63% of claim; Wall charger not in price (~₹60,000); Price corroborated, confirm before buying
A12: MAHINDRA-BE6SPORTEQ-ONE-59-BAAS | B12: V002 | C12: Mahindra | D12: BE 6 SPORTEQ | E12: SUV | F12: One 59 kWh BaaS | G12: BaaS | H12: 1145000 | I12: verified | J12: 59 | K12: RWD | L12: 5 | M12: 5 | N12: 573 | O12: MIDC Part 1 + Part 2 | P12: 400 | S12: 6.78 | T12: Maker real-world claim (estimate) | U12: =IF(S12="","",((1-Assumptions!$B$4)*Assumptions!$B$2+Assumptions!$B$4*Assumptions!$B$3)/S12) -> 1.3864307 | V12: =IF(U12="","",U12*Assumptions!$B$5*365*Assumptions!$B$6) -> 101209.44 | W12: No | X12: 60000 | Y12: 7.2 kW wall box ₹60,000 (Mahindra XEV 9e/9S pages); BE 6 price assumed same | Z12: =IF(OR(G12<>"battery included",H12="",V12=""),"",H12+X12+V12) | AA12: 455 | AB12: 207 | AC12: 222 | AD12: 6 | AE12: Yes | AF12: None | AG12: Rear camera | AH12: None | AI12: No | AJ12: No | AK12: 140 | AL12: 106.2 | AM12: =IF(OR(S12="",AL12=""),"",100/S12/AL12*60) -> 8.3329167 | AN12: 8.7 | AO12: 11 | AP12: Lifetime (1st owner) | AQ12: Rated, coverage unconfirmed | AR12: 31.97 | AS12: 45 | AV12: Crash rating may not cover this version; BaaS: battery paid via separate loan (up to 8 yrs); not pay-per-km
A13: MAHINDRA-BE6SPORTEQ-TWO-59-BAAS | B13: V004 | C13: Mahindra | D13: BE 6 SPORTEQ | E13: SUV | F13: Two 59 kWh BaaS | G13: BaaS | H13: 1295000 | I13: verified | J13: 59 | K13: RWD | L13: 5 | M13: 5 | N13: 573 | O13: MIDC Part 1 + Part 2 | P13: 400 | S13: 6.78 | T13: Maker real-world claim (estimate) | U13: =IF(S13="","",((1-Assumptions!$B$4)*Assumptions!$B$2+Assumptions!$B$4*Assumptions!$B$3)/S13) -> 1.3864307 | V13: =IF(U13="","",U13*Assumptions!$B$5*365*Assumptions!$B$6) -> 101209.44 | W13: No | X13: 60000 | Y13: 7.2 kW wall box ₹60,000 (Mahindra XEV 9e/9S pages); BE 6 price assumed same | Z13: =IF(OR(G13<>"battery included",H13="",V13=""),"",H13+X13+V13) | AA13: 455 | AB13: 207 | AC13: 222 | AD13: 6 | AE13: Yes | AF13: None | AG13: 540° | AH13: None | AI13: No | AJ13: No | AK13: 140 | AL13: 106.2 | AM13: =IF(OR(S13="",AL13=""),"",100/S13/AL13*60) -> 8.3329167 | AN13: 8.7 | AO13: 11 | AP13: Lifetime (1st owner) | AQ13: Rated, coverage unconfirmed | AR13: 31.97 | AS13: 45 | AV13: Crash rating may not cover this version; BaaS: battery paid via separate loan (up to 8 yrs); not pay-per-km
A14: MAHINDRA-BE6SPORTEQ-THREE-59-BAAS | B14: V006 | C14: Mahindra | D14: BE 6 SPORTEQ | E14: SUV | F14: Three 59 kWh BaaS | G14: BaaS | H14: 1395000 | I14: verified | J14: 59 | K14: RWD | L14: 5 | M14: 5 | N14: 573 | O14: MIDC Part 1 + Part 2 | P14: 400 | S14: 6.78 | T14: Maker real-world claim (estimate) | U14: =IF(S14="","",((1-Assumptions!$B$4)*Assumptions!$B$2+Assumptions!$B$4*Assumptions!$B$3)/S14) -> 1.3864307 | V14: =IF(U14="","",U14*Assumptions!$B$5*365*Assumptions!$B$6) -> 101209.44 | W14: No | X14: 60000 | Y14: 7.2 kW wall box ₹60,000 (Mahindra XEV 9e/9S pages); BE 6 price assumed same | Z14: =IF(OR(G14<>"battery included",H14="",V14=""),"",H14+X14+V14) | AA14: 455 | AB14: 207 | AC14: 222 | AD14: 6 | AE14: Yes | AF14: None | AG14: 540° | AH14: Panoramic | AI14: Yes | AJ14: No | AK14: 140 | AL14: 106.2 | AM14: =IF(OR(S14="",AL14=""),"",100/S14/AL14*60) -> 8.3329167 | AN14: 8.7 | AO14: 11 | AP14: Lifetime (1st owner) | AQ14: Rated, coverage unconfirmed | AR14: 31.97 | AS14: 45 | AV14: Crash rating may not cover this version; BaaS: battery paid via separate loan (up to 8 yrs); not pay-per-km
A15: MAHINDRA-BE6SPORTEQ-THREE-70-BAAS | B15: V008 | C15: Mahindra | D15: BE 6 SPORTEQ | E15: SUV | F15: Three 70 kWh BaaS | G15: BaaS | H15: 1395000 | I15: verified | J15: 70 | K15: RWD | L15: 5 | M15: 5 | N15: 651 | O15: MIDC Part 1 + Part 2 | P15: 450 | S15: 6.43 | T15: Maker real-world claim (estimate) | U15: =IF(S15="","",((1-Assumptions!$B$4)*Assumptions!$B$2+Assumptions!$B$4*Assumptions!$B$3)/S15) -> 1.4618974 | V15: =IF(U15="","",U15*Assumptions!$B$5*365*Assumptions!$B$6) -> 106718.51 | W15: No | X15: 60000 | Y15: 7.2 kW wall box ₹60,000 (Mahindra XEV 9e/9S pages); BE 6 price assumed same | Z15: =IF(OR(G15<>"battery included",H15="",V15=""),"",H15+X15+V15) | AA15: 455 | AB15: 207 | AC15: 222 | AD15: 6 | AE15: Yes | AF15: None | AG15: 540° | AH15: Panoramic | AI15: Yes | AJ15: No | AK15: 160 | AL15: 126 | AM15: =IF(OR(S15="",AL15=""),"",100/S15/AL15*60) -> 7.4057617 | AN15: 10.2 | AO15: 11 | AP15: Lifetime (1st owner) | AQ15: Rated, coverage unconfirmed | AR15: 31.97 | AS15: 45 | AV15: Crash rating may not cover this version; BaaS: battery paid via separate loan (up to 8 yrs); not pay-per-km
A16: MAHINDRA-BE6SPORTEQ-FE-79-BAAS | B16: V014 | C16: Mahindra | D16: BE 6 SPORTEQ | E16: SUV | F16: FE 79 kWh BaaS | G16: BaaS | H16: 1445000 | I16: verified | J16: 79 | K16: RWD | L16: 5 | M16: 5 | N16: 708 | O16: MIDC Part 1 + Part 2 | P16: 500 | Q16: 449 | R16: 63 | S16: 5.68 | T16: Independent test | U16: =IF(S16="","",((1-Assumptions!$B$4)*Assumptions!$B$2+Assumptions!$B$4*Assumptions!$B$3)/S16) -> 1.6549296 | V16: =IF(U16="","",U16*Assumptions!$B$5*365*Assumptions!$B$6) -> 120809.86 | W16: No | X16: 60000 | Y16: 7.2 kW wall box ₹60,000 (Mahindra XEV 9e/9S pages); BE 6 price assumed same | Z16: =IF(OR(G16<>"battery included",H16="",V16=""),"",H16+X16+V16) | AA16: 455 | AB16: 207 | AC16: 222 | AD16: 6 | AE16: Yes | AF16: None | AG16: 540° | AH16: Panoramic | AI16: No | AJ16: Yes | AK16: 180 | AL16: 142.2 | AM16: =IF(OR(S16="",AL16=""),"",100/S16/AL16*60) -> 7.4285375 | AN16: 11.7 | AO16: 11 | AP16: Lifetime (1st owner) | AQ16: Rated, coverage unconfirmed | AR16: 31.97 | AS16: 45 | AV16: Crash rating may not cover this version; Tested range only 63% of claim; BaaS: battery paid via separate loan (up to 8 yrs); not pay-per-km
A17: MAHINDRA-BE6SPORTEQ-THREEPLUS-70-BAAS | B17: V010 | C17: Mahindra | D17: BE 6 SPORTEQ | E17: SUV | F17: Three+ 70 kWh BaaS | G17: BaaS | H17: 1495000 | I17: verified | J17: 70 | K17: RWD | L17: 5 | M17: 5 | N17: 651 | O17: MIDC Part 1 + Part 2 | P17: 450 | S17: 6.43 | T17: Maker real-world claim (estimate) | U17: =IF(S17="","",((1-Assumptions!$B$4)*Assumptions!$B$2+Assumptions!$B$4*Assumptions!$B$3)/S17) -> 1.4618974 | V17: =IF(U17="","",U17*Assumptions!$B$5*365*Assumptions!$B$6) -> 106718.51 | W17: No | X17: 60000 | Y17: 7.2 kW wall box ₹60,000 (Mahindra XEV 9e/9S pages); BE 6 price assumed same | Z17: =IF(OR(G17<>"battery included",H17="",V17=""),"",H17+X17+V17) | AA17: 455 | AB17: 207 | AC17: 222 | AD17: 6 | AE17: Yes | AF17: L2 | AG17: 540° | AH17: Panoramic | AI17: Yes | AJ17: No | AK17: 160 | AL17: 126 | AM17: =IF(OR(S17="",AL17=""),"",100/S17/AL17*60) -> 7.4057617 | AN17: 10.2 | AO17: 11 | AP17: Lifetime (1st owner) | AQ17: Rated, coverage unconfirmed | AR17: 31.97 | AS17: 45 | AV17: Crash rating may not cover this version; BaaS: battery paid via separate loan (up to 8 yrs); not pay-per-km
A18: MAHINDRA-BE6SPORTEQ-THREEPLUS-79-BAAS | B18: V012 | C18: Mahindra | D18: BE 6 SPORTEQ | E18: SUV | F18: Three+ 79 kWh BaaS | G18: BaaS | H18: 1495000 | I18: verified | J18: 79 | K18: RWD | L18: 5 | M18: 5 | N18: 708 | O18: MIDC Part 1 + Part 2 | P18: 500 | Q18: 449 | R18: 63 | S18: 5.68 | T18: Independent test | U18: =IF(S18="","",((1-Assumptions!$B$4)*Assumptions!$B$2+Assumptions!$B$4*Assumptions!$B$3)/S18) -> 1.6549296 | V18: =IF(U18="","",U18*Assumptions!$B$5*365*Assumptions!$B$6) -> 120809.86 | W18: No | X18: 60000 | Y18: 7.2 kW wall box ₹60,000 (Mahindra XEV 9e/9S pages); BE 6 price assumed same | Z18: =IF(OR(G18<>"battery included",H18="",V18=""),"",H18+X18+V18) | AA18: 455 | AB18: 207 | AC18: 222 | AD18: 6 | AE18: Yes | AF18: L2 | AG18: 540° | AH18: Panoramic | AI18: Yes | AJ18: No | AK18: 180 | AL18: 142.2 | AM18: =IF(OR(S18="",AL18=""),"",100/S18/AL18*60) -> 7.4285375 | AN18: 11.7 | AO18: 11 | AP18: Lifetime (1st owner) | AQ18: Rated, coverage unconfirmed | AR18: 31.97 | AS18: 45 | AV18: Crash rating may not cover this version; Tested range only 63% of claim; BaaS: battery paid via separate loan (up to 8 yrs); not pay-per-km
A19: MAHINDRA-BE6SPORTEQ-FOUR-79-BAAS | B19: V016 | C19: Mahindra | D19: BE 6 SPORTEQ | E19: SUV | F19: Four 79 kWh BaaS | G19: BaaS | H19: 1695000 | I19: verified | J19: 79 | K19: RWD | L19: 5 | M19: 5 | N19: 708 | O19: MIDC Part 1 + Part 2 | P19: 500 | Q19: 449 | R19: 63 | S19: 5.68 | T19: Independent test | U19: =IF(S19="","",((1-Assumptions!$B$4)*Assumptions!$B$2+Assumptions!$B$4*Assumptions!$B$3)/S19) -> 1.6549296 | V19: =IF(U19="","",U19*Assumptions!$B$5*365*Assumptions!$B$6) -> 120809.86 | W19: No | X19: 60000 | Y19: 7.2 kW wall box ₹60,000 (Mahindra XEV 9e/9S pages); BE 6 price assumed same | Z19: =IF(OR(G19<>"battery included",H19="",V19=""),"",H19+X19+V19) | AA19: 455 | AB19: 207 | AC19: 222 | AD19: 6 | AE19: Yes | AF19: L2+ | AG19: 540° | AH19: Panoramic | AI19: Yes | AJ19: Yes | AK19: 180 | AL19: 142.2 | AM19: =IF(OR(S19="",AL19=""),"",100/S19/AL19*60) -> 7.4285375 | AN19: 11.7 | AO19: 11 | AP19: Lifetime (1st owner) | AQ19: Rated, coverage unconfirmed | AR19: 31.97 | AS19: 45 | AV19: Crash rating may not cover this version; Tested range only 63% of claim; BaaS: battery paid via separate loan (up to 8 yrs); not pay-per-km
A20: MAHINDRA-BE6SPORTEQ-FEFOUR-79-BAAS | B20: V018 | C20: Mahindra | D20: BE 6 SPORTEQ | E20: SUV | F20: FE Four 79 kWh BaaS | G20: BaaS | H20: 1695000 | I20: verified | J20: 79 | K20: RWD | L20: 5 | M20: 5 | N20: 708 | O20: MIDC Part 1 + Part 2 | P20: 500 | Q20: 449 | R20: 63 | S20: 5.68 | T20: Independent test | U20: =IF(S20="","",((1-Assumptions!$B$4)*Assumptions!$B$2+Assumptions!$B$4*Assumptions!$B$3)/S20) -> 1.6549296 | V20: =IF(U20="","",U20*Assumptions!$B$5*365*Assumptions!$B$6) -> 120809.86 | W20: No | X20: 60000 | Y20: 7.2 kW wall box ₹60,000 (Mahindra XEV 9e/9S pages); BE 6 price assumed same | Z20: =IF(OR(G20<>"battery included",H20="",V20=""),"",H20+X20+V20) | AA20: 455 | AB20: 207 | AC20: 222 | AD20: 6 | AE20: Yes | AF20: L2+ | AG20: 540° | AH20: Panoramic | AI20: Not stated | AJ20: Yes | AK20: 180 | AL20: 142.2 | AM20: =IF(OR(S20="",AL20=""),"",100/S20/AL20*60) -> 7.4285375 | AN20: 11.7 | AO20: 11 | AP20: Lifetime (1st owner) | AQ20: Rated, coverage unconfirmed | AR20: 31.97 | AS20: 45 | AV20: Crash rating may not cover this version; Tested range only 63% of claim; BaaS: battery paid via separate loan (up to 8 yrs); not pay-per-km
A21: MAHINDRA-BE6SPORTEQ-LAUNCHEDITION-79-BAAS | B21: V020 | C21: Mahindra | D21: BE 6 SPORTEQ | E21: SUV | F21: Launch Edition 79 kWh BaaS | G21: BaaS | H21: 1695000 | I21: verified | J21: 79 | K21: RWD | L21: 5 | M21: 5 | N21: 708 | O21: MIDC Part 1 + Part 2 | P21: 500 | Q21: 449 | R21: 63 | S21: 5.68 | T21: Independent test | U21: =IF(S21="","",((1-Assumptions!$B$4)*Assumptions!$B$2+Assumptions!$B$4*Assumptions!$B$3)/S21) -> 1.6549296 | V21: =IF(U21="","",U21*Assumptions!$B$5*365*Assumptions!$B$6) -> 120809.86 | W21: No | X21: 60000 | Y21: 7.2 kW wall box ₹60,000 (Mahindra XEV 9e/9S pages); BE 6 price assumed same | Z21: =IF(OR(G21<>"battery included",H21="",V21=""),"",H21+X21+V21) | AA21: 455 | AB21: 207 | AC21: 222 | AD21: 6 | AE21: Yes | AF21: L2+ | AG21: 540° | AH21: Panoramic | AI21: Yes | AJ21: Yes | AK21: 180 | AL21: 142.2 | AM21: =IF(OR(S21="",AL21=""),"",100/S21/AL21*60) -> 7.4285375 | AN21: 11.7 | AO21: 11 | AP21: Lifetime (1st owner) | AQ21: Rated, coverage unconfirmed | AR21: 31.97 | AS21: 45 | AV21: Crash rating may not cover this version; Tested range only 63% of claim; BaaS: battery paid via separate loan (up to 8 yrs); not pay-per-km
A22: MAHINDRA-XEV9S-PACKONEABOVE-59 | B22: V033 | C22: Mahindra | D22: XEV 9S | E22: SUV | F22: Pack One Above 59 kWh | G22: battery included | H22: 2065000 | I22: corroborated | J22: 59 | K22: RWD | L22: 7 | M22: 7 | N22: 521 | O22: MIDC Part 1 + Part 2 | P22: 400 | S22: 6.78 | T22: Maker real-world claim (estimate) | U22: =IF(S22="","",((1-Assumptions!$B$4)*Assumptions!$B$2+Assumptions!$B$4*Assumptions!$B$3)/S22) -> 1.3864307 | V22: =IF(U22="","",U22*Assumptions!$B$5*365*Assumptions!$B$6) -> 101209.44 | W22: No | X22: 60000 | Y22: 7.2 kW wall box ₹60,000 (Mahindra XEV 9e/9S pages) | Z22: =IF(OR(G22<>"battery included",H22="",V22=""),"",H22+X22+V22) -> 2226209.4 | AA22: 527 | AB22: 205 | AC22: 222 | AD22: 6 | AE22: Yes | AF22: None | AG22: Rear camera | AH22: Openable panoramic | AI22: No | AJ22: No | AK22: 140 | AL22: 106.2 | AM22: =IF(OR(S22="",AL22=""),"",100/S22/AL22*60) -> 8.3329167 | AN22: 8.7 | AO22: 11 | AP22: Lifetime (1st owner) | AQ22: Not tested | AV22: No Bharat NCAP crash test; Wall charger not in price (~₹60,000); Price corroborated, confirm before buying
A23: MAHINDRA-XEV9S-PACKONEABOVE-79 | B23: V035 | C23: Mahindra | D23: XEV 9S | E23: SUV | F23: Pack One Above 79 kWh | G23: battery included | H23: 2265000 | I23: corroborated | J23: 79 | K23: RWD | L23: 7 | M23: 7 | N23: 679 | O23: MIDC Part 1 + Part 2 | P23: 500 | Q23: 478 | R23: 70 | S23: 6.33 | T23: Maker real-world claim (estimate) | U23: =IF(S23="","",((1-Assumptions!$B$4)*Assumptions!$B$2+Assumptions!$B$4*Assumptions!$B$3)/S23) -> 1.4849921 | V23: =IF(U23="","",U23*Assumptions!$B$5*365*Assumptions!$B$6) -> 108404.42 | W23: No | X23: 60000 | Y23: 7.2 kW wall box ₹60,000 (Mahindra XEV 9e/9S pages) | Z23: =IF(OR(G23<>"battery included",H23="",V23=""),"",H23+X23+V23) -> 2433404.4 | AA23: 527 | AB23: 205 | AC23: 222 | AD23: 6 | AE23: Yes | AF23: None | AG23: Rear camera | AH23: Openable panoramic | AI23: No | AJ23: No | AK23: 180 | AL23: 142.2 | AM23: =IF(OR(S23="",AL23=""),"",100/S23/AL23*60) -> 6.6657335 | AN23: 11.7 | AO23: 11 | AP23: Lifetime (1st owner) | AQ23: Not tested | AV23: No Bharat NCAP crash test; Wall charger not in price (~₹60,000); Price corroborated, confirm before buying
A24: MAHINDRA-XEV9S-PACKTWOABOVE-70 | B24: V037 | C24: Mahindra | D24: XEV 9S | E24: SUV | F24: Pack Two Above 70 kWh (7-seater) | G24: battery included | H24: 2505000 | I24: corroborated | J24: 70 | K24: RWD | L24: 7 | M24: 7 | N24: 600 | O24: MIDC Part 1 + Part 2 | P24: 450 | S24: 6.43 | T24: Maker real-world claim (estimate) | U24: =IF(S24="","",((1-Assumptions!$B$4)*Assumptions!$B$2+Assumptions!$B$4*Assumptions!$B$3)/S24) -> 1.4618974 | V24: =IF(U24="","",U24*Assumptions!$B$5*365*Assumptions!$B$6) -> 106718.51 | W24: No | X24: 60000 | Y24: 7.2 kW wall box ₹60,000 (Mahindra XEV 9e/9S pages) | Z24: =IF(OR(G24<>"battery included",H24="",V24=""),"",H24+X24+V24) -> 2671718.5 | AA24: 527 | AB24: 205 | AC24: 222 | AD24: 6 | AE24: Yes | AF24: L2 | AG24: 360° | AH24: Openable panoramic | AI24: Yes | AJ24: No | AK24: 160 | AL24: 126 | AM24: =IF(OR(S24="",AL24=""),"",100/S24/AL24*60) -> 7.4057617 | AN24: 10.2 | AO24: 11 | AP24: Lifetime (1st owner) | AQ24: Not tested | AV24: No Bharat NCAP crash test; Wall charger not in price (~₹60,000); Price corroborated, confirm before buying
A25: MAHINDRA-XEV9S-PACKTWOABOVE-70-6S | B25: V084 | C25: Mahindra | D25: XEV 9S | E25: SUV | F25: Pack Two Above 70 kWh (6-seater) | G25: battery included | H25: 2525000 | I25: corroborated | J25: 70 | K25: RWD | L25: 6 | M25: 6 | N25: 600 | O25: MIDC Part 1 + Part 2 | P25: 450 | S25: 6.43 | T25: Maker real-world claim (estimate) | U25: =IF(S25="","",((1-Assumptions!$B$4)*Assumptions!$B$2+Assumptions!$B$4*Assumptions!$B$3)/S25) -> 1.4618974 | V25: =IF(U25="","",U25*Assumptions!$B$5*365*Assumptions!$B$6) -> 106718.51 | W25: No | X25: 60000 | Y25: 7.2 kW wall box ₹60,000 (Mahindra XEV 9e/9S pages) | Z25: =IF(OR(G25<>"battery included",H25="",V25=""),"",H25+X25+V25) -> 2691718.5 | AA25: 527 | AB25: 205 | AC25: 222 | AD25: 6 | AE25: Yes | AF25: L2 | AG25: 360° | AH25: Openable panoramic | AI25: Yes | AJ25: No | AK25: 160 | AL25: 126 | AM25: =IF(OR(S25="",AL25=""),"",100/S25/AL25*60) -> 7.4057617 | AN25: 10.2 | AO25: 11 | AP25: Lifetime (1st owner) | AQ25: Not tested | AV25: No Bharat NCAP crash test; Wall charger not in price (~₹60,000); Price corroborated, confirm before buying
A26: MAHINDRA-XEV9S-PACKTWOABOVE-79 | B26: V039 | C26: Mahindra | D26: XEV 9S | E26: SUV | F26: Pack Two Above 79 kWh (7-seater) | G26: battery included | H26: 2595000 | I26: corroborated | J26: 79 | K26: RWD | L26: 7 | M26: 7 | N26: 679 | O26: MIDC Part 1 + Part 2 | P26: 500 | Q26: 478 | R26: 70 | S26: 6.33 | T26: Maker real-world claim (estimate) | U26: =IF(S26="","",((1-Assumptions!$B$4)*Assumptions!$B$2+Assumptions!$B$4*Assumptions!$B$3)/S26) -> 1.4849921 | V26: =IF(U26="","",U26*Assumptions!$B$5*365*Assumptions!$B$6) -> 108404.42 | W26: No | X26: 60000 | Y26: 7.2 kW wall box ₹60,000 (Mahindra XEV 9e/9S pages) | Z26: =IF(OR(G26<>"battery included",H26="",V26=""),"",H26+X26+V26) -> 2763404.4 | AA26: 527 | AB26: 205 | AC26: 222 | AD26: 6 | AE26: Yes | AF26: L2 | AG26: 360° | AH26: Openable panoramic | AI26: Yes | AJ26: No | AK26: 180 | AL26: 142.2 | AM26: =IF(OR(S26="",AL26=""),"",100/S26/AL26*60) -> 6.6657335 | AN26: 11.7 | AO26: 11 | AP26: Lifetime (1st owner) | AQ26: Not tested | AV26: No Bharat NCAP crash test; Wall charger not in price (~₹60,000); Price corroborated, confirm before buying
A27: MAHINDRA-XEV9S-PACKTWOABOVE-79-6S | B27: V085 | C27: Mahindra | D27: XEV 9S | E27: SUV | F27: Pack Two Above 79 kWh (6-seater) | G27: battery included | H27: 2615000 | I27: corroborated | J27: 79 | K27: RWD | L27: 6 | M27: 6 | N27: 679 | O27: MIDC Part 1 + Part 2 | P27: 500 | Q27: 478 | R27: 70 | S27: 6.33 | T27: Maker real-world claim (estimate) | U27: =IF(S27="","",((1-Assumptions!$B$4)*Assumptions!$B$2+Assumptions!$B$4*Assumptions!$B$3)/S27) -> 1.4849921 | V27: =IF(U27="","",U27*Assumptions!$B$5*365*Assumptions!$B$6) -> 108404.42 | W27: No | X27: 60000 | Y27: 7.2 kW wall box ₹60,000 (Mahindra XEV 9e/9S pages) | Z27: =IF(OR(G27<>"battery included",H27="",V27=""),"",H27+X27+V27) -> 2783404.4 | AA27: 527 | AB27: 205 | AC27: 222 | AD27: 6 | AE27: Yes | AF27: L2 | AG27: 360° | AH27: Openable panoramic | AI27: Yes | AJ27: No | AK27: 180 | AL27: 142.2 | AM27: =IF(OR(S27="",AL27=""),"",100/S27/AL27*60) -> 6.6657335 | AN27: 11.7 | AO27: 11 | AP27: Lifetime (1st owner) | AQ27: Not tested | AV27: No Bharat NCAP crash test; Wall charger not in price (~₹60,000); Price corroborated, confirm before buying
A28: MAHINDRA-XEV9S-PACKTHREE-79 | B28: V041 | C28: Mahindra | D28: XEV 9S | E28: SUV | F28: Pack Three 79 kWh (7-seater) | G28: battery included | H28: 2785000 | I28: corroborated | J28: 79 | K28: RWD | L28: 7 | M28: 7 | N28: 679 | O28: MIDC Part 1 + Part 2 | P28: 500 | Q28: 478 | R28: 70 | S28: 6.33 | T28: Maker real-world claim (estimate) | U28: =IF(S28="","",((1-Assumptions!$B$4)*Assumptions!$B$2+Assumptions!$B$4*Assumptions!$B$3)/S28) -> 1.4849921 | V28: =IF(U28="","",U28*Assumptions!$B$5*365*Assumptions!$B$6) -> 108404.42 | W28: No | X28: 60000 | Y28: 7.2 kW wall box ₹60,000 (Mahindra XEV 9e/9S pages) | Z28: =IF(OR(G28<>"battery included",H28="",V28=""),"",H28+X28+V28) -> 2953404.4 | AA28: 527 | AB28: 205 | AC28: 222 | AD28: 7 | AE28: Yes | AF28: L2+ | AG28: 360° | AH28: Openable panoramic | AI28: Yes | AJ28: Yes | AK28: 180 | AL28: 142.2 | AM28: =IF(OR(S28="",AL28=""),"",100/S28/AL28*60) -> 6.6657335 | AN28: 11.7 | AO28: 11 | AP28: Lifetime (1st owner) | AQ28: Not tested | AV28: No Bharat NCAP crash test; Wall charger not in price (~₹60,000); Price corroborated, confirm before buying
A29: MAHINDRA-XEV9S-PACKTHREE-79-6S | B29: V086 | C29: Mahindra | D29: XEV 9S | E29: SUV | F29: Pack Three 79 kWh (6-seater) | G29: battery included | H29: 2805000 | I29: corroborated | J29: 79 | K29: RWD | L29: 6 | M29: 6 | N29: 679 | O29: MIDC Part 1 + Part 2 | P29: 500 | Q29: 478 | R29: 70 | S29: 6.33 | T29: Maker real-world claim (estimate) | U29: =IF(S29="","",((1-Assumptions!$B$4)*Assumptions!$B$2+Assumptions!$B$4*Assumptions!$B$3)/S29) -> 1.4849921 | V29: =IF(U29="","",U29*Assumptions!$B$5*365*Assumptions!$B$6) -> 108404.42 | W29: No | X29: 60000 | Y29: 7.2 kW wall box ₹60,000 (Mahindra XEV 9e/9S pages) | Z29: =IF(OR(G29<>"battery included",H29="",V29=""),"",H29+X29+V29) -> 2973404.4 | AA29: 527 | AB29: 205 | AC29: 222 | AD29: 7 | AE29: Yes | AF29: L2+ | AG29: 360° | AH29: Openable panoramic | AI29: Yes | AJ29: Yes | AK29: 180 | AL29: 142.2 | AM29: =IF(OR(S29="",AL29=""),"",100/S29/AL29*60) -> 6.6657335 | AN29: 11.7 | AO29: 11 | AP29: Lifetime (1st owner) | AQ29: Not tested | AV29: No Bharat NCAP crash test; Wall charger not in price (~₹60,000); Price corroborated, confirm before buying
A30: MAHINDRA-XEV9S-PACKTHREEABOVE-79 | B30: V087 | C30: Mahindra | D30: XEV 9S | E30: SUV | F30: Pack Three Above 79 kWh (7-seater) | G30: battery included | H30: 2995000 | I30: corroborated | J30: 79 | K30: RWD | L30: 7 | M30: 7 | N30: 679 | O30: MIDC Part 1 + Part 2 | P30: 500 | Q30: 478 | R30: 70 | S30: 6.33 | T30: Maker real-world claim (estimate) | U30: =IF(S30="","",((1-Assumptions!$B$4)*Assumptions!$B$2+Assumptions!$B$4*Assumptions!$B$3)/S30) -> 1.4849921 | V30: =IF(U30="","",U30*Assumptions!$B$5*365*Assumptions!$B$6) -> 108404.42 | W30: No | X30: 60000 | Y30: 7.2 kW wall box ₹60,000 (Mahindra XEV 9e/9S pages) | Z30: =IF(OR(G30<>"battery included",H30="",V30=""),"",H30+X30+V30) -> 3163404.4 | AA30: 527 | AB30: 205 | AC30: 222 | AD30: 7 | AE30: Yes | AF30: L2+ | AG30: 360° | AH30: Openable panoramic | AI30: Yes | AJ30: Yes | AK30: 180 | AL30: 142.2 | AM30: =IF(OR(S30="",AL30=""),"",100/S30/AL30*60) -> 6.6657335 | AN30: 11.7 | AO30: 11 | AP30: Lifetime (1st owner) | AQ30: Not tested | AV30: No Bharat NCAP crash test; Wall charger not in price (~₹60,000); Price corroborated, confirm before buying
A31: MAHINDRA-XEV9S-PACKTHREEABOVE-79-6S | B31: V043 | C31: Mahindra | D31: XEV 9S | E31: SUV | F31: Pack Three Above 79 kWh (6-seater) | G31: battery included | H31: 3015000 | I31: verified | J31: 79 | K31: RWD | L31: 6 | M31: 6 | N31: 679 | O31: MIDC Part 1 + Part 2 | P31: 500 | Q31: 478 | R31: 70 | S31: 6.33 | T31: Maker real-world claim (estimate) | U31: =IF(S31="","",((1-Assumptions!$B$4)*Assumptions!$B$2+Assumptions!$B$4*Assumptions!$B$3)/S31) -> 1.4849921 | V31: =IF(U31="","",U31*Assumptions!$B$5*365*Assumptions!$B$6) -> 108404.42 | W31: No | X31: 60000 | Y31: 7.2 kW wall box ₹60,000 (Mahindra XEV 9e/9S pages) | Z31: =IF(OR(G31<>"battery included",H31="",V31=""),"",H31+X31+V31) -> 3183404.4 | AA31: 527 | AB31: 205 | AC31: 222 | AD31: 7 | AE31: Yes | AF31: L2+ | AG31: 360° | AH31: Openable panoramic | AI31: Yes | AJ31: Yes | AK31: 180 | AL31: 142.2 | AM31: =IF(OR(S31="",AL31=""),"",100/S31/AL31*60) -> 6.6657335 | AN31: 11.7 | AO31: 11 | AP31: Lifetime (1st owner) | AQ31: Not tested | AV31: No Bharat NCAP crash test; Wall charger not in price (~₹60,000)
A32: MAHINDRA-XEV9S-PACKONEABOVE-59-BAAS | B32: V034 | C32: Mahindra | D32: XEV 9S | E32: SUV | F32: Pack One Above 59 kWh BaaS | G32: BaaS | H32: 1265000 | I32: verified | J32: 59 | K32: RWD | L32: 7 | M32: 7 | N32: 521 | O32: MIDC Part 1 + Part 2 | P32: 400 | S32: 6.78 | T32: Maker real-world claim (estimate) | U32: =IF(S32="","",((1-Assumptions!$B$4)*Assumptions!$B$2+Assumptions!$B$4*Assumptions!$B$3)/S32) -> 1.3864307 | V32: =IF(U32="","",U32*Assumptions!$B$5*365*Assumptions!$B$6) -> 101209.44 | W32: No | X32: 60000 | Y32: 7.2 kW wall box ₹60,000 (Mahindra XEV 9e/9S pages) | Z32: =IF(OR(G32<>"battery included",H32="",V32=""),"",H32+X32+V32) | AA32: 527 | AB32: 205 | AC32: 222 | AD32: 6 | AE32: Yes | AF32: None | AG32: Rear camera | AH32: Openable panoramic | AI32: No | AJ32: No | AK32: 140 | AL32: 106.2 | AM32: =IF(OR(S32="",AL32=""),"",100/S32/AL32*60) -> 8.3329167 | AN32: 8.7 | AO32: 11 | AP32: Lifetime (1st owner) | AQ32: Not tested | AV32: No Bharat NCAP crash test; BaaS: battery paid via separate loan (up to 8 yrs); not pay-per-km
A33: MAHINDRA-XEV9S-PACKONEABOVE-79-BAAS | B33: V036 | C33: Mahindra | D33: XEV 9S | E33: SUV | F33: Pack One Above 79 kWh BaaS | G33: BaaS | H33: 1265000 | I33: verified | J33: 79 | K33: RWD | L33: 7 | M33: 7 | N33: 679 | O33: MIDC Part 1 + Part 2 | P33: 500 | Q33: 478 | R33: 70 | S33: 6.33 | T33: Maker real-world claim (estimate) | U33: =IF(S33="","",((1-Assumptions!$B$4)*Assumptions!$B$2+Assumptions!$B$4*Assumptions!$B$3)/S33) -> 1.4849921 | V33: =IF(U33="","",U33*Assumptions!$B$5*365*Assumptions!$B$6) -> 108404.42 | W33: No | X33: 60000 | Y33: 7.2 kW wall box ₹60,000 (Mahindra XEV 9e/9S pages) | Z33: =IF(OR(G33<>"battery included",H33="",V33=""),"",H33+X33+V33) | AA33: 527 | AB33: 205 | AC33: 222 | AD33: 6 | AE33: Yes | AF33: None | AG33: Rear camera | AH33: Openable panoramic | AI33: No | AJ33: No | AK33: 180 | AL33: 142.2 | AM33: =IF(OR(S33="",AL33=""),"",100/S33/AL33*60) -> 6.6657335 | AN33: 11.7 | AO33: 11 | AP33: Lifetime (1st owner) | AQ33: Not tested | AV33: No Bharat NCAP crash test; BaaS: battery paid via separate loan (up to 8 yrs); not pay-per-km
A34: MAHINDRA-XEV9S-PACKTWOABOVE-79-BAAS | B34: V040 | C34: Mahindra | D34: XEV 9S | E34: SUV | F34: Pack Two Above 79 kWh BaaS | G34: BaaS | H34: 1595000 | I34: verified | J34: 79 | K34: RWD | L34: 7 | M34: 6 or 7 | N34: 679 | O34: MIDC Part 1 + Part 2 | P34: 500 | Q34: 478 | R34: 70 | S34: 6.33 | T34: Maker real-world claim (estimate) | U34: =IF(S34="","",((1-Assumptions!$B$4)*Assumptions!$B$2+Assumptions!$B$4*Assumptions!$B$3)/S34) -> 1.4849921 | V34: =IF(U34="","",U34*Assumptions!$B$5*365*Assumptions!$B$6) -> 108404.42 | W34: No | X34: 60000 | Y34: 7.2 kW wall box ₹60,000 (Mahindra XEV 9e/9S pages) | Z34: =IF(OR(G34<>"battery included",H34="",V34=""),"",H34+X34+V34) | AA34: 527 | AB34: 205 | AC34: 222 | AD34: 6 | AE34: Yes | AF34: L2 | AG34: 360° | AH34: Openable panoramic | AI34: Yes | AJ34: No | AK34: 180 | AL34: 142.2 | AM34: =IF(OR(S34="",AL34=""),"",100/S34/AL34*60) -> 6.6657335 | AN34: 11.7 | AO34: 11 | AP34: Lifetime (1st owner) | AQ34: Not tested | AV34: No Bharat NCAP crash test; BaaS: battery paid via separate loan (up to 8 yrs); not pay-per-km
A35: MAHINDRA-XEV9S-PACKTWOABOVE-70-BAAS | B35: V038 | C35: Mahindra | D35: XEV 9S | E35: SUV | F35: Pack Two Above 70 kWh BaaS | G35: BaaS | H35: 1605000 | I35: verified | J35: 70 | K35: RWD | L35: 7 | M35: 6 or 7 | N35: 600 | O35: MIDC Part 1 + Part 2 | P35: 450 | S35: 6.43 | T35: Maker real-world claim (estimate) | U35: =IF(S35="","",((1-Assumptions!$B$4)*Assumptions!$B$2+Assumptions!$B$4*Assumptions!$B$3)/S35) -> 1.4618974 | V35: =IF(U35="","",U35*Assumptions!$B$5*365*Assumptions!$B$6) -> 106718.51 | W35: No | X35: 60000 | Y35: 7.2 kW wall box ₹60,000 (Mahindra XEV 9e/9S pages) | Z35: =IF(OR(G35<>"battery included",H35="",V35=""),"",H35+X35+V35) | AA35: 527 | AB35: 205 | AC35: 222 | AD35: 6 | AE35: Yes | AF35: L2 | AG35: 360° | AH35: Openable panoramic | AI35: Yes | AJ35: No | AK35: 160 | AL35: 126 | AM35: =IF(OR(S35="",AL35=""),"",100/S35/AL35*60) -> 7.4057617 | AN35: 10.2 | AO35: 11 | AP35: Lifetime (1st owner) | AQ35: Not tested | AV35: No Bharat NCAP crash test; BaaS: battery paid via separate loan (up to 8 yrs); not pay-per-km
A36: MAHINDRA-XEV9S-PACKTHREE-79-BAAS | B36: V042 | C36: Mahindra | D36: XEV 9S | E36: SUV | F36: Pack Three 79 kWh BaaS | G36: BaaS | H36: 1785000 | I36: verified | J36: 79 | K36: RWD | L36: 7 | M36: 6 or 7 | N36: 679 | O36: MIDC Part 1 + Part 2 | P36: 500 | Q36: 478 | R36: 70 | S36: 6.33 | T36: Maker real-world claim (estimate) | U36: =IF(S36="","",((1-Assumptions!$B$4)*Assumptions!$B$2+Assumptions!$B$4*Assumptions!$B$3)/S36) -> 1.4849921 | V36: =IF(U36="","",U36*Assumptions!$B$5*365*Assumptions!$B$6) -> 108404.42 | W36: No | X36: 60000 | Y36: 7.2 kW wall box ₹60,000 (Mahindra XEV 9e/9S pages) | Z36: =IF(OR(G36<>"battery included",H36="",V36=""),"",H36+X36+V36) | AA36: 527 | AB36: 205 | AC36: 222 | AD36: 7 | AE36: Yes | AF36: L2+ | AG36: 360° | AH36: Openable panoramic | AI36: Yes | AJ36: Yes | AK36: 180 | AL36: 142.2 | AM36: =IF(OR(S36="",AL36=""),"",100/S36/AL36*60) -> 6.6657335 | AN36: 11.7 | AO36: 11 | AP36: Lifetime (1st owner) | AQ36: Not tested | AV36: No Bharat NCAP crash test; BaaS: battery paid via separate loan (up to 8 yrs); not pay-per-km
A37: MAHINDRA-XEV9S-PACKTHREEABOVE-79-BAAS | B37: V044 | C37: Mahindra | D37: XEV 9S | E37: SUV | F37: Pack Three Above 79 kWh BaaS | G37: BaaS | H37: 1995000 | I37: verified | J37: 79 | K37: RWD | L37: 7 | M37: 6 or 7 | N37: 679 | O37: MIDC Part 1 + Part 2 | P37: 500 | Q37: 478 | R37: 70 | S37: 6.33 | T37: Maker real-world claim (estimate) | U37: =IF(S37="","",((1-Assumptions!$B$4)*Assumptions!$B$2+Assumptions!$B$4*Assumptions!$B$3)/S37) -> 1.4849921 | V37: =IF(U37="","",U37*Assumptions!$B$5*365*Assumptions!$B$6) -> 108404.42 | W37: No | X37: 60000 | Y37: 7.2 kW wall box ₹60,000 (Mahindra XEV 9e/9S pages) | Z37: =IF(OR(G37<>"battery included",H37="",V37=""),"",H37+X37+V37) | AA37: 527 | AB37: 205 | AC37: 222 | AD37: 7 | AE37: Yes | AF37: L2+ | AG37: 360° | AH37: Openable panoramic | AI37: Yes | AJ37: Yes | AK37: 180 | AL37: 142.2 | AM37: =IF(OR(S37="",AL37=""),"",100/S37/AL37*60) -> 6.6657335 | AN37: 11.7 | AO37: 11 | AP37: Lifetime (1st owner) | AQ37: Not tested | AV37: No Bharat NCAP crash test; BaaS: battery paid via separate loan (up to 8 yrs); not pay-per-km
A38: MAHINDRA-XEV9E-PACKONE-59 | B38: V021 | C38: Mahindra | D38: XEV 9e | E38: SUV coupé | F38: Pack One 59 kWh | G38: battery included | H38: 2190000 | I38: verified | J38: 59 | K38: RWD | L38: 5 | M38: 5 | N38: 522 | O38: MIDC Part 1 + Part 2 | P38: 400 | S38: 6.78 | T38: Maker real-world claim (estimate) | U38: =IF(S38="","",((1-Assumptions!$B$4)*Assumptions!$B$2+Assumptions!$B$4*Assumptions!$B$3)/S38) -> 1.3864307 | V38: =IF(U38="","",U38*Assumptions!$B$5*365*Assumptions!$B$6) -> 101209.44 | W38: No | X38: 60000 | Y38: 7.2 kW wall box ₹60,000 (Mahindra XEV 9e/9S pages) | Z38: =IF(OR(G38<>"battery included",H38="",V38=""),"",H38+X38+V38) -> 2351209.4 | AA38: 663 | AB38: 207 | AC38: 218 | AD38: 6 | AE38: Yes | AF38: None | AG38: Rear camera | AH38: Not stated | AI38: No | AJ38: No | AK38: 140 | AL38: 106.2 | AM38: =IF(OR(S38="",AL38=""),"",100/S38/AL38*60) -> 8.3329167 | AN38: 8.7 | AO38: 11 | AP38: Lifetime (1st owner) | AQ38: Rated, applies | AR38: 32 | AS38: 45 | AV38: Wall charger not in price (~₹60,000)
A39: MAHINDRA-XEV9E-PACKTWO-59 | B39: V023 | C39: Mahindra | D39: XEV 9e | E39: SUV coupé | F39: Pack Two 59 kWh | G39: battery included | H39: 2490000 | I39: verified | J39: 59 | K39: RWD | L39: 5 | M39: 5 | N39: 522 | O39: MIDC Part 1 + Part 2 | P39: 400 | S39: 6.78 | T39: Maker real-world claim (estimate) | U39: =IF(S39="","",((1-Assumptions!$B$4)*Assumptions!$B$2+Assumptions!$B$4*Assumptions!$B$3)/S39) -> 1.3864307 | V39: =IF(U39="","",U39*Assumptions!$B$5*365*Assumptions!$B$6) -> 101209.44 | W39: No | X39: 60000 | Y39: 7.2 kW wall box ₹60,000 (Mahindra XEV 9e/9S pages) | Z39: =IF(OR(G39<>"battery included",H39="",V39=""),"",H39+X39+V39) -> 2651209.4 | AA39: 663 | AB39: 207 | AC39: 218 | AD39: 6 | AE39: Yes | AF39: L2 | AG39: Rear camera | AH39: Not stated | AI39: No | AJ39: No | AK39: 140 | AL39: 106.2 | AM39: =IF(OR(S39="",AL39=""),"",100/S39/AL39*60) -> 8.3329167 | AN39: 8.7 | AO39: 11 | AP39: Lifetime (1st owner) | AQ39: Rated, applies | AR39: 32 | AS39: 45 | AV39: Wall charger not in price (~₹60,000)
A40: MAHINDRA-XEV9E-PACKTWO-79 | B40: V025 | C40: Mahindra | D40: XEV 9e | E40: SUV coupé | F40: Pack Two 79 kWh | G40: battery included | H40: 2650000 | I40: corroborated | J40: 79 | K40: RWD | L40: 5 | M40: 5 | N40: 656 | O40: MIDC Part 1 + Part 2 | P40: 500 | Q40: 456 | R40: 70 | S40: 6.33 | T40: Maker real-world claim (estimate) | U40: =IF(S40="","",((1-Assumptions!$B$4)*Assumptions!$B$2+Assumptions!$B$4*Assumptions!$B$3)/S40) -> 1.4849921 | V40: =IF(U40="","",U40*Assumptions!$B$5*365*Assumptions!$B$6) -> 108404.42 | W40: No | X40: 60000 | Y40: 7.2 kW wall box ₹60,000 (Mahindra XEV 9e/9S pages) | Z40: =IF(OR(G40<>"battery included",H40="",V40=""),"",H40+X40+V40) -> 2818404.4 | AA40: 663 | AB40: 207 | AC40: 218 | AD40: 6 | AE40: Yes | AF40: L2 | AG40: Rear camera | AH40: Not stated | AI40: No | AJ40: No | AK40: 180 | AL40: 142.2 | AM40: =IF(OR(S40="",AL40=""),"",100/S40/AL40*60) -> 6.6657335 | AN40: 11.7 | AO40: 11 | AP40: Lifetime (1st owner) | AQ40: Rated, applies | AR40: 32 | AS40: 45 | AV40: Wall charger not in price (~₹60,000); Price corroborated, confirm before buying
A41: MAHINDRA-XEV9E-PACKTHREESELECT-59 | B41: V027 | C41: Mahindra | D41: XEV 9e | E41: SUV coupé | F41: Pack Three Select 59 kWh | G41: battery included | H41: 2790000 | I41: verified | J41: 59 | K41: RWD | L41: 5 | M41: 5 | N41: 522 | O41: MIDC Part 1 + Part 2 | P41: 400 | S41: 6.78 | T41: Maker real-world claim (estimate) | U41: =IF(S41="","",((1-Assumptions!$B$4)*Assumptions!$B$2+Assumptions!$B$4*Assumptions!$B$3)/S41) -> 1.3864307 | V41: =IF(U41="","",U41*Assumptions!$B$5*365*Assumptions!$B$6) -> 101209.44 | W41: No | X41: 60000 | Y41: 7.2 kW wall box ₹60,000 (Mahindra XEV 9e/9S pages) | Z41: =IF(OR(G41<>"battery included",H41="",V41=""),"",H41+X41+V41) -> 2951209.4 | AA41: 663 | AB41: 207 | AC41: 218 | AD41: 7 | AE41: Yes | AF41: L2 | AG41: 360° | AH41: Not stated | AI41: Yes | AJ41: Yes | AK41: 140 | AL41: 106.2 | AM41: =IF(OR(S41="",AL41=""),"",100/S41/AL41*60) -> 8.3329167 | AN41: 8.7 | AO41: 11 | AP41: Lifetime (1st owner) | AQ41: Rated, applies | AR41: 32 | AS41: 45 | AV41: Wall charger not in price (~₹60,000)
A42: MAHINDRA-XEV9E-CINELUXE-79 | B42: V031 | C42: Mahindra | D42: XEV 9e | E42: SUV coupé | F42: Cineluxe 79 kWh | G42: battery included | H42: 2935000 | I42: verified | J42: 79 | K42: RWD | L42: 5 | M42: 5 | N42: 656 | O42: MIDC Part 1 + Part 2 | P42: 500 | Q42: 456 | R42: 70 | S42: 6.33 | T42: Maker real-world claim (estimate) | U42: =IF(S42="","",((1-Assumptions!$B$4)*Assumptions!$B$2+Assumptions!$B$4*Assumptions!$B$3)/S42) -> 1.4849921 | V42: =IF(U42="","",U42*Assumptions!$B$5*365*Assumptions!$B$6) -> 108404.42 | W42: No | X42: 60000 | Y42: 7.2 kW wall box ₹60,000 (Mahindra XEV 9e/9S pages) | Z42: =IF(OR(G42<>"battery included",H42="",V42=""),"",H42+X42+V42) -> 3103404.4 | AC42: 218 | AE42: Not stated | AF42: Not stated | AG42: Not stated | AH42: Not stated | AI42: Not stated | AJ42: Yes | AK42: 180 | AL42: 142.2 | AM42: =IF(OR(S42="",AL42=""),"",100/S42/AL42*60) -> 6.6657335 | AP42: Lifetime (1st owner) | AQ42: Rated, applies | AR42: 32 | AS42: 45 | AV42: ESP not listed; Wall charger not in price (~₹60,000)
A43: MAHINDRA-XEV9E-PACKTHREE-79 | B43: V029 | C43: Mahindra | D43: XEV 9e | E43: SUV coupé | F43: Pack Three 79 kWh | G43: battery included | H43: 3050000 | I43: verified | J43: 79 | K43: RWD | L43: 5 | M43: 5 | N43: 656 | O43: MIDC Part 1 + Part 2 | P43: 500 | Q43: 456 | R43: 70 | S43: 6.33 | T43: Maker real-world claim (estimate) | U43: =IF(S43="","",((1-Assumptions!$B$4)*Assumptions!$B$2+Assumptions!$B$4*Assumptions!$B$3)/S43) -> 1.4849921 | V43: =IF(U43="","",U43*Assumptions!$B$5*365*Assumptions!$B$6) -> 108404.42 | W43: No | X43: 60000 | Y43: 7.2 kW wall box ₹60,000 (Mahindra XEV 9e/9S pages) | Z43: =IF(OR(G43<>"battery included",H43="",V43=""),"",H43+X43+V43) -> 3218404.4 | AA43: 663 | AB43: 207 | AC43: 218 | AD43: 7 | AE43: Yes | AF43: L2+ | AG43: 360° | AH43: Not stated | AI43: Yes | AJ43: Yes | AK43: 180 | AL43: 142.2 | AM43: =IF(OR(S43="",AL43=""),"",100/S43/AL43*60) -> 6.6657335 | AN43: 11.7 | AO43: 11 | AP43: Lifetime (1st owner) | AQ43: Rated, applies | AR43: 32 | AS43: 45 | AV43: Wall charger not in price (~₹60,000)
A44: MAHINDRA-XEV9E-PACKONE-59-BAAS | B44: V022 | C44: Mahindra | D44: XEV 9e | E44: SUV coupé | F44: Pack One 59 kWh BaaS | G44: BaaS | H44: 1390000 | I44: verified | J44: 59 | K44: RWD | L44: 5 | M44: 5 | N44: 522 | O44: MIDC Part 1 + Part 2 | P44: 400 | S44: 6.78 | T44: Maker real-world claim (estimate) | U44: =IF(S44="","",((1-Assumptions!$B$4)*Assumptions!$B$2+Assumptions!$B$4*Assumptions!$B$3)/S44) -> 1.3864307 | V44: =IF(U44="","",U44*Assumptions!$B$5*365*Assumptions!$B$6) -> 101209.44 | W44: No | X44: 60000 | Y44: 7.2 kW wall box ₹60,000 (Mahindra XEV 9e/9S pages) | Z44: =IF(OR(G44<>"battery included",H44="",V44=""),"",H44+X44+V44) | AA44: 663 | AB44: 207 | AC44: 218 | AD44: 6 | AE44: Yes | AF44: None | AG44: Rear camera | AH44: Not stated | AI44: No | AJ44: No | AK44: 140 | AL44: 106.2 | AM44: =IF(OR(S44="",AL44=""),"",100/S44/AL44*60) -> 8.3329167 | AN44: 8.7 | AO44: 11 | AP44: Lifetime (1st owner) | AQ44: Rated, applies | AR44: 32 | AS44: 45 | AV44: BaaS: battery paid via separate loan (up to 8 yrs); not pay-per-km
A45: MAHINDRA-XEV9E-PACKTWO-79-BAAS | B45: V026 | C45: Mahindra | D45: XEV 9e | E45: SUV coupé | F45: Pack Two 79 kWh BaaS | G45: BaaS | H45: 1650000 | I45: verified | J45: 79 | K45: RWD | L45: 5 | M45: 5 | N45: 656 | O45: MIDC Part 1 + Part 2 | P45: 500 | Q45: 456 | R45: 70 | S45: 6.33 | T45: Maker real-world claim (estimate) | U45: =IF(S45="","",((1-Assumptions!$B$4)*Assumptions!$B$2+Assumptions!$B$4*Assumptions!$B$3)/S45) -> 1.4849921 | V45: =IF(U45="","",U45*Assumptions!$B$5*365*Assumptions!$B$6) -> 108404.42 | W45: No | X45: 60000 | Y45: 7.2 kW wall box ₹60,000 (Mahindra XEV 9e/9S pages) | Z45: =IF(OR(G45<>"battery included",H45="",V45=""),"",H45+X45+V45) | AA45: 663 | AB45: 207 | AC45: 218 | AD45: 6 | AE45: Yes | AF45: L2 | AG45: Rear camera | AH45: Not stated | AI45: No | AJ45: No | AK45: 180 | AL45: 142.2 | AM45: =IF(OR(S45="",AL45=""),"",100/S45/AL45*60) -> 6.6657335 | AN45: 11.7 | AO45: 11 | AP45: Lifetime (1st owner) | AQ45: Rated, applies | AR45: 32 | AS45: 45 | AV45: BaaS: battery paid via separate loan (up to 8 yrs); not pay-per-km
A46: MAHINDRA-XEV9E-CINELUXE-79-BAAS | B46: V032 | C46: Mahindra | D46: XEV 9e | E46: SUV coupé | F46: Cineluxe 79 kWh BaaS | G46: BaaS | H46: 1935000 | I46: verified | J46: 79 | K46: RWD | L46: 5 | M46: 5 | N46: 656 | O46: MIDC Part 1 + Part 2 | P46: 500 | Q46: 456 | R46: 70 | S46: 6.33 | T46: Maker real-world claim (estimate) | U46: =IF(S46="","",((1-Assumptions!$B$4)*Assumptions!$B$2+Assumptions!$B$4*Assumptions!$B$3)/S46) -> 1.4849921 | V46: =IF(U46="","",U46*Assumptions!$B$5*365*Assumptions!$B$6) -> 108404.42 | W46: No | X46: 60000 | Y46: 7.2 kW wall box ₹60,000 (Mahindra XEV 9e/9S pages) | Z46: =IF(OR(G46<>"battery included",H46="",V46=""),"",H46+X46+V46) | AC46: 218 | AE46: Not stated | AF46: Not stated | AG46: Not stated | AH46: Not stated | AI46: Not stated | AJ46: Yes | AK46: 180 | AL46: 142.2 | AM46: =IF(OR(S46="",AL46=""),"",100/S46/AL46*60) -> 6.6657335 | AP46: Lifetime (1st owner) | AQ46: Rated, applies | AR46: 32 | AS46: 45 | AV46: ESP not listed; BaaS: battery paid via separate loan (up to 8 yrs); not pay-per-km
A47: MAHINDRA-XEV9E-PACKTHREE-79-BAAS | B47: V030 | C47: Mahindra | D47: XEV 9e | E47: SUV coupé | F47: Pack Three 79 kWh BaaS | G47: BaaS | H47: 2050000 | I47: verified | J47: 79 | K47: RWD | L47: 5 | M47: 5 | N47: 656 | O47: MIDC Part 1 + Part 2 | P47: 500 | Q47: 456 | R47: 70 | S47: 6.33 | T47: Maker real-world claim (estimate) | U47: =IF(S47="","",((1-Assumptions!$B$4)*Assumptions!$B$2+Assumptions!$B$4*Assumptions!$B$3)/S47) -> 1.4849921 | V47: =IF(U47="","",U47*Assumptions!$B$5*365*Assumptions!$B$6) -> 108404.42 | W47: No | X47: 60000 | Y47: 7.2 kW wall box ₹60,000 (Mahindra XEV 9e/9S pages) | Z47: =IF(OR(G47<>"battery included",H47="",V47=""),"",H47+X47+V47) | AA47: 663 | AB47: 207 | AC47: 218 | AD47: 7 | AE47: Yes | AF47: L2+ | AG47: 360° | AH47: Not stated | AI47: Yes | AJ47: Yes | AK47: 180 | AL47: 142.2 | AM47: =IF(OR(S47="",AL47=""),"",100/S47/AL47*60) -> 6.6657335 | AN47: 11.7 | AO47: 11 | AP47: Lifetime (1st owner) | AQ47: Rated, applies | AR47: 32 | AS47: 45 | AV47: BaaS: battery paid via separate loan (up to 8 yrs); not pay-per-km
A48: MAHINDRA-XEV9E-PACKTWO-59-BAAS | B48: V024 | C48: Mahindra | D48: XEV 9e | E48: SUV coupé | F48: Pack Two 59 kWh BaaS | G48: BaaS | I48: pending | J48: 59 | K48: RWD | L48: 5 | M48: 5 | N48: 522 | O48: MIDC Part 1 + Part 2 | P48: 400 | S48: 6.78 | T48: Maker real-world claim (estimate) | U48: =IF(S48="","",((1-Assumptions!$B$4)*Assumptions!$B$2+Assumptions!$B$4*Assumptions!$B$3)/S48) -> 1.3864307 | V48: =IF(U48="","",U48*Assumptions!$B$5*365*Assumptions!$B$6) -> 101209.44 | W48: No | X48: 60000 | Y48: 7.2 kW wall box ₹60,000 (Mahindra XEV 9e/9S pages) | Z48: =IF(OR(G48<>"battery included",H48="",V48=""),"",H48+X48+V48) | AA48: 663 | AB48: 207 | AC48: 218 | AD48: 6 | AE48: Yes | AF48: L2 | AG48: Rear camera | AH48: Not stated | AI48: No | AJ48: No | AK48: 140 | AL48: 106.2 | AM48: =IF(OR(S48="",AL48=""),"",100/S48/AL48*60) -> 8.3329167 | AN48: 8.7 | AO48: 11 | AP48: Lifetime (1st owner) | AQ48: Rated, applies | AR48: 32 | AS48: 45 | AV48: BaaS: battery paid via separate loan (up to 8 yrs); not pay-per-km; Price pending, confirm before buying
A49: MAHINDRA-XEV9E-PACKTHREESELECT-59-BAAS | B49: V028 | C49: Mahindra | D49: XEV 9e | E49: SUV coupé | F49: Pack Three Select 59 kWh BaaS | G49: BaaS | I49: pending | J49: 59 | K49: RWD | L49: 5 | M49: 5 | N49: 522 | O49: MIDC Part 1 + Part 2 | P49: 400 | S49: 6.78 | T49: Maker real-world claim (estimate) | U49: =IF(S49="","",((1-Assumptions!$B$4)*Assumptions!$B$2+Assumptions!$B$4*Assumptions!$B$3)/S49) -> 1.3864307 | V49: =IF(U49="","",U49*Assumptions!$B$5*365*Assumptions!$B$6) -> 101209.44 | W49: No | X49: 60000 | Y49: 7.2 kW wall box ₹60,000 (Mahindra XEV 9e/9S pages) | Z49: =IF(OR(G49<>"battery included",H49="",V49=""),"",H49+X49+V49) | AA49: 663 | AB49: 207 | AC49: 218 | AD49: 7 | AE49: Yes | AF49: L2 | AG49: 360° | AH49: Not stated | AI49: Yes | AJ49: Yes | AK49: 140 | AL49: 106.2 | AM49: =IF(OR(S49="",AL49=""),"",100/S49/AL49*60) -> 8.3329167 | AN49: 8.7 | AO49: 11 | AP49: Lifetime (1st owner) | AQ49: Rated, applies | AR49: 32 | AS49: 45 | AV49: BaaS: battery paid via separate loan (up to 8 yrs); not pay-per-km; Price pending, confirm before buying
A50: MAHINDRA-XUV3XOEV-AX5-394 | B50: V045 | C50: Mahindra | D50: XUV 3XO EV | E50: SUV | F50: AX5 39.4 kWh | G50: battery included | H50: 1389000 | I50: verified | J50: 39.4 | K50: FWD | L50: 5 | M50: 5 | N50: 351 | O50: MIDC Part 1 + Part 2 | P50: 285 | S50: 7.23 | T50: Maker real-world claim (estimate) | U50: =IF(S50="","",((1-Assumptions!$B$4)*Assumptions!$B$2+Assumptions!$B$4*Assumptions!$B$3)/S50) -> 1.3001383 | V50: =IF(U50="","",U50*Assumptions!$B$5*365*Assumptions!$B$6) -> 94910.097 | W50: No | X50: 60000 | Y50: Assumed ₹60,000 (not published for XUV 3XO EV); 6.6 kW onboard charger limits benefit | Z50: =IF(OR(G50<>"battery included",H50="",V50=""),"",H50+X50+V50) -> 1543910.1 | AA50: 364 | AB50: 190 | AD50: 6 | AE50: Yes | AF50: None | AG50: Rear camera | AH50: Sunroof | AI50: Not stated | AJ50: Not stated | AK50: 50 | AL50: 37.8 | AM50: =IF(OR(S50="",AL50=""),"",100/S50/AL50*60) -> 21.954379 | AN50: 6.5 | AO50: 6.6 | AP50: Lifetime (1st owner) | AQ50: Not tested | AV50: No Bharat NCAP crash test; Onboard charger 6.6 kW: a 7.2 kW wall box won't charge faster; Wall charger not in price (~₹60,000); Slow DC fast-charging
A51: MAHINDRA-XUV3XOEV-AX7L-394 | B51: V046 | C51: Mahindra | D51: XUV 3XO EV | E51: SUV | F51: AX7L 39.4 kWh | G51: battery included | H51: 1496000 | I51: corroborated | J51: 39.4 | K51: FWD | L51: 5 | M51: 5 | N51: 351 | O51: MIDC Part 1 + Part 2 | P51: 285 | S51: 7.23 | T51: Maker real-world claim (estimate) | U51: =IF(S51="","",((1-Assumptions!$B$4)*Assumptions!$B$2+Assumptions!$B$4*Assumptions!$B$3)/S51) -> 1.3001383 | V51: =IF(U51="","",U51*Assumptions!$B$5*365*Assumptions!$B$6) -> 94910.097 | W51: No | X51: 60000 | Y51: Assumed ₹60,000 (not published for XUV 3XO EV); 6.6 kW onboard charger limits benefit | Z51: =IF(OR(G51<>"battery included",H51="",V51=""),"",H51+X51+V51) -> 1650910.1 | AA51: 364 | AB51: 190 | AD51: 6 | AE51: Yes | AF51: L2 | AG51: 360° | AH51: Panoramic | AI51: Not stated | AJ51: Not stated | AK51: 50 | AL51: 37.8 | AM51: =IF(OR(S51="",AL51=""),"",100/S51/AL51*60) -> 21.954379 | AN51: 6.5 | AO51: 6.6 | AP51: Lifetime (1st owner) | AQ51: Not tested | AV51: No Bharat NCAP crash test; Onboard charger 6.6 kW: a 7.2 kW wall box won't charge faster; Wall charger not in price (~₹60,000); Price corroborated, confirm before buying; Slow DC fast-charging
A52: TATA-CURVVEV-ACCOMPLISHEDX55-55 | B52: V059 | C52: Tata | D52: Curvv.ev | E52: SUV coupé | F52: Accomplished X 55 | G52: battery included | H52: 1719000 | I52: verified | J52: 55 | K52: FWD | L52: 5 | M52: 5 | N52: 502 | O52: MIDC Part 1 + Part 2 | P52: 400 | Q52: 365 | R52: 73 | S52: 6.64 | T52: Independent test | U52: =IF(S52="","",((1-Assumptions!$B$4)*Assumptions!$B$2+Assumptions!$B$4*Assumptions!$B$3)/S52) -> 1.4156627 | V52: =IF(U52="","",U52*Assumptions!$B$5*365*Assumptions!$B$6) -> 103343.37 | W52: Unclear | X52: 50000 | Y52: Brochure vs website disagree; ₹50,000 assumed | Z52: =IF(OR(G52<>"battery included",H52="",V52=""),"",H52+X52+V52) -> 1872343.4 | AA52: 500 | AB52: 186 | AD52: 6 | AE52: Yes | AF52: None | AG52: 360° | AH52: Panoramic | AI52: Passive only | AJ52: Not stated | AK52: 70 | AL52: 57.8 | AM52: =IF(OR(S52="",AL52=""),"",100/S52/AL52*60) -> 15.633468 | AN52: 8.4 | AP52: Lifetime (1st owner) | AQ52: Rated, applies | AR52: 30.81 | AS52: 44.83 | AV52: Wall charger not in price (~₹50,000)
A53: TATA-CURVVEV-EMPOWEREDX55-55 | B53: V060 | C53: Tata | D53: Curvv.ev | E53: SUV coupé | F53: Empowered X 55 | G53: battery included | H53: 1939000 | I53: verified | J53: 55 | K53: FWD | L53: 5 | M53: 5 | N53: 502 | O53: MIDC Part 1 + Part 2 | P53: 400 | Q53: 365 | R53: 73 | S53: 6.64 | T53: Independent test | U53: =IF(S53="","",((1-Assumptions!$B$4)*Assumptions!$B$2+Assumptions!$B$4*Assumptions!$B$3)/S53) -> 1.4156627 | V53: =IF(U53="","",U53*Assumptions!$B$5*365*Assumptions!$B$6) -> 103343.37 | W53: Yes (7.2 kW) | X53: 0 | Y53: Included per Tata | Z53: =IF(OR(G53<>"battery included",H53="",V53=""),"",H53+X53+V53) -> 2042343.4 | AA53: 500 | AB53: 186 | AD53: 6 | AE53: Yes | AF53: L2 | AG53: 360° | AH53: Panoramic | AI53: Yes | AJ53: Not stated | AK53: 70 | AL53: 57.8 | AM53: =IF(OR(S53="",AL53=""),"",100/S53/AL53*60) -> 15.633468 | AN53: 8.4 | AP53: Lifetime (1st owner) | AQ53: Rated, applies | AR53: 30.81 | AS53: 44.83 | AV53: None flagged
A54: TATA-HARRIEREV-ADVENTURE65-65 | B54: V061 | C54: Tata | D54: Harrier.ev | E54: SUV | F54: Adventure 65 | G54: battery included | H54: 2179000 | I54: verified | J54: 65 | K54: RWD | L54: 5 | M54: 5 | N54: 538 | O54: MIDC Part 1 + Part 2 | P54: 420 | S54: 6.46 | T54: Maker real-world claim (estimate) | U54: =IF(S54="","",((1-Assumptions!$B$4)*Assumptions!$B$2+Assumptions!$B$4*Assumptions!$B$3)/S54) -> 1.4551084 | V54: =IF(U54="","",U54*Assumptions!$B$5*365*Assumptions!$B$6) -> 106222.91 | W54: No | X54: 50000 | Y54: Tata 'ACFC' option price | Z54: =IF(OR(G54<>"battery included",H54="",V54=""),"",H54+X54+V54) -> 2335222.9 | AA54: 502 | AD54: 6 | AE54: Yes | AF54: None | AG54: Not stated | AH54: None | AI54: No | AJ54: Not stated | AK54: 100 | AL54: 93.6 | AM54: =IF(OR(S54="",AL54=""),"",100/S54/AL54*60) -> 9.9229975 | AN54: 10.3 | AP54: Lifetime (1st owner) | AQ54: Not tested | AT54: 3 | AU54: 600 | AV54: No Bharat NCAP crash test; Wall charger not in price (~₹50,000)
A55: TATA-HARRIEREV-ADVENTURES65-65 | B55: V062 | C55: Tata | D55: Harrier.ev | E55: SUV | F55: Adventure S 65 | G55: battery included | H55: 2229000 | I55: verified | J55: 65 | K55: RWD | L55: 5 | M55: 5 | N55: 538 | O55: MIDC Part 1 + Part 2 | P55: 420 | S55: 6.46 | T55: Maker real-world claim (estimate) | U55: =IF(S55="","",((1-Assumptions!$B$4)*Assumptions!$B$2+Assumptions!$B$4*Assumptions!$B$3)/S55) -> 1.4551084 | V55: =IF(U55="","",U55*Assumptions!$B$5*365*Assumptions!$B$6) -> 106222.91 | W55: No | X55: 50000 | Y55: Tata 'ACFC' option price | Z55: =IF(OR(G55<>"battery included",H55="",V55=""),"",H55+X55+V55) -> 2385222.9 | AA55: 502 | AD55: 6 | AE55: Yes | AF55: None | AG55: Not stated | AH55: Panoramic | AI55: No | AJ55: Not stated | AK55: 100 | AL55: 93.6 | AM55: =IF(OR(S55="",AL55=""),"",100/S55/AL55*60) -> 9.9229975 | AN55: 10.3 | AP55: Lifetime (1st owner) | AQ55: Not tested | AT55: 3 | AU55: 600 | AV55: No Bharat NCAP crash test; Wall charger not in price (~₹50,000)
A56: TATA-HARRIEREV-FEARLESSPLUS65-65 | B56: V063 | C56: Tata | D56: Harrier.ev | E56: SUV | F56: Fearless+ 65 | G56: battery included | H56: 2429000 | I56: verified | J56: 65 | K56: RWD | L56: 5 | M56: 5 | N56: 538 | O56: MIDC Part 1 + Part 2 | P56: 420 | S56: 6.46 | T56: Maker real-world claim (estimate) | U56: =IF(S56="","",((1-Assumptions!$B$4)*Assumptions!$B$2+Assumptions!$B$4*Assumptions!$B$3)/S56) -> 1.4551084 | V56: =IF(U56="","",U56*Assumptions!$B$5*365*Assumptions!$B$6) -> 106222.91 | W56: No | X56: 50000 | Y56: Tata 'ACFC' option price | Z56: =IF(OR(G56<>"battery included",H56="",V56=""),"",H56+X56+V56) -> 2585222.9 | AA56: 502 | AD56: 7 | AE56: Yes | AF56: None | AG56: 360° | AH56: Panoramic | AI56: Yes | AJ56: Not stated | AK56: 100 | AL56: 93.6 | AM56: =IF(OR(S56="",AL56=""),"",100/S56/AL56*60) -> 9.9229975 | AN56: 10.3 | AP56: Lifetime (1st owner) | AQ56: Not tested | AT56: 3 | AU56: 600 | AV56: No Bharat NCAP crash test; Wall charger not in price (~₹50,000)
A57: TATA-HARRIEREV-FEARLESSPLUS75-75 | B57: V064 | C57: Tata | D57: Harrier.ev | E57: SUV | F57: Fearless+ 75 | G57: battery included | H57: 2529000 | I57: verified | J57: 75 | K57: RWD | L57: 5 | M57: 5 | N57: 627 | O57: MIDC Part 1 + Part 2 | P57: 480 | S57: 6.4 | T57: Maker real-world claim (estimate) | U57: =IF(S57="","",((1-Assumptions!$B$4)*Assumptions!$B$2+Assumptions!$B$4*Assumptions!$B$3)/S57) -> 1.46875 | V57: =IF(U57="","",U57*Assumptions!$B$5*365*Assumptions!$B$6) -> 107218.75 | W57: No | X57: 50000 | Y57: Tata 'ACFC' option price | Z57: =IF(OR(G57<>"battery included",H57="",V57=""),"",H57+X57+V57) -> 2686218.8 | AA57: 502 | AD57: 7 | AE57: Yes | AF57: None | AG57: 360° | AH57: Panoramic | AI57: Yes | AJ57: Not stated | AK57: 120 | AL57: 108 | AM57: =IF(OR(S57="",AL57=""),"",100/S57/AL57*60) -> 8.6805556 | AN57: 11.9 | AP57: Lifetime (1st owner) | AQ57: Not tested | AT57: 3 | AU57: 600 | AV57: No Bharat NCAP crash test; Wall charger not in price (~₹50,000)
A58: TATA-HARRIEREV-FEARLESSPLUSQWD75-75-AWD | B58: V066 | C58: Tata | D58: Harrier.ev | E58: SUV | F58: Fearless+ QWD 75 (AWD) | G58: battery included | H58: 2679000 | I58: verified | J58: 75 | K58: AWD | L58: 5 | M58: 5 | N58: 622 | O58: MIDC Part 1 + Part 2 | P58: 460 | Q58: 401 | R58: 64 | S58: 5.35 | T58: Independent test | U58: =IF(S58="","",((1-Assumptions!$B$4)*Assumptions!$B$2+Assumptions!$B$4*Assumptions!$B$3)/S58) -> 1.7570093 | V58: =IF(U58="","",U58*Assumptions!$B$5*365*Assumptions!$B$6) -> 128261.68 | W58: No | X58: 50000 | Y58: Tata 'ACFC' option price | Z58: =IF(OR(G58<>"battery included",H58="",V58=""),"",H58+X58+V58) -> 2857261.7 | AA58: 502 | AD58: 7 | AE58: Yes | AF58: None | AG58: 360° | AH58: Panoramic | AI58: Yes | AJ58: Not stated | AK58: 120 | AL58: 108 | AM58: =IF(OR(S58="",AL58=""),"",100/S58/AL58*60) -> 10.384216 | AN58: 11.9 | AP58: Lifetime (1st owner) | AQ58: Not tested | AT58: 6 | AU58: 600 | AV58: No Bharat NCAP crash test; Tested range only 64% of claim; Wall charger not in price (~₹50,000)
A59: TATA-HARRIEREV-EMPOWERED75-75 | B59: V065 | C59: Tata | D59: Harrier.ev | E59: SUV | F59: Empowered 75 | G59: battery included | H59: 2779000 | I59: verified | J59: 75 | K59: RWD | L59: 5 | M59: 5 | N59: 627 | O59: MIDC Part 1 + Part 2 | P59: 480 | S59: 6.4 | T59: Maker real-world claim (estimate) | U59: =IF(S59="","",((1-Assumptions!$B$4)*Assumptions!$B$2+Assumptions!$B$4*Assumptions!$B$3)/S59) -> 1.46875 | V59: =IF(U59="","",U59*Assumptions!$B$5*365*Assumptions!$B$6) -> 107218.75 | W59: No | X59: 50000 | Y59: Tata 'ACFC' option price | Z59: =IF(OR(G59<>"battery included",H59="",V59=""),"",H59+X59+V59) -> 2936218.8 | AA59: 502 | AD59: 7 | AE59: Yes | AF59: L2 | AG59: 540° | AH59: Panoramic | AI59: Yes | AJ59: Not stated | AK59: 120 | AL59: 108 | AM59: =IF(OR(S59="",AL59=""),"",100/S59/AL59*60) -> 8.6805556 | AN59: 11.9 | AP59: Lifetime (1st owner) | AQ59: Not tested | AT59: 4 | AU59: 600 | AV59: No Bharat NCAP crash test; Wall charger not in price (~₹50,000)
A60: TATA-HARRIEREV-EMPOWEREDQWD75-75-AWD | B60: V067 | C60: Tata | D60: Harrier.ev | E60: SUV | F60: Empowered QWD 75 (AWD) | G60: battery included | H60: 2929000 | I60: verified | J60: 75 | K60: AWD | L60: 5 | M60: 5 | N60: 622 | O60: MIDC Part 1 + Part 2 | P60: 460 | Q60: 401 | R60: 64 | S60: 5.35 | T60: Independent test | U60: =IF(S60="","",((1-Assumptions!$B$4)*Assumptions!$B$2+Assumptions!$B$4*Assumptions!$B$3)/S60) -> 1.7570093 | V60: =IF(U60="","",U60*Assumptions!$B$5*365*Assumptions!$B$6) -> 128261.68 | W60: No | X60: 50000 | Y60: Tata 'ACFC' option price | Z60: =IF(OR(G60<>"battery included",H60="",V60=""),"",H60+X60+V60) -> 3107261.7 | AA60: 502 | AD60: 7 | AE60: Yes | AF60: L2 | AG60: 540° | AH60: Panoramic | AI60: Yes | AJ60: Not stated | AK60: 120 | AL60: 108 | AM60: =IF(OR(S60="",AL60=""),"",100/S60/AL60*60) -> 10.384216 | AN60: 11.9 | AP60: Lifetime (1st owner) | AQ60: Not tested | AT60: 6 | AU60: 600 | AV60: No Bharat NCAP crash test; Tested range only 64% of claim; Wall charger not in price (~₹50,000)
A61: TATA-NEXONEV-CREATIVEPLUSMR-30 | B61: V047 | C61: Tata | D61: Nexon.ev | E61: SUV | F61: Creative+ MR | G61: battery included | H61: 1249000 | I61: verified | J61: 30 | K61: FWD | L61: 5 | M61: 5 | N61: 275 | O61: MIDC Part 1 + Part 2 | P61: 210 | S61: 7 | T61: Maker real-world claim (estimate) | U61: =IF(S61="","",((1-Assumptions!$B$4)*Assumptions!$B$2+Assumptions!$B$4*Assumptions!$B$3)/S61) -> 1.3428571 | V61: =IF(U61="","",U61*Assumptions!$B$5*365*Assumptions!$B$6) -> 98028.571 | W61: Not stated | X61: 50000 | Y61: Not stated; ₹50,000 assumed (Tata ACFC price) | Z61: =IF(OR(G61<>"battery included",H61="",V61=""),"",H61+X61+V61) -> 1397028.6 | AA61: 350 | AB61: 205 | AD61: 6 | AE61: Yes | AF61: None | AG61: Rear camera | AH61: None | AI61: No | AJ61: Not stated | AK61: 50 | AL61: 22.5 | AM61: =IF(OR(S61="",AL61=""),"",100/S61/AL61*60) -> 38.095238 | AN61: 4.8 | AP61: 8 yrs / 1.6L km | AQ61: Rated, coverage unconfirmed | AR61: 29.86 | AS61: 44.95 | AV61: Crash rating may not cover this version; Battery warranty 8 yrs/1.6L km (not lifetime); Wall charger not in price (~₹50,000); Slow DC fast-charging
A62: TATA-NEXONEV-FEARLESSMR-30 | B62: V048 | C62: Tata | D62: Nexon.ev | E62: SUV | F62: Fearless MR | G62: battery included | H62: 1329000 | I62: verified | J62: 30 | K62: FWD | L62: 5 | M62: 5 | N62: 275 | O62: MIDC Part 1 + Part 2 | P62: 210 | S62: 7 | T62: Maker real-world claim (estimate) | U62: =IF(S62="","",((1-Assumptions!$B$4)*Assumptions!$B$2+Assumptions!$B$4*Assumptions!$B$3)/S62) -> 1.3428571 | V62: =IF(U62="","",U62*Assumptions!$B$5*365*Assumptions!$B$6) -> 98028.571 | W62: Not stated | X62: 50000 | Y62: Not stated; ₹50,000 assumed (Tata ACFC price) | Z62: =IF(OR(G62<>"battery included",H62="",V62=""),"",H62+X62+V62) -> 1477028.6 | AA62: 350 | AB62: 205 | AD62: 6 | AE62: Yes | AF62: None | AG62: Rear camera | AH62: None | AI62: No | AJ62: Not stated | AK62: 50 | AL62: 22.5 | AM62: =IF(OR(S62="",AL62=""),"",100/S62/AL62*60) -> 38.095238 | AN62: 4.8 | AP62: 8 yrs / 1.6L km | AQ62: Rated, coverage unconfirmed | AR62: 29.86 | AS62: 44.95 | AV62: Crash rating may not cover this version; Battery warranty 8 yrs/1.6L km (not lifetime); Wall charger not in price (~₹50,000); Slow DC fast-charging
A63: TATA-NEXONEV-CREATIVE45-45 | B63: V049 | C63: Tata | D63: Nexon.ev | E63: SUV | F63: Creative 45 | G63: battery included | H63: 1434000 | I63: verified | J63: 45 | K63: FWD | L63: 5 | M63: 5 | N63: 489 | O63: MIDC Part 1 + Part 2 | P63: 350 | Q63: 350 | R63: 72 | S63: 7.79 | T63: Independent test | U63: =IF(S63="","",((1-Assumptions!$B$4)*Assumptions!$B$2+Assumptions!$B$4*Assumptions!$B$3)/S63) -> 1.2066752 | V63: =IF(U63="","",U63*Assumptions!$B$5*365*Assumptions!$B$6) -> 88087.291 | W63: Not stated | X63: 50000 | Y63: Not stated; ₹50,000 assumed (Tata ACFC price) | Z63: =IF(OR(G63<>"battery included",H63="",V63=""),"",H63+X63+V63) -> 1572087.3 | AA63: 350 | AB63: 190 | AD63: 6 | AE63: Yes | AF63: None | AG63: Rear camera | AH63: None | AI63: No | AJ63: Not stated | AK63: 60 | AL63: 47.2 | AM63: =IF(OR(S63="",AL63=""),"",100/S63/AL63*60) -> 16.318183 | AN63: 7.3 | AP63: Lifetime (1st owner) | AQ63: Rated, applies | AR63: 29.86 | AS63: 44.95 | AV63: Wall charger not in price (~₹50,000)
A64: TATA-NEXONEV-FEARLESS45-45 | B64: V050 | C64: Tata | D64: Nexon.ev | E64: SUV | F64: Fearless 45 | G64: battery included | H64: 1534000 | I64: verified | J64: 45 | K64: FWD | L64: 5 | M64: 5 | N64: 489 | O64: MIDC Part 1 + Part 2 | P64: 350 | Q64: 350 | R64: 72 | S64: 7.79 | T64: Independent test | U64: =IF(S64="","",((1-Assumptions!$B$4)*Assumptions!$B$2+Assumptions!$B$4*Assumptions!$B$3)/S64) -> 1.2066752 | V64: =IF(U64="","",U64*Assumptions!$B$5*365*Assumptions!$B$6) -> 88087.291 | W64: Not stated | X64: 50000 | Y64: Not stated; ₹50,000 assumed (Tata ACFC price) | Z64: =IF(OR(G64<>"battery included",H64="",V64=""),"",H64+X64+V64) -> 1672087.3 | AA64: 350 | AB64: 190 | AD64: 6 | AE64: Yes | AF64: None | AG64: Rear camera | AH64: None | AI64: No | AJ64: Not stated | AK64: 60 | AL64: 47.2 | AM64: =IF(OR(S64="",AL64=""),"",100/S64/AL64*60) -> 16.318183 | AN64: 7.3 | AP64: Lifetime (1st owner) | AQ64: Rated, applies | AR64: 29.86 | AS64: 44.95 | AV64: Wall charger not in price (~₹50,000)
A65: TATA-NEXONEV-EMPOWERED45-45 | B65: V051 | C65: Tata | D65: Nexon.ev | E65: SUV | F65: Empowered 45 | G65: battery included | H65: 1634000 | I65: verified | J65: 45 | K65: FWD | L65: 5 | M65: 5 | N65: 489 | O65: MIDC Part 1 + Part 2 | P65: 350 | Q65: 350 | R65: 72 | S65: 7.79 | T65: Independent test | U65: =IF(S65="","",((1-Assumptions!$B$4)*Assumptions!$B$2+Assumptions!$B$4*Assumptions!$B$3)/S65) -> 1.2066752 | V65: =IF(U65="","",U65*Assumptions!$B$5*365*Assumptions!$B$6) -> 88087.291 | W65: Not stated | X65: 50000 | Y65: Not stated; ₹50,000 assumed (Tata ACFC price) | Z65: =IF(OR(G65<>"battery included",H65="",V65=""),"",H65+X65+V65) -> 1772087.3 | AA65: 350 | AB65: 190 | AD65: 6 | AE65: Yes | AF65: None | AG65: 360° | AH65: Sunroof | AI65: No | AJ65: Not stated | AK65: 60 | AL65: 47.2 | AM65: =IF(OR(S65="",AL65=""),"",100/S65/AL65*60) -> 16.318183 | AN65: 7.3 | AP65: Lifetime (1st owner) | AQ65: Rated, applies | AR65: 29.86 | AS65: 44.95 | AV65: Wall charger not in price (~₹50,000)
A66: TATA-NEXONEV-EMPOWEREDPLUSA45-45 | B66: V052 | C66: Tata | D66: Nexon.ev | E66: SUV | F66: Empowered+A 45 | G66: battery included | H66: 1769000 | I66: verified | J66: 45 | K66: FWD | L66: 5 | M66: 5 | N66: 489 | O66: MIDC Part 1 + Part 2 | P66: 350 | Q66: 350 | R66: 72 | S66: 7.79 | T66: Independent test | U66: =IF(S66="","",((1-Assumptions!$B$4)*Assumptions!$B$2+Assumptions!$B$4*Assumptions!$B$3)/S66) -> 1.2066752 | V66: =IF(U66="","",U66*Assumptions!$B$5*365*Assumptions!$B$6) -> 88087.291 | W66: Yes (7.2 kW) | X66: 0 | Y66: Included per Tata | Z66: =IF(OR(G66<>"battery included",H66="",V66=""),"",H66+X66+V66) -> 1857087.3 | AA66: 350 | AB66: 190 | AD66: 6 | AE66: Yes | AF66: L2 | AG66: 360° | AH66: Panoramic | AI66: Yes | AJ66: Not stated | AK66: 60 | AL66: 47.2 | AM66: =IF(OR(S66="",AL66=""),"",100/S66/AL66*60) -> 16.318183 | AN66: 7.3 | AP66: Lifetime (1st owner) | AQ66: Rated, applies | AR66: 29.86 | AS66: 44.95 | AV66: None flagged
A67: TATA-PUNCHEV-SMART30-30 | B67: V053 | C67: Tata | D67: Punch.ev | E67: SUV | F67: Smart 30 | G67: battery included | H67: 979000 | I67: verified | J67: 30 | K67: FWD | L67: 5 | M67: 5 | N67: 365 | O67: MIDC Part 1 + Part 2 | P67: 260 | S67: 8.67 | T67: Maker real-world claim (estimate) | U67: =IF(S67="","",((1-Assumptions!$B$4)*Assumptions!$B$2+Assumptions!$B$4*Assumptions!$B$3)/S67) -> 1.0841984 | V67: =IF(U67="","",U67*Assumptions!$B$5*365*Assumptions!$B$6) -> 79146.482 | W67: Yes (3.3 kW) | X67: 0 | Y67: 3.3 kW wall box included (brochure) | Z67: =IF(OR(G67<>"battery included",H67="",V67=""),"",H67+X67+V67) -> 1058146.5 | AA67: 366 | AB67: 195 | AD67: 6 | AE67: Yes | AF67: None | AG67: Sensors only | AH67: None | AI67: No | AJ67: Not stated | AK67: 65 | AL67: 42 | AM67: =IF(OR(S67="",AL67=""),"",100/S67/AL67*60) -> 16.477179 | AN67: 5 | AP67: 8 yrs / 1.6L km | AQ67: Rated, applies | AR67: 31.09 | AS67: 45 | AV67: Battery warranty 8 yrs/1.6L km (not lifetime)
A68: TATA-PUNCHEV-SMARTPLUS30-30 | B68: V054 | C68: Tata | D68: Punch.ev | E68: SUV | F68: Smart+ 30 | G68: battery included | H68: 1039000 | I68: verified | J68: 30 | K68: FWD | L68: 5 | M68: 5 | N68: 365 | O68: MIDC Part 1 + Part 2 | P68: 260 | S68: 8.67 | T68: Maker real-world claim (estimate) | U68: =IF(S68="","",((1-Assumptions!$B$4)*Assumptions!$B$2+Assumptions!$B$4*Assumptions!$B$3)/S68) -> 1.0841984 | V68: =IF(U68="","",U68*Assumptions!$B$5*365*Assumptions!$B$6) -> 79146.482 | W68: Yes (3.3 kW) | X68: 0 | Y68: 3.3 kW wall box included (brochure) | Z68: =IF(OR(G68<>"battery included",H68="",V68=""),"",H68+X68+V68) -> 1118146.5 | AA68: 366 | AB68: 195 | AD68: 6 | AE68: Yes | AF68: None | AG68: Sensors only | AH68: None | AI68: No | AJ68: Not stated | AK68: 65 | AL68: 42 | AM68: =IF(OR(S68="",AL68=""),"",100/S68/AL68*60) -> 16.477179 | AN68: 5 | AP68: 8 yrs / 1.6L km | AQ68: Rated, applies | AR68: 31.09 | AS68: 45 | AV68: Battery warranty 8 yrs/1.6L km (not lifetime)
A69: TATA-PUNCHEV-SMARTPLUS40-40 | B69: V055 | C69: Tata | D69: Punch.ev | E69: SUV | F69: Smart+ 40 | G69: battery included | H69: 1119000 | I69: verified | J69: 40 | K69: FWD | L69: 5 | M69: 5 | N69: 468 | O69: MIDC Part 1 + Part 2 | P69: 335 | Q69: 304 | R69: 65 | S69: 7.61 | T69: Independent test | U69: =IF(S69="","",((1-Assumptions!$B$4)*Assumptions!$B$2+Assumptions!$B$4*Assumptions!$B$3)/S69) -> 1.2352168 | V69: =IF(U69="","",U69*Assumptions!$B$5*365*Assumptions!$B$6) -> 90170.828 | W69: Yes (3.3 kW) | X69: 0 | Y69: 3.3 kW wall box included (brochure) | Z69: =IF(OR(G69<>"battery included",H69="",V69=""),"",H69+X69+V69) -> 1209170.8 | AA69: 366 | AB69: 195 | AD69: 6 | AE69: Yes | AF69: None | AG69: Rear camera | AH69: None | AI69: No | AJ69: Not stated | AK69: 65 | AL69: 56 | AM69: =IF(OR(S69="",AL69=""),"",100/S69/AL69*60) -> 14.079219 | AN69: 5.9 | AP69: Lifetime (1st owner) | AQ69: Rated, applies | AR69: 31.09 | AS69: 45 | AV69: Tested range only 65% of claim
A70: TATA-PUNCHEV-ADVENTURE40-40 | B70: V056 | C70: Tata | D70: Punch.ev | E70: SUV | F70: Adventure 40 | G70: battery included | H70: 1194000 | I70: verified | J70: 40 | K70: FWD | L70: 5 | M70: 5 | N70: 468 | O70: MIDC Part 1 + Part 2 | P70: 335 | Q70: 304 | R70: 65 | S70: 7.61 | T70: Independent test | U70: =IF(S70="","",((1-Assumptions!$B$4)*Assumptions!$B$2+Assumptions!$B$4*Assumptions!$B$3)/S70) -> 1.2352168 | V70: =IF(U70="","",U70*Assumptions!$B$5*365*Assumptions!$B$6) -> 90170.828 | W70: Yes (3.3 kW) | X70: 0 | Y70: 3.3 kW wall box included (brochure) | Z70: =IF(OR(G70<>"battery included",H70="",V70=""),"",H70+X70+V70) -> 1284170.8 | AA70: 366 | AB70: 195 | AD70: 6 | AE70: Yes | AF70: None | AG70: Rear camera | AH70: None | AI70: No | AJ70: Not stated | AK70: 65 | AL70: 56 | AM70: =IF(OR(S70="",AL70=""),"",100/S70/AL70*60) -> 14.079219 | AN70: 5.9 | AP70: Lifetime (1st owner) | AQ70: Rated, applies | AR70: 31.09 | AS70: 45 | AV70: Tested range only 65% of claim
A71: TATA-PUNCHEV-EMPOWERED40-40 | B71: V057 | C71: Tata | D71: Punch.ev | E71: SUV | F71: Empowered 40 | G71: battery included | H71: 1269000 | I71: verified | J71: 40 | K71: FWD | L71: 5 | M71: 5 | N71: 468 | O71: MIDC Part 1 + Part 2 | P71: 335 | Q71: 304 | R71: 65 | S71: 7.61 | T71: Independent test | U71: =IF(S71="","",((1-Assumptions!$B$4)*Assumptions!$B$2+Assumptions!$B$4*Assumptions!$B$3)/S71) -> 1.2352168 | V71: =IF(U71="","",U71*Assumptions!$B$5*365*Assumptions!$B$6) -> 90170.828 | W71: Yes (3.3 kW) | X71: 0 | Y71: 3.3 kW wall box included (brochure) | Z71: =IF(OR(G71<>"battery included",H71="",V71=""),"",H71+X71+V71) -> 1359170.8 | AA71: 366 | AB71: 195 | AD71: 6 | AE71: Yes | AF71: None | AG71: 360° | AH71: None | AI71: No | AJ71: Not stated | AK71: 65 | AL71: 56 | AM71: =IF(OR(S71="",AL71=""),"",100/S71/AL71*60) -> 14.079219 | AN71: 5.9 | AP71: Lifetime (1st owner) | AQ71: Rated, applies | AR71: 31.09 | AS71: 45 | AV71: Tested range only 65% of claim
A72: TATA-PUNCHEV-EMPOWEREDPLUSS40-40 | B72: V058 | C72: Tata | D72: Punch.ev | E72: SUV | F72: Empowered+ S 40 | G72: battery included | H72: 1299000 | I72: verified | J72: 40 | K72: FWD | L72: 5 | M72: 5 | N72: 468 | O72: MIDC Part 1 + Part 2 | P72: 335 | Q72: 304 | R72: 65 | S72: 7.61 | T72: Independent test | U72: =IF(S72="","",((1-Assumptions!$B$4)*Assumptions!$B$2+Assumptions!$B$4*Assumptions!$B$3)/S72) -> 1.2352168 | V72: =IF(U72="","",U72*Assumptions!$B$5*365*Assumptions!$B$6) -> 90170.828 | W72: Yes (3.3 kW) | X72: 0 | Y72: 3.3 kW wall box included (brochure) | Z72: =IF(OR(G72<>"battery included",H72="",V72=""),"",H72+X72+V72) -> 1389170.8 | AA72: 366 | AB72: 195 | AD72: 6 | AE72: Yes | AF72: None | AG72: 360° | AH72: Sunroof | AI72: Yes | AJ72: Not stated | AK72: 65 | AL72: 56 | AM72: =IF(OR(S72="",AL72=""),"",100/S72/AL72*60) -> 14.079219 | AN72: 5.9 | AP72: Lifetime (1st owner) | AQ72: Rated, applies | AR72: 31.09 | AS72: 45 | AV72: Tested range only 65% of claim
A73: TATA-SIERRAEV-PURE63-63 | B73: V068 | C73: Tata | D73: Sierra.ev | E73: SUV | F73: Pure 63 | G73: battery included | H73: 1879000 | I73: verified | J73: 63 | K73: RWD | L73: 5 | M73: 5 | N73: 566 | O73: MIDC Part 1 + Part 2 | P73: 440 | S73: 6.98 | T73: Maker real-world claim (estimate) | U73: =IF(S73="","",((1-Assumptions!$B$4)*Assumptions!$B$2+Assumptions!$B$4*Assumptions!$B$3)/S73) -> 1.3467049 | V73: =IF(U73="","",U73*Assumptions!$B$5*365*Assumptions!$B$6) -> 98309.456 | W73: No | X73: 49000 | Y73: Tata 'ACFC' option price | Z73: =IF(OR(G73<>"battery included",H73="",V73=""),"",H73+X73+V73) -> 2026309.5 | AA73: 622 | AB73: 205 | AD73: 6 | AE73: Yes | AF73: None | AG73: Rear camera | AH73: None | AI73: No | AJ73: Not stated | AK73: 110 | AL73: 90.7 | AM73: =IF(OR(S73="",AL73=""),"",100/S73/AL73*60) -> 9.4773854 | AN73: 9.9 | AP73: Lifetime (1st owner) | AQ73: Not tested | AV73: No Bharat NCAP crash test; Wall charger not in price (~₹49,000)
A74: TATA-SIERRAEV-PURES63-63 | B74: V069 | C74: Tata | D74: Sierra.ev | E74: SUV | F74: Pure S 63 | G74: battery included | H74: 1999000 | I74: verified | J74: 63 | K74: RWD | L74: 5 | M74: 5 | N74: 566 | O74: MIDC Part 1 + Part 2 | P74: 440 | S74: 6.98 | T74: Maker real-world claim (estimate) | U74: =IF(S74="","",((1-Assumptions!$B$4)*Assumptions!$B$2+Assumptions!$B$4*Assumptions!$B$3)/S74) -> 1.3467049 | V74: =IF(U74="","",U74*Assumptions!$B$5*365*Assumptions!$B$6) -> 98309.456 | W74: No | X74: 49000 | Y74: Tata 'ACFC' option price | Z74: =IF(OR(G74<>"battery included",H74="",V74=""),"",H74+X74+V74) -> 2146309.5 | AA74: 622 | AB74: 205 | AD74: 6 | AE74: Yes | AF74: None | AG74: Rear camera | AH74: Panoramic | AI74: No | AJ74: Not stated | AK74: 110 | AL74: 90.7 | AM74: =IF(OR(S74="",AL74=""),"",100/S74/AL74*60) -> 9.4773854 | AN74: 9.9 | AP74: Lifetime (1st owner) | AQ74: Not tested | AV74: No Bharat NCAP crash test; Wall charger not in price (~₹49,000)
A75: TATA-SIERRAEV-ADVENTURE63-63 | B75: V070 | C75: Tata | D75: Sierra.ev | E75: SUV | F75: Adventure 63 | G75: battery included | H75: 2099000 | I75: verified | J75: 63 | K75: RWD | L75: 5 | M75: 5 | N75: 566 | O75: MIDC Part 1 + Part 2 | P75: 440 | S75: 6.98 | T75: Maker real-world claim (estimate) | U75: =IF(S75="","",((1-Assumptions!$B$4)*Assumptions!$B$2+Assumptions!$B$4*Assumptions!$B$3)/S75) -> 1.3467049 | V75: =IF(U75="","",U75*Assumptions!$B$5*365*Assumptions!$B$6) -> 98309.456 | W75: No | X75: 49000 | Y75: Tata 'ACFC' option price | Z75: =IF(OR(G75<>"battery included",H75="",V75=""),"",H75+X75+V75) -> 2246309.5 | AA75: 622 | AB75: 205 | AD75: 6 | AE75: Yes | AF75: None | AG75: 360° | AH75: Panoramic | AI75: No | AJ75: Not stated | AK75: 110 | AL75: 90.7 | AM75: =IF(OR(S75="",AL75=""),"",100/S75/AL75*60) -> 9.4773854 | AN75: 9.9 | AP75: Lifetime (1st owner) | AQ75: Not tested | AT75: 4 | AV75: No Bharat NCAP crash test; Wall charger not in price (~₹49,000)
A76: TATA-SIERRAEV-ADVENTURE75-75 | B76: V071 | C76: Tata | D76: Sierra.ev | E76: SUV | F76: Adventure 75 | G76: battery included | H76: 2219000 | I76: verified | J76: 75 | K76: RWD | L76: 5 | M76: 5 | N76: 665 | O76: MIDC Part 1 + Part 2 | P76: 510 | S76: 6.8 | T76: Maker real-world claim (estimate) | U76: =IF(S76="","",((1-Assumptions!$B$4)*Assumptions!$B$2+Assumptions!$B$4*Assumptions!$B$3)/S76) -> 1.3823529 | V76: =IF(U76="","",U76*Assumptions!$B$5*365*Assumptions!$B$6) -> 100911.76 | W76: No | X76: 49000 | Y76: Tata 'ACFC' option price | Z76: =IF(OR(G76<>"battery included",H76="",V76=""),"",H76+X76+V76) -> 2368911.8 | AA76: 622 | AB76: 205 | AD76: 6 | AE76: Yes | AF76: None | AG76: 360° | AH76: Panoramic | AI76: No | AJ76: Not stated | AK76: 120 | AL76: 103.8 | AM76: =IF(OR(S76="",AL76=""),"",100/S76/AL76*60) -> 8.50051 | AN76: 11.7 | AP76: Lifetime (1st owner) | AQ76: Not tested | AT76: 4 | AV76: No Bharat NCAP crash test; Wall charger not in price (~₹49,000)
A77: TATA-SIERRAEV-EMPOWERED63-63 | B77: V072 | C77: Tata | D77: Sierra.ev | E77: SUV | F77: Empowered 63 | G77: battery included | H77: 2279000 | I77: verified | J77: 63 | K77: RWD | L77: 5 | M77: 5 | N77: 566 | O77: MIDC Part 1 + Part 2 | P77: 440 | S77: 6.98 | T77: Maker real-world claim (estimate) | U77: =IF(S77="","",((1-Assumptions!$B$4)*Assumptions!$B$2+Assumptions!$B$4*Assumptions!$B$3)/S77) -> 1.3467049 | V77: =IF(U77="","",U77*Assumptions!$B$5*365*Assumptions!$B$6) -> 98309.456 | W77: No | X77: 49000 | Y77: Tata 'ACFC' option price | Z77: =IF(OR(G77<>"battery included",H77="",V77=""),"",H77+X77+V77) -> 2426309.5 | AA77: 622 | AB77: 205 | AD77: 6 | AE77: Yes | AF77: None | AG77: 360° | AH77: Panoramic | AI77: Yes | AJ77: Not stated | AK77: 110 | AL77: 90.7 | AM77: =IF(OR(S77="",AL77=""),"",100/S77/AL77*60) -> 9.4773854 | AN77: 9.9 | AP77: Lifetime (1st owner) | AQ77: Not tested | AT77: 4 | AV77: No Bharat NCAP crash test; Wall charger not in price (~₹49,000)
A78: TATA-SIERRAEV-EMPOWERED75-75 | B78: V073 | C78: Tata | D78: Sierra.ev | E78: SUV | F78: Empowered 75 | G78: battery included | H78: 2379000 | I78: verified | J78: 75 | K78: RWD | L78: 5 | M78: 5 | N78: 665 | O78: MIDC Part 1 + Part 2 | P78: 510 | S78: 6.8 | T78: Maker real-world claim (estimate) | U78: =IF(S78="","",((1-Assumptions!$B$4)*Assumptions!$B$2+Assumptions!$B$4*Assumptions!$B$3)/S78) -> 1.3823529 | V78: =IF(U78="","",U78*Assumptions!$B$5*365*Assumptions!$B$6) -> 100911.76 | W78: No | X78: 49000 | Y78: Tata 'ACFC' option price | Z78: =IF(OR(G78<>"battery included",H78="",V78=""),"",H78+X78+V78) -> 2528911.8 | AA78: 622 | AB78: 205 | AD78: 6 | AE78: Yes | AF78: None | AG78: 360° | AH78: Panoramic | AI78: Yes | AJ78: Not stated | AK78: 120 | AL78: 103.8 | AM78: =IF(OR(S78="",AL78=""),"",100/S78/AL78*60) -> 8.50051 | AN78: 11.7 | AP78: Lifetime (1st owner) | AQ78: Not tested | AT78: 4 | AV78: No Bharat NCAP crash test; Wall charger not in price (~₹49,000)
A79: TATA-SIERRAEV-EMPOWEREDA75-75 | B79: V074 | C79: Tata | D79: Sierra.ev | E79: SUV | F79: Empowered A 75 | G79: battery included | H79: 2479000 | I79: verified | J79: 75 | K79: RWD | L79: 5 | M79: 5 | N79: 665 | O79: MIDC Part 1 + Part 2 | P79: 510 | S79: 6.8 | T79: Maker real-world claim (estimate) | U79: =IF(S79="","",((1-Assumptions!$B$4)*Assumptions!$B$2+Assumptions!$B$4*Assumptions!$B$3)/S79) -> 1.3823529 | V79: =IF(U79="","",U79*Assumptions!$B$5*365*Assumptions!$B$6) -> 100911.76 | W79: No | X79: 49000 | Y79: Tata 'ACFC' option price | Z79: =IF(OR(G79<>"battery included",H79="",V79=""),"",H79+X79+V79) -> 2628911.8 | AA79: 622 | AB79: 205 | AD79: 6 | AE79: Yes | AF79: L2+ | AG79: 540° | AH79: Panoramic | AI79: Yes | AJ79: Not stated | AK79: 120 | AL79: 103.8 | AM79: =IF(OR(S79="",AL79=""),"",100/S79/AL79*60) -> 8.50051 | AN79: 11.7 | AP79: Lifetime (1st owner) | AQ79: Not tested | AT79: 4 | AV79: No Bharat NCAP crash test; Wall charger not in price (~₹49,000)
A80: TATA-SIERRAEV-EMPOWEREDAQWD75-75-AWD | B80: V075 | C80: Tata | D80: Sierra.ev | E80: SUV | F80: Empowered A QWD 75 (AWD) | G80: battery included | H80: 2599000 | I80: verified | J80: 75 | K80: AWD | L80: 5 | M80: 5 | N80: 624 | O80: MIDC Part 1 + Part 2 | P80: 480 | S80: 6.4 | T80: Maker real-world claim (estimate) | U80: =IF(S80="","",((1-Assumptions!$B$4)*Assumptions!$B$2+Assumptions!$B$4*Assumptions!$B$3)/S80) -> 1.46875 | V80: =IF(U80="","",U80*Assumptions!$B$5*365*Assumptions!$B$6) -> 107218.75 | W80: No | X80: 49000 | Y80: Tata 'ACFC' option price | Z80: =IF(OR(G80<>"battery included",H80="",V80=""),"",H80+X80+V80) -> 2755218.8 | AA80: 622 | AB80: 205 | AD80: 6 | AE80: Yes | AF80: L2+ | AG80: 540° | AH80: Panoramic | AI80: Yes | AJ80: Not stated | AK80: 120 | AL80: 103.8 | AM80: =IF(OR(S80="",AL80=""),"",100/S80/AL80*60) -> 9.0317919 | AN80: 11.7 | AP80: Lifetime (1st owner) | AQ80: Not tested | AT80: 6 | AV80: No Bharat NCAP crash test; Wall charger not in price (~₹49,000)
A81: TATA-TIAGOEV-SMART19-192 | B81: V076 | C81: Tata | D81: Tiago.ev | E81: Hatchback | F81: Smart 19 | G81: battery included | H81: 699000 | I81: verified | J81: 19.2 | K81: Not stated | L81: 5 | M81: 5 | N81: 226 | O81: ARAI certified (cycle not stated) | P81: 160 | S81: 8.33 | T81: Maker real-world claim (estimate) | U81: =IF(S81="","",((1-Assumptions!$B$4)*Assumptions!$B$2+Assumptions!$B$4*Assumptions!$B$3)/S81) -> 1.1284514 | V81: =IF(U81="","",U81*Assumptions!$B$5*365*Assumptions!$B$6) -> 82376.951 | W81: Yes (3.3 kW) | X81: 0 | Y81: 3.3 kW box included; 7.2 kW optional | Z81: =IF(OR(G81<>"battery included",H81="",V81=""),"",H81+X81+V81) -> 781376.95 | AA81: 240 | AD81: 6 | AE81: Not listed | AF81: Not stated | AG81: Sensors only | AH81: Not stated | AI81: Not stated | AJ81: Not stated | AL81: 23 | AM81: =IF(OR(S81="",AL81=""),"",100/S81/AL81*60) -> 31.316875 | AN81: 2.9 | AP81: 8 yrs / 1.6L km | AQ81: Not tested | AV81: ESP not listed; No Bharat NCAP crash test; Battery warranty 8 yrs/1.6L km (not lifetime); Slow DC fast-charging
A82: TATA-TIAGOEV-PUREPLUS19-192 | B82: V077 | C82: Tata | D82: Tiago.ev | E82: Hatchback | F82: Pure+ 19 | G82: battery included | H82: 864000 | I82: verified | J82: 19.2 | K82: Not stated | L82: 5 | M82: 5 | N82: 226 | O82: ARAI certified (cycle not stated) | P82: 160 | S82: 8.33 | T82: Maker real-world claim (estimate) | U82: =IF(S82="","",((1-Assumptions!$B$4)*Assumptions!$B$2+Assumptions!$B$4*Assumptions!$B$3)/S82) -> 1.1284514 | V82: =IF(U82="","",U82*Assumptions!$B$5*365*Assumptions!$B$6) -> 82376.951 | W82: Yes (3.3 kW) | X82: 0 | Y82: 3.3 kW box included; 7.2 kW optional | Z82: =IF(OR(G82<>"battery included",H82="",V82=""),"",H82+X82+V82) -> 946376.95 | AA82: 240 | AD82: 6 | AE82: Not listed | AF82: Not stated | AG82: Rear camera | AH82: Not stated | AI82: Not stated | AJ82: Not stated | AL82: 23 | AM82: =IF(OR(S82="",AL82=""),"",100/S82/AL82*60) -> 31.316875 | AN82: 2.9 | AP82: 8 yrs / 1.6L km | AQ82: Not tested | AV82: ESP not listed; No Bharat NCAP crash test; Battery warranty 8 yrs/1.6L km (not lifetime); Slow DC fast-charging
A83: TATA-TIAGOEV-PUREPLUS24-24 | B83: V078 | C83: Tata | D83: Tiago.ev | E83: Hatchback | F83: Pure+ 24 | G83: battery included | H83: 964000 | I83: verified | J83: 24 | K83: Not stated | L83: 5 | M83: 5 | N83: 285 | O83: ARAI certified (cycle not stated) | P83: 205 | Q83: 187 | R83: 66 | S83: 7.77 | T83: Independent test | U83: =IF(S83="","",((1-Assumptions!$B$4)*Assumptions!$B$2+Assumptions!$B$4*Assumptions!$B$3)/S83) -> 1.2097812 | V83: =IF(U83="","",U83*Assumptions!$B$5*365*Assumptions!$B$6) -> 88314.028 | W83: Yes (3.3 kW) | X83: 0 | Y83: 3.3 kW box included; 7.2 kW optional | Z83: =IF(OR(G83<>"battery included",H83="",V83=""),"",H83+X83+V83) -> 1052314 | AA83: 240 | AD83: 6 | AE83: Not listed | AF83: Not stated | AG83: Rear camera | AH83: Not stated | AI83: Not stated | AJ83: Not stated | AL83: 28.8 | AM83: =IF(OR(S83="",AL83=""),"",100/S83/AL83*60) -> 26.812527 | AN83: 3.9 | AP83: Lifetime (1st owner) | AQ83: Not tested | AV83: ESP not listed; No Bharat NCAP crash test; Tested range only 66% of claim; Slow DC fast-charging
A84: TATA-TIAGOEV-CREATIVEPLUS24-24 | B84: V079 | C84: Tata | D84: Tiago.ev | E84: Hatchback | F84: Creative+ 24 | G84: battery included | H84: 1009000 | I84: verified | J84: 24 | K84: Not stated | L84: 5 | M84: 5 | N84: 285 | O84: ARAI certified (cycle not stated) | P84: 205 | Q84: 187 | R84: 66 | S84: 7.77 | T84: Independent test | U84: =IF(S84="","",((1-Assumptions!$B$4)*Assumptions!$B$2+Assumptions!$B$4*Assumptions!$B$3)/S84) -> 1.2097812 | V84: =IF(U84="","",U84*Assumptions!$B$5*365*Assumptions!$B$6) -> 88314.028 | W84: Yes (3.3 kW) | X84: 0 | Y84: 3.3 kW box included; 7.2 kW optional | Z84: =IF(OR(G84<>"battery included",H84="",V84=""),"",H84+X84+V84) -> 1097314 | AA84: 240 | AD84: 6 | AE84: Yes | AF84: Not stated | AG84: 360° | AH84: Not stated | AI84: Not stated | AJ84: Not stated | AL84: 28.8 | AM84: =IF(OR(S84="",AL84=""),"",100/S84/AL84*60) -> 26.812527 | AN84: 3.9 | AP84: Lifetime (1st owner) | AQ84: Not tested | AV84: No Bharat NCAP crash test; Tested range only 66% of claim; Slow DC fast-charging
A85: TATA-TIGOREV-XE-26 | B85: V080 | C85: Tata | D85: Tigor.ev | E85: Sedan | F85: XE | G85: battery included | H85: 1249000 | I85: verified | J85: 26 | K85: FWD | L85: 5 | M85: 5 | N85: 315 | O85: ARAI certified (cycle not stated) | Q85: 190 | R85: 60 | S85: 7.29 | T85: Independent test | U85: =IF(S85="","",((1-Assumptions!$B$4)*Assumptions!$B$2+Assumptions!$B$4*Assumptions!$B$3)/S85) -> 1.2894376 | V85: =IF(U85="","",U85*Assumptions!$B$5*365*Assumptions!$B$6) -> 94128.944 | W85: Yes (3.3 kW) | X85: 0 | Y85: 3.3 kW box included; 7.2 kW optional | Z85: =IF(OR(G85<>"battery included",H85="",V85=""),"",H85+X85+V85) -> 1343128.9 | AA85: 316 | AD85: 2 | AE85: Not listed | AF85: None | AG85: Sensors only | AH85: Not stated | AI85: Not stated | AJ85: Not stated | AL85: 18.5 | AM85: =IF(OR(S85="",AL85=""),"",100/S85/AL85*60) -> 44.488933 | AN85: 10.4 | AP85: 8 yrs / 1.6L km | AQ85: Not tested | AV85: ESP not listed; No Bharat NCAP crash test; Battery warranty 8 yrs/1.6L km (not lifetime); Tested range only 60% of claim; Slow DC fast-charging
A86: TATA-TIGOREV-XT-26 | B86: V081 | C86: Tata | D86: Tigor.ev | E86: Sedan | F86: XT | G86: battery included | H86: 1299000 | I86: verified | J86: 26 | K86: FWD | L86: 5 | M86: 5 | N86: 315 | O86: ARAI certified (cycle not stated) | Q86: 190 | R86: 60 | S86: 7.29 | T86: Independent test | U86: =IF(S86="","",((1-Assumptions!$B$4)*Assumptions!$B$2+Assumptions!$B$4*Assumptions!$B$3)/S86) -> 1.2894376 | V86: =IF(U86="","",U86*Assumptions!$B$5*365*Assumptions!$B$6) -> 94128.944 | W86: Yes (3.3 kW) | X86: 0 | Y86: 3.3 kW box included; 7.2 kW optional | Z86: =IF(OR(G86<>"battery included",H86="",V86=""),"",H86+X86+V86) -> 1393128.9 | AA86: 316 | AD86: 2 | AE86: Not listed | AF86: None | AG86: Sensors only | AH86: Not stated | AI86: Not stated | AJ86: Not stated | AL86: 18.5 | AM86: =IF(OR(S86="",AL86=""),"",100/S86/AL86*60) -> 44.488933 | AN86: 10.4 | AP86: 8 yrs / 1.6L km | AQ86: Not tested | AV86: ESP not listed; No Bharat NCAP crash test; Battery warranty 8 yrs/1.6L km (not lifetime); Tested range only 60% of claim; Slow DC fast-charging
A87: TATA-TIGOREV-XZPLUS-26 | B87: V082 | C87: Tata | D87: Tigor.ev | E87: Sedan | F87: XZ+ | G87: battery included | H87: 1349000 | I87: verified | J87: 26 | K87: FWD | L87: 5 | M87: 5 | N87: 315 | O87: ARAI certified (cycle not stated) | Q87: 190 | R87: 60 | S87: 7.29 | T87: Independent test | U87: =IF(S87="","",((1-Assumptions!$B$4)*Assumptions!$B$2+Assumptions!$B$4*Assumptions!$B$3)/S87) -> 1.2894376 | V87: =IF(U87="","",U87*Assumptions!$B$5*365*Assumptions!$B$6) -> 94128.944 | W87: Yes (3.3 kW) | X87: 0 | Y87: 3.3 kW box included; 7.2 kW optional | Z87: =IF(OR(G87<>"battery included",H87="",V87=""),"",H87+X87+V87) -> 1443128.9 | AA87: 316 | AD87: 2 | AE87: Not listed | AF87: None | AG87: Rear camera | AH87: Not stated | AI87: Not stated | AJ87: Not stated | AL87: 18.5 | AM87: =IF(OR(S87="",AL87=""),"",100/S87/AL87*60) -> 44.488933 | AN87: 10.4 | AP87: 8 yrs / 1.6L km | AQ87: Not tested | AV87: ESP not listed; No Bharat NCAP crash test; Battery warranty 8 yrs/1.6L km (not lifetime); Tested range only 60% of claim; Slow DC fast-charging
A88: TATA-TIGOREV-XZPLUSLUX-26 | B88: V083 | C88: Tata | D88: Tigor.ev | E88: Sedan | F88: XZ+ Lux | G88: battery included | H88: 1375000 | I88: verified | J88: 26 | K88: FWD | L88: 5 | M88: 5 | N88: 315 | O88: ARAI certified (cycle not stated) | Q88: 190 | R88: 60 | S88: 7.29 | T88: Independent test | U88: =IF(S88="","",((1-Assumptions!$B$4)*Assumptions!$B$2+Assumptions!$B$4*Assumptions!$B$3)/S88) -> 1.2894376 | V88: =IF(U88="","",U88*Assumptions!$B$5*365*Assumptions!$B$6) -> 94128.944 | W88: Yes (3.3 kW) | X88: 0 | Y88: 3.3 kW box included; 7.2 kW optional | Z88: =IF(OR(G88<>"battery included",H88="",V88=""),"",H88+X88+V88) -> 1469128.9 | AA88: 316 | AD88: 2 | AE88: Not listed | AF88: None | AG88: Rear camera | AH88: Not stated | AI88: Not stated | AJ88: Not stated | AL88: 18.5 | AM88: =IF(OR(S88="",AL88=""),"",100/S88/AL88*60) -> 44.488933 | AN88: 10.4 | AP88: 8 yrs / 1.6L km | AQ88: Not tested | AV88: ESP not listed; No Bharat NCAP crash test; Battery warranty 8 yrs/1.6L km (not lifetime); Tested range only 60% of claim; Slow DC fast-charging

Sheet Variant_Ladder
A1: model | B1: from_variant | C1: to_variant | D1: from_price_inr | E1: to_price_inr | F1: extra_cost_inr | G1: what_you_gain | H1: what_does_not_change | I1: factory_only_gains | J1: note
A2: BE 6 SPORTEQ | B2: One 59 kWh | C2: Two 59 kWh | D2: 1945000 | E2: 2095000 | F2: =E2-D2 -> 150000 | G2: Camera: Rear camera → 540°; Audio: 6 speakers → 16-speaker Harman Kardon, Dolby Atmos; Screens: Dual 31.24 cm → Triple 31.24 cm; Wheels: R18 steel, aero covers → R19 Versa steel, aero covers; Climate: Single zone auto, rear AC vents → Dual zone auto, rear AC vents | I2: None (accessories may cover some)
A3: BE 6 SPORTEQ | B3: Two 59 kWh | C3: Three 59 kWh | D3: 2095000 | E3: 2195000 | F3: =E3-D3 -> 100000 | G3: Sunroof: None → Panoramic; Vent. seats: No → Yes; Wheels: R19 Versa steel, aero covers → R19 alloy; Powered seat: no → yes (6-way) | I3: Sunroof, Vent. seats
A4: BE 6 SPORTEQ | B4: Three 59 kWh | C4: Three 70 kWh | D4: 2195000 | E4: 2295000 | F4: =E4-D4 -> 100000 | G4: Battery kWh: 59 → 70; Range km: 573 → 651 | I4: Battery kWh, Range km
A5: BE 6 SPORTEQ | B5: Three 70 kWh | C5: Three+ 70 kWh | D5: 2295000 | E5: 2395000 | F5: =E5-D5 -> 100000 | G5: ADAS: None → L2; Power tailgate: no → yes (gesture) | I5: ADAS
A6: BE 6 SPORTEQ | B6: Three+ 70 kWh | C6: FE 79 kWh | D6: 2395000 | E6: 2445000 | F6: =E6-D6 -> 50000 | G6: Battery kWh: 70 → 79; Range km: 651 → 708; ADAS: L2 → None; Vent. seats: Yes → No; Screens: Triple 31.24 cm → Dual 31.24 cm; Wheels: R19 alloy → R20 alloy; Power tailgate: yes (gesture) → no; Powered seat: yes (6-way) → no; Adaptive suspension: no → yes | I6: ADAS, Adaptive suspension, Battery kWh, Range km, Vent. seats
A7: BE 6 SPORTEQ | B7: FE 79 kWh | C7: Three+ 79 kWh | D7: 2445000 | E7: 2495000 | F7: =E7-D7 -> 50000 | G7: ADAS: None → L2; Vent. seats: No → Yes; Screens: Dual 31.24 cm → Triple 31.24 cm; Wheels: R20 alloy → R19 alloy; Power tailgate: no → yes (gesture); Powered seat: no → yes (6-way); Adaptive suspension: yes → no | I7: ADAS, Adaptive suspension, Vent. seats
A8: BE 6 SPORTEQ | B8: Three+ 79 kWh | C8: Four 79 kWh | D8: 2495000 | E8: 2695000 | F8: =E8-D8 -> 200000 | G8: ADAS: L2 → L2+; HUD: no → yes (AR HUD); Auto park: no → yes; Adaptive suspension: no → yes | I8: ADAS, Adaptive suspension, HUD
A9: BE 6 SPORTEQ | B9: Four 79 kWh | C9: FE Four 79 kWh | D9: 2695000 | E9: 2695000 | F9: =E9-D9 -> 0 | G9: Vent. seats: Yes → Not stated; Screens: Triple 31.24 cm → Dual 31.24 cm; Wheels: R19 alloy → R20 alloy; Powered seat: yes (6-way) → CHECK | I9: Vent. seats | J9: Same price
A10: BE 6 SPORTEQ | B10: FE Four 79 kWh | C10: Launch Edition 79 kWh | D10: 2695000 | E10: 2695000 | F10: =E10-D10 -> 0 | G10: Vent. seats: Not stated → Yes; Screens: Dual 31.24 cm → Triple 31.24 cm; Wheels: R20 alloy → R19 alloy; Powered seat: CHECK → yes (6-way) | I10: Vent. seats | J10: Same price
A11: Curvv.ev | B11: Accomplished X 55 | C11: Empowered X 55 | D11: 1719000 | E11: 1939000 | F11: =E11-D11 -> 220000 | G11: ADAS: None → L2; Vent. seats: Passive only → Yes; Charger in box: Unclear → Yes (7.2 kW); Audio: 4 speakers + 4 tweeters → JBL 9 speakers with subwoofer; Screens: 26.03 cm touchscreen + 26.03 cm cockpit → 31.24 cm touchscreen; Power tailgate: no → yes (gesture); Powered seat: — → 6-way powered; App suite: Not listed → Arcade.ev | I11: ADAS, Vent. seats
A12: Harrier.ev | B12: Adventure 65 | C12: Adventure S 65 | D12: 2179000 | E12: 2229000 | F12: =E12-D12 -> 50000 | G12: Sunroof: None → Panoramic; Screens: 26.03 cm touchscreen + 26.03 cm cockpit → 31.24 cm touchscreen + 26.03 cm cockpit; App suite: no → Arcade.ev | I12: Sunroof
A13: Harrier.ev | B13: Adventure S 65 | C13: Fearless+ 65 | D13: 2229000 | E13: 2429000 | F13: =E13-D13 -> 200000 | G13: Airbags: 6 → 7; Camera: Not stated → 360°; Vent. seats: No → Yes; Audio: Not listed → JBL Black 10 speakers incl. subwoofer; Climate: Single zone FATC → Dual zone FATC, voice assisted; Powered seat: no (8-way manual driver) → yes (6-way powered, memory, welcome retract); Wireless charger: — → yes | I13: Airbags, Vent. seats
A14: Harrier.ev | B14: Fearless+ 65 | C14: Fearless+ 75 | D14: 2429000 | E14: 2529000 | F14: =E14-D14 -> 100000 | G14: Battery kWh: 65 → 75; Range km: 538 → 627 | I14: Battery kWh, Range km
A15: Harrier.ev | B15: Fearless+ 75 | C15: Fearless+ QWD 75 (AWD) | D15: 2529000 | E15: 2679000 | F15: =E15-D15 -> 150000 | G15: Range km: 627 → 622; Drive: RWD → AWD; Terrain modes: 3 → 6 | I15: Drive, Range km, Terrain modes
A16: Harrier.ev | B16: Fearless+ QWD 75 (AWD) | C16: Empowered 75 | D16: 2679000 | E16: 2779000 | F16: =E16-D16 -> 100000 | G16: Range km: 622 → 627; Drive: AWD → RWD; ADAS: None → L2; Camera: 360° → 540°; Terrain modes: 6 → 4; Audio: JBL Black 10 speakers incl. subwoofer → JBL Black 10 speakers, Dolby Atmos; Screens: 31.24 cm touchscreen + 26.03 cm cockpit → 36.9 cm (14.53 in) Samsung Neo QLED touchscreen; Auto park: no → yes (15 features incl. Summon, Anywhere Parking); Power tailgate: no → yes (gesture) | I16: ADAS, Drive, Range km, Terrain modes
A17: Harrier.ev | B17: Empowered 75 | C17: Empowered QWD 75 (AWD) | D17: 2779000 | E17: 2929000 | F17: =E17-D17 -> 150000 | G17: Range km: 627 → 622; Drive: RWD → AWD; Terrain modes: 4 → 6 | I17: Drive, Range km, Terrain modes
A18: Nexon.ev | B18: Creative+ MR | C18: Fearless MR | D18: 1249000 | E18: 1329000 | F18: =E18-D18 -> 80000 | G18: Audio: 4 speakers → 4 speakers + 4 tweeters; Screens: 17.78 cm touchscreen → 26.03 cm touchscreen + 26.03 cm cockpit | I18: None (accessories may cover some)
A19: Nexon.ev | B19: Fearless MR | C19: Creative 45 | D19: 1329000 | E19: 1434000 | F19: =E19-D19 -> 105000 | G19: Battery kWh: 30 → 45; Range km: 275 → 489; Battery warranty: 8 yrs / 1.6L km → Lifetime (1st owner); Crash test: Rated, coverage unconfirmed → Rated, applies; Audio: 4 speakers + 4 tweeters → 4 speakers; Screens: 26.03 cm touchscreen + 26.03 cm cockpit → 17.78 cm touchscreen; Keyless: — → yes (PEPS) | I19: Battery kWh, Battery warranty, Range km
A20: Nexon.ev | B20: Creative 45 | C20: Fearless 45 | D20: 1434000 | E20: 1534000 | F20: =E20-D20 -> 100000 | G20: Audio: 4 speakers → 4 speakers + 4 tweeters; Screens: 17.78 cm touchscreen → 26.03 cm touchscreen + 26.03 cm cockpit | I20: None (accessories may cover some)
A21: Nexon.ev | B21: Fearless 45 | C21: Empowered 45 | D21: 1534000 | E21: 1634000 | F21: =E21-D21 -> 100000 | G21: Camera: Rear camera → 360°; Sunroof: None → Sunroof; Audio: 4 speakers + 4 tweeters → JBL audio modes; Upholstery: — → Leatherette; Cruise: — → Standard; Wireless charger: — → yes | I21: Sunroof
A22: Nexon.ev | B22: Empowered 45 | C22: Empowered+A 45 | D22: 1634000 | E22: 1769000 | F22: =E22-D22 -> 135000 | G22: ADAS: None → L2; Sunroof: Sunroof → Panoramic; Vent. seats: No → Yes; Charger in box: Not stated → Yes (7.2 kW); Audio: JBL audio modes → JBL 9-speaker with subwoofer; Screens: 26.03 cm touchscreen + 26.03 cm cockpit → 31.24 cm touchscreen + 26.03 cm cockpit; App suite: no → Arcade.ev | I22: ADAS, Sunroof, Vent. seats
... A42: XEV 9S | B42: Pack One Above 79 kWh | C42: Pack Two Above 70 kWh (7-seater) | D42: 2265000 | E42: 2505000 | F42: =E42-D42 -> 240000 | G42: Battery kWh: 79 → 70; Range km: 679 → 600; ADAS: None → L2; Camera: Rear camera → 360°; Vent. seats: No → Yes; Audio: 6 speakers → 16-speaker Harman Kardon, Dolby Atmos; Wheels: R18 stylised wheel → R18 alloy; Upholstery: Premium fabric → Leatherette; Climate: Single zone auto, rear AC vents → Dual zone auto, rear AC vents; Powered seat: no (6-way manual) → yes (6-way powered, memory); Cruise: Standard → Adaptive; Wireless charger: None → Front | I42: ADAS, Battery kWh, Range km, Vent. seats
A43: XEV 9S | B43: Pack Two Above 70 kWh (7-seater) | C43: Pack Two Above 70 kWh (6-seater) | D43: 2505000 | E43: 2525000 | F43: =E43-D43 -> 20000 | G43: Seats: 7 → 6 | I43: Seats | J43: Captain-seat version
A44: XEV 9S | B44: Pack Two Above 70 kWh (6-seater) | C44: Pack Two Above 79 kWh (7-seater) | D44: 2525000 | E44: 2595000 | F44: =E44-D44 -> 70000 | G44: Battery kWh: 70 → 79; Range km: 600 → 679; Seats: 6 → 7 | I44: Battery kWh, Range km, Seats
A45: XEV 9S | B45: Pack Two Above 79 kWh (7-seater) | C45: Pack Two Above 79 kWh (6-seater) | D45: 2595000 | E45: 2615000 | F45: =E45-D45 -> 20000 | G45: Seats: 7 → 6 | I45: Seats | J45: Captain-seat version
A46: XEV 9S | B46: Pack Two Above 79 kWh (6-seater) | C46: Pack Three 79 kWh (7-seater) | D46: 2615000 | E46: 2785000 | F46: =E46-D46 -> 170000 | G46: Seats: 6 → 7; Airbags: 6 → 7; ADAS: L2 → L2+; Keyless: no → yes; Wireless charger: Front → Front & rear; Adaptive suspension: no → yes | I46: ADAS, Adaptive suspension, Airbags, Seats
A47: XEV 9S | B47: Pack Three 79 kWh (7-seater) | C47: Pack Three 79 kWh (6-seater) | D47: 2785000 | E47: 2805000 | F47: =E47-D47 -> 20000 | G47: Seats: 7 → 6 | I47: Seats | J47: Captain-seat version
A48: XEV 9S | B48: Pack Three 79 kWh (6-seater) | C48: Pack Three Above 79 kWh (7-seater) | D48: 2805000 | E48: 2995000 | F48: =E48-D48 -> 190000 | G48: Seats: 6 → 7; HUD: no → yes (AR HUD); Auto park: no → yes | I48: HUD, Seats
A49: XEV 9S | B49: Pack Three Above 79 kWh (7-seater) | C49: Pack Three Above 79 kWh (6-seater) | D49: 2995000 | E49: 3015000 | F49: =E49-D49 -> 20000 | G49: Seats: 7 → 6 | I49: Seats | J49: Captain-seat version
A50: XEV 9e | B50: Pack One 59 kWh | C50: Pack Two 59 kWh | D50: 2190000 | E50: 2490000 | F50: =E50-D50 -> 300000 | G50: ADAS: None → L2; Audio: 6 speakers → 16-speaker Harman Kardon, Dolby Atmos; Wheels: R19 stylised wheel → R19 alloy; Upholstery: Premium fabric → Leatherette; Climate: Single zone auto, rear AC vents → Dual zone auto, rear AC vents; Powered seat: no (6-way manual) → yes (6-way powered, memory); Cruise: Standard → Adaptive; Wireless charger: None → Front | I50: ADAS
A51: XEV 9e | B51: Pack Two 59 kWh | C51: Pack Two 79 kWh | D51: 2490000 | E51: 2650000 | F51: =E51-D51 -> 160000 | G51: Battery kWh: 59 → 79; Range km: 522 → 656 | I51: Battery kWh, Range km
A52: XEV 9e | B52: Pack Two 79 kWh | C52: Pack Three Select 59 kWh | D52: 2650000 | E52: 2790000 | F52: =E52-D52 -> 140000 | G52: Battery kWh: 79 → 59; Range km: 656 → 522; Airbags: 6 → 7; Camera: Rear camera → 360°; Vent. seats: No → Yes; Auto park: no → yes; Power tailgate: no → yes (gesture); Keyless: no → yes; Wireless charger: Front → Front & rear; Adaptive suspension: no → yes | I52: Adaptive suspension, Airbags, Battery kWh, Range km, Vent. seats
A53: XEV 9e | B53: Pack Three Select 59 kWh | C53: Cineluxe 79 kWh | D53: 2790000 | E53: 2935000 | F53: =E53-D53 -> 145000 | G53: Battery kWh: 59 → 79; Range km: 522 → 656; Airbags: 7 → None; ESP: Yes → Not stated; ADAS: L2 → Not stated; Camera: 360° → Not stated; Vent. seats: Yes → Not stated; Screens: — → Coast-to-coast HD screens; Wheels: R19 alloy → R19; Upholstery: Leatherette → Distinct leatherette (Cineluxe-specific); App suite: Fun&Work (60+ in-built apps) → Not stated for Cineluxe | I53: ADAS, Airbags, Battery kWh, ESP, Range km, Vent. seats
A54: XEV 9e | B54: Cineluxe 79 kWh | C54: Pack Three 79 kWh | D54: 2935000 | E54: 3050000 | F54: =E54-D54 -> 115000 | G54: Airbags: None → 7; ESP: Not stated → Yes; ADAS: Not stated → L2+; Camera: Not stated → 360°; Vent. seats: Not stated → Yes; Wheels: R19 → R19 alloy; HUD: — → yes (AR HUD); Auto park: — → yes; Power tailgate: — → yes (gesture); Upholstery: Distinct leatherette (Cineluxe-specific) → Leatherette; Climate: — → Dual zone auto, rear AC vents; Powered seat: — → yes (6-way powered, memory); Cruise: — → Adaptive; Keyless: — → yes; Wireless charger: — → Front & rear; App suite: Not stated for Cineluxe → Fun&Work (60+ in-built apps) | I54: ADAS, Airbags, ESP, HUD, Vent. seats
A55: XUV 3XO EV | B55: AX5 39.4 kWh | C55: AX7L 39.4 kWh | D55: 1389000 | E55: 1496000 | F55: =E55-D55 -> 107000 | G55: ADAS: None → L2; Camera: Rear camera → 360°; Sunroof: Sunroof → Panoramic; Audio: 6 speakers → 7-speaker Harman Kardon with subwoofer, Dolby Atmos; Wheels: R16 diamond-cut alloy → R17 diamond-cut alloy; Upholstery: Not leatherette (AX7L adds leatherette seats) → Leatherette | I55: ADAS, Sunroof

Sheet Test_Cases
A1: buyer_profile | B1: rank | C1: variant | D1: price_inr | E1: 5yr_cost_inr (40 km/day, ₹9.4/kWh) | F1: why_it_fits | G1: watch_outs | H1: cheaper_alternative_note
A2: First EV, city commute, tight budget | B2: 1 | C2: Tiago.ev Smart 19 | D2: 699000 | E2: 781377 | F2: Tiago.ev Hatchback, 5 seats, claimed 226 km, maker real-world 160+ km, ESP Not listed, ADAS Not stated, camera Sensors only, NCAP Not tested | G2: ESP not listed; No Bharat NCAP crash test; Battery warranty 8 yrs/1.6L km (not lifetime); Slow DC fast-charging
B3: 2 | C3: Tiago.ev Pure+ 19 | D3: 864000 | E3: 946377 | F3: Tiago.ev Hatchback, 5 seats, claimed 226 km, maker real-world 160+ km, ESP Not listed, ADAS Not stated, camera Rear camera, NCAP Not tested | G3: ESP not listed; No Bharat NCAP crash test; Battery warranty 8 yrs/1.6L km (not lifetime); Slow DC fast-charging
B4: 3 | C4: Tiago.ev Pure+ 24 | D4: 964000 | E4: 1052314 | F4: Tiago.ev Hatchback, 5 seats, claimed 285 km, tested 187 km, ESP Not listed, ADAS Not stated, camera Rear camera, NCAP Not tested | G4: ESP not listed; No Bharat NCAP crash test; Tested range only 66% of claim; Slow DC fast-charging
A5: Family of 5, safety first, ₹16L | B5: 1 | C5: Punch.ev Smart 30 | D5: 979000 | E5: 1058146 | F5: Punch.ev SUV, 5 seats, claimed 365 km, maker real-world 260+ km, ESP Yes, ADAS None, camera Sensors only, NCAP Rated, applies | G5: Battery warranty 8 yrs/1.6L km (not lifetime)
B6: 2 | C6: Punch.ev Smart+ 30 | D6: 1039000 | E6: 1118146 | F6: Punch.ev SUV, 5 seats, claimed 365 km, maker real-world 260+ km, ESP Yes, ADAS None, camera Sensors only, NCAP Rated, applies | G6: Battery warranty 8 yrs/1.6L km (not lifetime)
B7: 3 | C7: Punch.ev Smart+ 40 | D7: 1119000 | E7: 1209171 | F7: Punch.ev SUV, 5 seats, claimed 468 km, tested 304 km, ESP Yes, ADAS None, camera Rear camera, NCAP Rated, applies | G7: Tested range only 65% of claim
A8: Long highway trips, ₹25L, wants real range 400+ km | B8: 1 | C8: XEV 9S Pack One Above 79 kWh | D8: 2265000 | E8: 2433404 | F8: XEV 9S SUV, 7 seats, claimed 679 km, tested 478 km, ESP Yes, ADAS None, camera Rear camera, NCAP Not tested | G8: No Bharat NCAP crash test; Wall charger not in price (~₹60,000); Price corroborated, confirm before buying | H8: Cheapest that still meets must-haves: Sierra.ev Adventure 75 at ₹2,219,000 (saves ₹46,000); see Variant_Ladder for what you give up
B9: 2 | C9: BE 6 SPORTEQ Three+ 79 kWh | D9: 2495000 | E9: 2675810 | F9: BE 6 SPORTEQ SUV, 5 seats, claimed 708 km, tested 449 km, ESP Yes, ADAS L2, camera 540°, NCAP Rated, coverage unconfirmed | G9: Crash rating may not cover this version; Tested range only 63% of claim; Wall charger not in price (~₹60,000); Price corroborated, confirm before buying
B10: 3 | C10: BE 6 SPORTEQ FE 79 kWh | D10: 2445000 | E10: 2625810 | F10: BE 6 SPORTEQ SUV, 5 seats, claimed 708 km, tested 449 km, ESP Yes, ADAS None, camera 540°, NCAP Rated, coverage unconfirmed | G10: Crash rating may not cover this version; Tested range only 63% of claim; Wall charger not in price (~₹60,000); Price corroborated, confirm before buying
A11: Big family, 7 seats, ₹27L | B11: 1 | C11: XEV 9S Pack One Above 59 kWh | D11: 2065000 | E11: 2226209 | F11: XEV 9S SUV, 7 seats, claimed 521 km, maker real-world 400+ km, ESP Yes, ADAS None, camera Rear camera, NCAP Not tested | G11: No Bharat NCAP crash test; Wall charger not in price (~₹60,000); Price corroborated, confirm before buying
B12: 2 | C12: XEV 9S Pack One Above 79 kWh | D12: 2265000 | E12: 2433404 | F12: XEV 9S SUV, 7 seats, claimed 679 km, tested 478 km, ESP Yes, ADAS None, camera Rear camera, NCAP Not tested | G12: No Bharat NCAP crash test; Wall charger not in price (~₹60,000); Price corroborated, confirm before buying
B13: 3 | C13: XEV 9S Pack Two Above 70 kWh (7-seater) | D13: 2505000 | E13: 2671719 | F13: XEV 9S SUV, 7 seats, claimed 600 km, maker real-world 450+ km, ESP Yes, ADAS L2, camera 360°, NCAP Not tested | G13: No Bharat NCAP crash test; Wall charger not in price (~₹60,000); Price corroborated, confirm before buying
A14: Weekend off-road / bad roads, ₹27L | B14: 1 | C14: Sierra.ev Adventure 63 | D14: 2099000 | E14: 2246309 | F14: Sierra.ev SUV, 5 seats, claimed 566 km, maker real-world 440+ km, ESP Yes, ADAS None, camera 360°, NCAP Not tested | G14: No Bharat NCAP crash test; Wall charger not in price (~₹49,000)
B15: 2 | C15: Sierra.ev Adventure 75 | D15: 2219000 | E15: 2368912 | F15: Sierra.ev SUV, 5 seats, claimed 665 km, maker real-world 510+ km, ESP Yes, ADAS None, camera 360°, NCAP Not tested | G15: No Bharat NCAP crash test; Wall charger not in price (~₹49,000)
B16: 3 | C16: Sierra.ev Empowered 63 | D16: 2279000 | E16: 2426309 | F16: Sierra.ev SUV, 5 seats, claimed 566 km, maker real-world 440+ km, ESP Yes, ADAS None, camera 360°, NCAP Not tested | G16: No Bharat NCAP crash test; Wall charger not in price (~₹49,000)
A17: Wants ADAS + 360 camera, ₹18L | B17: 1 | C17: XUV 3XO EV AX7L 39.4 kWh | D17: 1496000 | E17: 1650910 | F17: XUV 3XO EV SUV, 5 seats, claimed 351 km, maker real-world 285+ km, ESP Yes, ADAS L2, camera 360°, NCAP Not tested | G17: No Bharat NCAP crash test; Onboard charger 6.6 kW: a 7.2 kW wall box won't charge faster; Wall charger not in price (~₹60,000); Price corroborated, confirm before buying; Slow DC fast-charging
B18: 2 | C18: Nexon.ev Empowered+A 45 | D18: 1769000 | E18: 1857087 | F18: Nexon.ev SUV, 5 seats, claimed 489 km, tested 350 km, ESP Yes, ADAS L2, camera 360°, NCAP Rated, applies | G18: None flagged
A20: Static snapshot computed with default assumptions by the build script, to sanity-check engine logic. Ranking: lowest 5-yr cost among variants meeting budget, seats and must-haves (range profile ranks by real-world range).

Sheet Engine_Rules
A1: rule | B1: detail
A2: ROLE SPLIT | B2: LLM: understand the buyer and explain results. Code: filter, rank and compute from Engine_Variants. The LLM never invents a number.
A3: STEP 1 Hard filters | B3: Budget (price_inr + charger_cost_inr if no charger), seats, body_type, must-have features. Treat 'Not stated' as unknown: never silently pass or fail it; ask or flag.
A4: STEP 2 Usage fit | B4: Daily km vs range_tested_km, else range_maker_realworld_km (never range_claimed_km alone). Home charging: if none, weight dc_avg_kw_est and minutes_dc_per_100km.
A5: STEP 3 Rank | B5: Default: lowest cost_to_own_period_inr. Range-led buyers: real-world range. Safety-led: ncap_adult_32, then ESP/airbags/ADAS.
A6: STEP 4 Always show | B6: Top 2-3 picks + one cheaper alternative (Variant_Ladder: what you give up) + watch_outs for each pick + price_status.
A7: STEP 5 Accessories | B7: Only suggest genuine accessories with equivalence 'same' or 'close' to fill a gap, with price. Never aftermarket. Never present a lower variant + accessories as equal to a higher variant.
A8: NEVER | B8: Apply a petrol/diesel crash rating to an EV. Quote BaaS price as the car's price without the battery loan. Present maker 'real-world' range as independent. Use a 'pending' value without saying so.
A9: CONFIDENCE | B9: verified = official; corroborated = 2+ independent sources; pending = say 'unconfirmed'. Independent test data always labelled as such.
A10: WHEN NOTHING FITS | B10: Say so plainly, show the nearest option above budget and what extra it costs. Don't stretch filters silently.
A11: DATA SCOPE | B11: Mahindra (BE 6 SPORTEQ, XEV 9e, XEV 9S, XUV 3XO EV) and Tata (Tiago.ev, Tigor.ev, Punch.ev, Nexon.ev, Curvv.ev, Harrier.ev, Sierra.ev). Tell users other brands aren't covered yet.
A12: COSTS NOT INCLUDED | B12: Registration, insurance, service, financing, resale, current offers/discounts (Tata running offers Oct 2026, see Q067).

Sheet Variants
A1: variant_id | B1: manufacturer | C1: model | D1: body_type | E1: model_year | F1: trim | G1: battery_kwh | H1: variant_name | I1: pricing_type | J1: ex_showroom_inr | K1: claimed_range_km | L1: range_standard | M1: source_id | N1: status | O1: official_price_inr | P1: official_battery_kwh | Q1: official_range_km | R1: price_match | S1: battery_match | T1: range_match | U1: checked_by | V1: date_checked | W1: notes
A2: V001 | B2: Mahindra | C2: BE 6 SPORTEQ | D2: SUV | E2: 2026 | F2: One | G2: 59 | H2: One 59 kWh | I2: battery included | J2: 1945000 | K2: 573 | L2: MIDC Part 1 + Part 2 | M2: S011 (price), S009 (battery, range) | N2: verified | O2: 1945000 | P2: 59 | Q2: 573 | R2: =IF(O2="","",IF(O2=J2,"Match","MISMATCH")) -> Match | S2: =IF(P2="","",IF(P2=G2,"Match","MISMATCH")) -> Match | T2: =IF(Q2="","",IF(Q2=K2,"Match","MISMATCH")) -> Match | U2: Claude | V2: 2026-10-22
A3: V002 | B3: Mahindra | C3: BE 6 SPORTEQ | D3: SUV | E3: 2026 | F3: One | G3: 59 | H3: One 59 kWh BaaS | I3: BaaS | J3: 1145000 | K3: 573 | L3: MIDC Part 1 + Part 2 | M3: S010 (price), S009 (battery, range) | N3: verified | O3: 1145000 | P3: 59 | Q3: 573 | R3: =IF(O3="","",IF(O3=J3,"Match","MISMATCH")) -> Match | S3: =IF(P3="","",IF(P3=G3,"Match","MISMATCH")) -> Match | T3: =IF(Q3="","",IF(Q3=K3,"Match","MISMATCH")) -> Match | U3: Claude | V3: 2026-10-22 | W3: Chassis price only. Battery is bought on a separate loan (up to 8 yrs). NOT pay-per-km.
A4: V003 | B4: Mahindra | C4: BE 6 SPORTEQ | D4: SUV | E4: 2026 | F4: Two | G4: 59 | H4: Two 59 kWh | I4: battery included | J4: 2095000 | K4: 573 | L4: MIDC Part 1 + Part 2 | M4: S001 (news) + S014 (chatbot) for price, S009 (battery, range) | N4: corroborated | P4: 59 | Q4: 573 | R4: =IF(O4="","",IF(O4=J4,"Match","MISMATCH")) | S4: =IF(P4="","",IF(P4=G4,"Match","MISMATCH")) -> Match | T4: =IF(Q4="","",IF(Q4=K4,"Match","MISMATCH")) -> Match | U4: Claude | V4: 2026-10-22 | W4: Price: news and Mahindra chatbot agree, and BaaS + battery value pattern holds. Dealer price list to confirm.; Mahindra chatbot (23 Oct) gives the same price again.; Corroborated: Autocar, TimesDrive, Cars24 and Mahindra chatbot agree.
A5: V004 | B5: Mahindra | C5: BE 6 SPORTEQ | D5: SUV | E5: 2026 | F5: Two | G5: 59 | H5: Two 59 kWh BaaS | I5: BaaS | J5: 1295000 | K5: 573 | L5: MIDC Part 1 + Part 2 | M5: S010 (price), S009 (battery, range) | N5: verified | O5: 1295000 | P5: 59 | Q5: 573 | R5: =IF(O5="","",IF(O5=J5,"Match","MISMATCH")) -> Match | S5: =IF(P5="","",IF(P5=G5,"Match","MISMATCH")) -> Match | T5: =IF(Q5="","",IF(Q5=K5,"Match","MISMATCH")) -> Match | U5: Claude | V5: 2026-10-22 | W5: Chassis price only. Battery is bought on a separate loan (up to 8 yrs). NOT pay-per-km.
A6: V005 | B6: Mahindra | C6: BE 6 SPORTEQ | D6: SUV | E6: 2026 | F6: Three | G6: 59 | H6: Three 59 kWh | I6: battery included | J6: 2195000 | K6: 573 | L6: MIDC Part 1 + Part 2 | M6: S001 (news) + S014 (chatbot) for price, S009 (battery, range) | N6: corroborated | P6: 59 | Q6: 573 | R6: =IF(O6="","",IF(O6=J6,"Match","MISMATCH")) | S6: =IF(P6="","",IF(P6=G6,"Match","MISMATCH")) -> Match | T6: =IF(Q6="","",IF(Q6=K6,"Match","MISMATCH")) -> Match | U6: Claude | V6: 2026-10-22 | W6: Price: news and Mahindra chatbot agree, and BaaS + battery value pattern holds. Dealer price list to confirm.; Mahindra chatbot (23 Oct) gives the same price again.; Corroborated: Autocar, TimesDrive, Cars24 and Mahindra chatbot agree.
A7: V006 | B7: Mahindra | C7: BE 6 SPORTEQ | D7: SUV | E7: 2026 | F7: Three | G7: 59 | H7: Three 59 kWh BaaS | I7: BaaS | J7: 1395000 | K7: 573 | L7: MIDC Part 1 + Part 2 | M7: S010 (price), S009 (battery, range) | N7: verified | O7: 1395000 | P7: 59 | Q7: 573 | R7: =IF(O7="","",IF(O7=J7,"Match","MISMATCH")) -> Match | S7: =IF(P7="","",IF(P7=G7,"Match","MISMATCH")) -> Match | T7: =IF(Q7="","",IF(Q7=K7,"Match","MISMATCH")) -> Match | U7: Claude | V7: 2026-10-22 | W7: Chassis price only. Battery is bought on a separate loan (up to 8 yrs). NOT pay-per-km.
A8: V007 | B8: Mahindra | C8: BE 6 SPORTEQ | D8: SUV | E8: 2026 | F8: Three | G8: 70 | H8: Three 70 kWh | I8: battery included | J8: 2295000 | K8: 651 | L8: MIDC Part 1 + Part 2 | M8: S001 (news) + S014 (chatbot) for price, S009 (battery, range) | N8: corroborated | P8: 70 | Q8: 651 | R8: =IF(O8="","",IF(O8=J8,"Match","MISMATCH")) | S8: =IF(P8="","",IF(P8=G8,"Match","MISMATCH")) -> Match | T8: =IF(Q8="","",IF(Q8=K8,"Match","MISMATCH")) -> Match | U8: Claude | V8: 2026-10-22 | W8: Price: news and Mahindra chatbot agree, and BaaS + battery value pattern holds. Dealer price list to confirm.; Range 651 km per Mahindra website (S011); brochure says 652 km. Website figure chosen by Madhu, see Q003.; Mahindra chatbot (23 Oct) gives the same price again.; Corroborated: Autocar, TimesDrive, Cars24 and Mahindra chatbot agree.
A9: V008 | B9: Mahindra | C9: BE 6 SPORTEQ | D9: SUV | E9: 2026 | F9: Three | G9: 70 | H9: Three 70 kWh BaaS | I9: BaaS | J9: 1395000 | K9: 651 | L9: MIDC Part 1 + Part 2 | M9: S010 (price), S009 (battery, range) | N9: verified | O9: 1395000 | P9: 70 | Q9: 651 | R9: =IF(O9="","",IF(O9=J9,"Match","MISMATCH")) -> Match | S9: =IF(P9="","",IF(P9=G9,"Match","MISMATCH")) -> Match | T9: =IF(Q9="","",IF(Q9=K9,"Match","MISMATCH")) -> Match | U9: Claude | V9: 2026-10-22 | W9: Chassis price only. Battery is bought on a separate loan (up to 8 yrs). NOT pay-per-km.; Range 651 km per Mahindra website (S011); brochure says 652 km. Website figure chosen by Madhu, see Q003.
A10: V009 | B10: Mahindra | C10: BE 6 SPORTEQ | D10: SUV | E10: 2026 | F10: Three+ | G10: 70 | H10: Three+ 70 kWh | I10: battery included | J10: 2395000 | K10: 651 | L10: MIDC Part 1 + Part 2 | M10: S001 (news) + S014 (chatbot) for price, S009 (battery, range) | N10: corroborated | P10: 70 | Q10: 651 | R10: =IF(O10="","",IF(O10=J10,"Match","MISMATCH")) | S10: =IF(P10="","",IF(P10=G10,"Match","MISMATCH")) -> Match | T10: =IF(Q10="","",IF(Q10=K10,"Match","MISMATCH")) -> Match | U10: Claude | V10: 2026-10-22 | W10: Price: news and Mahindra chatbot agree, and BaaS + battery value pattern holds. Dealer price list to confirm.; Range 651 km per Mahindra website (S011); brochure says 652 km. Website figure chosen by Madhu, see Q003.; Mahindra chatbot (23 Oct) gives the same price again.; Corroborated: Autocar, TimesDrive, Cars24 and Mahindra chatbot agree.
A11: V010 | B11: Mahindra | C11: BE 6 SPORTEQ | D11: SUV | E11: 2026 | F11: Three+ | G11: 70 | H11: Three+ 70 kWh BaaS | I11: BaaS | J11: 1495000 | K11: 651 | L11: MIDC Part 1 + Part 2 | M11: S010 (price), S009 (battery, range) | N11: verified | O11: 1495000 | P11: 70 | Q11: 651 | R11: =IF(O11="","",IF(O11=J11,"Match","MISMATCH")) -> Match | S11: =IF(P11="","",IF(P11=G11,"Match","MISMATCH")) -> Match | T11: =IF(Q11="","",IF(Q11=K11,"Match","MISMATCH")) -> Match | U11: Claude | V11: 2026-10-22 | W11: Chassis price only. Battery is bought on a separate loan (up to 8 yrs). NOT pay-per-km.; Range 651 km per Mahindra website (S011); brochure says 652 km. Website figure chosen by Madhu, see Q003.
A12: V011 | B12: Mahindra | C12: BE 6 SPORTEQ | D12: SUV | E12: 2026 | F12: Three+ | G12: 79 | H12: Three+ 79 kWh | I12: battery included | J12: 2495000 | K12: 708 | L12: MIDC Part 1 + Part 2 | M12: S001 (news) + S014 (chatbot) for price, S009 (battery, range) | N12: corroborated | P12: 79 | Q12: 708 | R12: =IF(O12="","",IF(O12=J12,"Match","MISMATCH")) | S12: =IF(P12="","",IF(P12=G12,"Match","MISMATCH")) -> Match | T12: =IF(Q12="","",IF(Q12=K12,"Match","MISMATCH")) -> Match | U12: Claude | V12: 2026-10-22 | W12: Price: news and Mahindra chatbot agree, and BaaS + battery value pattern holds. Dealer price list to confirm.; Mahindra chatbot (23 Oct) gives the same price again.; Corroborated: Autocar, TimesDrive, Cars24 and Mahindra chatbot agree.
A13: V012 | B13: Mahindra | C13: BE 6 SPORTEQ | D13: SUV | E13: 2026 | F13: Three+ | G13: 79 | H13: Three+ 79 kWh BaaS | I13: BaaS | J13: 1495000 | K13: 708 | L13: MIDC Part 1 + Part 2 | M13: S010 (price), S009 (battery, range) | N13: verified | O13: 1495000 | P13: 79 | Q13: 708 | R13: =IF(O13="","",IF(O13=J13,"Match","MISMATCH")) -> Match | S13: =IF(P13="","",IF(P13=G13,"Match","MISMATCH")) -> Match | T13: =IF(Q13="","",IF(Q13=K13,"Match","MISMATCH")) -> Match | U13: Claude | V13: 2026-10-22 | W13: Chassis price only. Battery is bought on a separate loan (up to 8 yrs). NOT pay-per-km.
A14: V013 | B14: Mahindra | C14: BE 6 SPORTEQ | D14: SUV | E14: 2026 | F14: FE | G14: 79 | H14: FE 79 kWh | I14: battery included | J14: 2445000 | K14: 708 | L14: MIDC Part 1 + Part 2 | M14: S001 (news) + S014 (chatbot) for price, S009 (battery, range) | N14: corroborated | P14: 79 | Q14: 708 | R14: =IF(O14="","",IF(O14=J14,"Match","MISMATCH")) | S14: =IF(P14="","",IF(P14=G14,"Match","MISMATCH")) -> Match | T14: =IF(Q14="","",IF(Q14=K14,"Match","MISMATCH")) -> Match | U14: Claude | V14: 2026-10-22 | W14: Price: news and Mahindra chatbot agree, and BaaS + battery value pattern holds. Dealer price list to confirm.; Mahindra chatbot (23 Oct) gives the same price again.; Corroborated: Autocar, TimesDrive, Cars24 and Mahindra chatbot agree.
A15: V014 | B15: Mahindra | C15: BE 6 SPORTEQ | D15: SUV | E15: 2026 | F15: FE | G15: 79 | H15: FE 79 kWh BaaS | I15: BaaS | J15: 1445000 | K15: 708 | L15: MIDC Part 1 + Part 2 | M15: S010 (price), S009 (battery, range) | N15: verified | O15: 1445000 | P15: 79 | Q15: 708 | R15: =IF(O15="","",IF(O15=J15,"Match","MISMATCH")) -> Match | S15: =IF(P15="","",IF(P15=G15,"Match","MISMATCH")) -> Match | T15: =IF(Q15="","",IF(Q15=K15,"Match","MISMATCH")) -> Match | U15: Claude | V15: 2026-10-22 | W15: Chassis price only. Battery is bought on a separate loan (up to 8 yrs). NOT pay-per-km.
A16: V015 | B16: Mahindra | C16: BE 6 SPORTEQ | D16: SUV | E16: 2026 | F16: Four | G16: 79 | H16: Four 79 kWh | I16: battery included | J16: 2695000 | K16: 708 | L16: MIDC Part 1 + Part 2 | M16: S001 (news) + S014 (chatbot) for price, S009 (battery, range) | N16: corroborated | P16: 79 | Q16: 708 | R16: =IF(O16="","",IF(O16=J16,"Match","MISMATCH")) | S16: =IF(P16="","",IF(P16=G16,"Match","MISMATCH")) -> Match | T16: =IF(Q16="","",IF(Q16=K16,"Match","MISMATCH")) -> Match | U16: Claude | V16: 2026-10-22 | W16: Price: news and Mahindra chatbot agree, and BaaS + battery value pattern holds. Dealer price list to confirm.; Mahindra chatbot (23 Oct) gives the same price again.; Corroborated: Autocar, TimesDrive, Cars24 and Mahindra chatbot agree.
A17: V016 | B17: Mahindra | C17: BE 6 SPORTEQ | D17: SUV | E17: 2026 | F17: Four | G17: 79 | H17: Four 79 kWh BaaS | I17: BaaS | J17: 1695000 | K17: 708 | L17: MIDC Part 1 + Part 2 | M17: S010 (price), S009 (battery, range) | N17: verified | O17: 1695000 | P17: 79 | Q17: 708 | R17: =IF(O17="","",IF(O17=J17,"Match","MISMATCH")) -> Match | S17: =IF(P17="","",IF(P17=G17,"Match","MISMATCH")) -> Match | T17: =IF(Q17="","",IF(Q17=K17,"Match","MISMATCH")) -> Match | U17: Claude | V17: 2026-10-22 | W17: Chassis price only. Battery is bought on a separate loan (up to 8 yrs). NOT pay-per-km.
A18: V017 | B18: Mahindra | C18: BE 6 SPORTEQ | D18: SUV | E18: 2026 | F18: FE Four | G18: 79 | H18: FE Four 79 kWh | I18: battery included | J18: 2695000 | K18: 708 | L18: MIDC Part 1 + Part 2 | M18: S001 (news) + S014 (chatbot) for price, S009 (battery, range) | N18: corroborated | P18: 79 | Q18: 708 | R18: =IF(O18="","",IF(O18=J18,"Match","MISMATCH")) | S18: =IF(P18="","",IF(P18=G18,"Match","MISMATCH")) -> Match | T18: =IF(Q18="","",IF(Q18=K18,"Match","MISMATCH")) -> Match | U18: Claude | V18: 2026-10-22 | W18: Price: news and Mahindra chatbot agree, and BaaS + battery value pattern holds. Dealer price list to confirm.; Mahindra chatbot (23 Oct) gives the same price again.; Corroborated: Autocar, TimesDrive, Cars24 and Mahindra chatbot agree.
A19: V018 | B19: Mahindra | C19: BE 6 SPORTEQ | D19: SUV | E19: 2026 | F19: FE Four | G19: 79 | H19: FE Four 79 kWh BaaS | I19: BaaS | J19: 1695000 | K19: 708 | L19: MIDC Part 1 + Part 2 | M19: S010 (price), S009 (battery, range) | N19: verified | O19: 1695000 | P19: 79 | Q19: 708 | R19: =IF(O19="","",IF(O19=J19,"Match","MISMATCH")) -> Match | S19: =IF(P19="","",IF(P19=G19,"Match","MISMATCH")) -> Match | T19: =IF(Q19="","",IF(Q19=K19,"Match","MISMATCH")) -> Match | U19: Claude | V19: 2026-10-22 | W19: Chassis price only. Battery is bought on a separate loan (up to 8 yrs). NOT pay-per-km.
A20: V019 | B20: Mahindra | C20: BE 6 SPORTEQ | D20: SUV | E20: 2026 | F20: Launch Edition | G20: 79 | H20: Launch Edition 79 kWh | I20: battery included | J20: 2695000 | K20: 708 | L20: MIDC Part 1 + Part 2 | M20: S001 (news) + S014 (chatbot) for price, S009 (battery, range) | N20: corroborated | P20: 79 | Q20: 708 | R20: =IF(O20="","",IF(O20=J20,"Match","MISMATCH")) | S20: =IF(P20="","",IF(P20=G20,"Match","MISMATCH")) -> Match | T20: =IF(Q20="","",IF(Q20=K20,"Match","MISMATCH")) -> Match | U20: Claude | V20: 2026-10-22 | W20: Price: news and Mahindra chatbot agree, and BaaS + battery value pattern holds. Dealer price list to confirm.; Mahindra chatbot (23 Oct) gives the same price again.; Corroborated: Autocar, TimesDrive, Cars24 and Mahindra chatbot agree.
A21: V020 | B21: Mahindra | C21: BE 6 SPORTEQ | D21: SUV | E21: 2026 | F21: Launch Edition | G21: 79 | H21: Launch Edition 79 kWh BaaS | I21: BaaS | J21: 1695000 | K21: 708 | L21: MIDC Part 1 + Part 2 | M21: S010 (price), S009 (battery, range) | N21: verified | O21: 1695000 | P21: 79 | Q21: 708 | R21: =IF(O21="","",IF(O21=J21,"Match","MISMATCH")) -> Match | S21: =IF(P21="","",IF(P21=G21,"Match","MISMATCH")) -> Match | T21: =IF(Q21="","",IF(Q21=K21,"Match","MISMATCH")) -> Match | U21: Claude | V21: 2026-10-22 | W21: Chassis price only. Battery is bought on a separate loan (up to 8 yrs). NOT pay-per-km.
A22: V021 | B22: Mahindra | C22: XEV 9e | D22: SUV coupé | E22: 2026 | F22: Pack One | G22: 59 | H22: Pack One 59 kWh | I22: battery included | J22: 2190000 | K22: 522 | L22: MIDC Part 1 + Part 2 | M22: S016 (price), S015 + S016 (battery, range) | N22: verified | O22: 2190000 | P22: 59 | Q22: 522 | R22: =IF(O22="","",IF(O22=J22,"Match","MISMATCH")) -> Match | S22: =IF(P22="","",IF(P22=G22,"Match","MISMATCH")) -> Match | T22: =IF(Q22="","",IF(Q22=K22,"Match","MISMATCH")) -> Match | U22: Claude | V22: 2026-10-22
A23: V022 | B23: Mahindra | C23: XEV 9e | D23: SUV coupé | E23: 2026 | F23: Pack One | G23: 59 | H23: Pack One 59 kWh BaaS | I23: BaaS | J23: 1390000 | K23: 522 | L23: MIDC Part 1 + Part 2 | M23: S010 (price), S015 + S016 (battery, range) | N23: verified | O23: 1390000 | P23: 59 | Q23: 522 | R23: =IF(O23="","",IF(O23=J23,"Match","MISMATCH")) -> Match | S23: =IF(P23="","",IF(P23=G23,"Match","MISMATCH")) -> Match | T23: =IF(Q23="","",IF(Q23=K23,"Match","MISMATCH")) -> Match | U23: Claude | V23: 2026-10-22 | W23: Chassis price only. Battery on separate loan.
A24: V023 | B24: Mahindra | C24: XEV 9e | D24: SUV coupé | E24: 2026 | F24: Pack Two | G24: 59 | H24: Pack Two 59 kWh | I24: battery included | J24: 2490000 | K24: 522 | L24: MIDC Part 1 + Part 2 | M24: S051 (price), S015 + S016 (battery, range) | N24: verified | O24: 2490000 | P24: 59 | Q24: 522 | R24: =IF(O24="","",IF(O24=J24,"Match","MISMATCH")) -> Match | S24: =IF(P24="","",IF(P24=G24,"Match","MISMATCH")) -> Match | T24: =IF(Q24="","",IF(Q24=K24,"Match","MISMATCH")) -> Match | U24: Claude | V24: 2026-10-22 | W24: Battery-included price not published. Get from Book Now page or dealer.; Chatbot says ₹24.90L with BaaS ₹16.50L, but Mahindra BaaS page gives ₹16.50L to Pack Two 79 kWh. See Q054.; ₹24.90L confirmed by Mahindra's XEV 9e page FAQ. Chatbot price was right; its BaaS figure was not.
A25: V024 | B25: Mahindra | C25: XEV 9e | D25: SUV coupé | E25: 2026 | F25: Pack Two | G25: 59 | H25: Pack Two 59 kWh BaaS | I25: BaaS | K25: 522 | L25: MIDC Part 1 + Part 2 | M25: S015 + S016 (battery, range) | N25: pending | P25: 59 | Q25: 522 | R25: =IF(O25="","",IF(O25=J25,"Match","MISMATCH")) | S25: =IF(P25="","",IF(P25=G25,"Match","MISMATCH")) -> Match | T25: =IF(Q25="","",IF(Q25=K25,"Match","MISMATCH")) -> Match | U25: Claude | V25: 2026-10-22 | W25: Not on Mahindra BaaS page, though page says BaaS is on all variants. See Q017.; Chatbot says ₹16.50L; BaaS page assigns that to 79 kWh. See Q054.; Mahindra BaaS page lists no Pack Two 59 kWh price. Chatbot's ₹16.50L belongs to 79 kWh. Left blank (not inferred).
A26: V025 | B26: Mahindra | C26: XEV 9e | D26: SUV coupé | E26: 2026 | F26: Pack Two | G26: 79 | H26: Pack Two 79 kWh | I26: battery included | J26: 2650000 | K26: 656 | L26: MIDC Part 1 + Part 2 | M26: S053 (price: Autocar, 91wheels, Team-BHP, MyCarHelpline agree), S015 (battery, range) | N26: corroborated | P26: 79 | Q26: 656 | R26: =IF(O26="","",IF(O26=J26,"Match","MISMATCH")) | S26: =IF(P26="","",IF(P26=G26,"Match","MISMATCH")) -> Match | T26: =IF(Q26="","",IF(Q26=K26,"Match","MISMATCH")) -> Match | U26: Claude | V26: 2026-10-22 | W26: Battery-included price not published. Get from Book Now page or dealer.; If battery value is ₹10L like BE 6, price would be ≈ ₹26.50L. Estimate only, not a source.; Chatbot says 'not available', but Mahindra's XEV 9e page lists this option. See Q055.; ₹26.50L: four independent secondary sources agree; not on an official page.
A27: V026 | B27: Mahindra | C27: XEV 9e | D27: SUV coupé | E27: 2026 | F27: Pack Two | G27: 79 | H27: Pack Two 79 kWh BaaS | I27: BaaS | J27: 1650000 | K27: 656 | L27: MIDC Part 1 + Part 2 | M27: S010 (price), S015 + S016 (battery, range) | N27: verified | O27: 1650000 | P27: 79 | Q27: 656 | R27: =IF(O27="","",IF(O27=J27,"Match","MISMATCH")) -> Match | S27: =IF(P27="","",IF(P27=G27,"Match","MISMATCH")) -> Match | T27: =IF(Q27="","",IF(Q27=K27,"Match","MISMATCH")) -> Match | U27: Claude | V27: 2026-10-22 | W27: Chassis price only. Battery on separate loan.
A28: V027 | B28: Mahindra | C28: XEV 9e | D28: SUV coupé | E28: 2026 | F28: Pack Three Select | G28: 59 | H28: Pack Three Select 59 kWh | I28: battery included | J28: 2790000 | K28: 522 | L28: MIDC Part 1 + Part 2 | M28: S051 (price), S015 + S016 (battery, range) | N28: verified | O28: 2790000 | P28: 59 | Q28: 522 | R28: =IF(O28="","",IF(O28=J28,"Match","MISMATCH")) -> Match | S28: =IF(P28="","",IF(P28=G28,"Match","MISMATCH")) -> Match | T28: =IF(Q28="","",IF(Q28=K28,"Match","MISMATCH")) -> Match | U28: Claude | V28: 2026-10-22 | W28: Battery-included price not published. Get from Book Now page or dealer.; Chatbot says 'not available', but Mahindra's XEV 9e page lists this option. See Q055.; ₹27.90L per Mahindra's XEV 9e page FAQ.
A29: V028 | B29: Mahindra | C29: XEV 9e | D29: SUV coupé | E29: 2026 | F29: Pack Three Select | G29: 59 | H29: Pack Three Select 59 kWh BaaS | I29: BaaS | K29: 522 | L29: MIDC Part 1 + Part 2 | M29: S015 + S016 (battery, range) | N29: pending | P29: 59 | Q29: 522 | R29: =IF(O29="","",IF(O29=J29,"Match","MISMATCH")) | S29: =IF(P29="","",IF(P29=G29,"Match","MISMATCH")) -> Match | T29: =IF(Q29="","",IF(Q29=K29,"Match","MISMATCH")) -> Match | U29: Claude | V29: 2026-10-22 | W29: Not on Mahindra BaaS page, though page says BaaS is on all variants. See Q017.
A30: V029 | B30: Mahindra | C30: XEV 9e | D30: SUV coupé | E30: 2026 | F30: Pack Three | G30: 79 | H30: Pack Three 79 kWh | I30: battery included | J30: 3050000 | K30: 656 | L30: MIDC Part 1 + Part 2 | M30: S051 (price), S015 + S016 (battery, range) | N30: verified | O30: 3050000 | P30: 79 | Q30: 656 | R30: =IF(O30="","",IF(O30=J30,"Match","MISMATCH")) -> Match | S30: =IF(P30="","",IF(P30=G30,"Match","MISMATCH")) -> Match | T30: =IF(Q30="","",IF(Q30=K30,"Match","MISMATCH")) -> Match | U30: Claude | V30: 2026-10-22 | W30: Battery-included price not published. Get from Book Now page or dealer.; If battery value is ₹10L like BE 6, price would be ≈ ₹30.50L. Estimate only, not a source.; ₹30.50L from chatbot; matches BaaS ₹20.50L + ₹10L battery pattern and aggregators. Screenshot website to verify.; ₹30.50L per Mahindra's XEV 9e page FAQ.
A31: V030 | B31: Mahindra | C31: XEV 9e | D31: SUV coupé | E31: 2026 | F31: Pack Three | G31: 79 | H31: Pack Three 79 kWh BaaS | I31: BaaS | J31: 2050000 | K31: 656 | L31: MIDC Part 1 + Part 2 | M31: S010 (price), S015 + S016 (battery, range) | N31: verified | O31: 2050000 | P31: 79 | Q31: 656 | R31: =IF(O31="","",IF(O31=J31,"Match","MISMATCH")) -> Match | S31: =IF(P31="","",IF(P31=G31,"Match","MISMATCH")) -> Match | T31: =IF(Q31="","",IF(Q31=K31,"Match","MISMATCH")) -> Match | U31: Claude | V31: 2026-10-22 | W31: Chassis price only. Battery on separate loan.
A32: V031 | B32: Mahindra | C32: XEV 9e | D32: SUV coupé | E32: 2026 | F32: Cineluxe | G32: 79 | H32: Cineluxe 79 kWh | I32: battery included | J32: 2935000 | K32: 656 | L32: MIDC Part 1 + Part 2 | M32: S019 (price), S015 + S016 (battery, range) | N32: verified | O32: 2935000 | P32: 79 | Q32: 656 | R32: =IF(O32="","",IF(O32=J32,"Match","MISMATCH")) -> Match | S32: =IF(P32="","",IF(P32=G32,"Match","MISMATCH")) -> Match | T32: =IF(Q32="","",IF(Q32=K32,"Match","MISMATCH")) -> Match | U32: Claude | V32: 2026-10-22 | W32: Not in brochure. Price + features from Cineluxe page (S019). Full feature list still unknown, see Q018.
A33: V032 | B33: Mahindra | C33: XEV 9e | D33: SUV coupé | E33: 2026 | F33: Cineluxe | G33: 79 | H33: Cineluxe 79 kWh BaaS | I33: BaaS | J33: 1935000 | K33: 656 | L33: MIDC Part 1 + Part 2 | M33: S010 (price), S015 + S016 (battery, range) | N33: verified | O33: 1935000 | P33: 79 | Q33: 656 | R33: =IF(O33="","",IF(O33=J33,"Match","MISMATCH")) -> Match | S33: =IF(P33="","",IF(P33=G33,"Match","MISMATCH")) -> Match | T33: =IF(Q33="","",IF(Q33=K33,"Match","MISMATCH")) -> Match | U33: Claude | V33: 2026-10-22 | W33: Chassis price only. Battery on separate loan.; Not in brochure. Price + features from Cineluxe page (S019). Full feature list still unknown, see Q018.
A34: V033 | B34: Mahindra | C34: XEV 9S | D34: SUV | E34: 2026 | F34: Pack One Above | G34: 59 | H34: Pack One Above 59 kWh | I34: battery included | J34: 2065000 | K34: 521 | L34: MIDC Part 1 + Part 2 | M34: S053 (price: CarWale, CarDekho, ZigWheels, V3Cars agree), S020 (battery, range) | N34: corroborated | P34: 59 | Q34: 521 | R34: =IF(O34="","",IF(O34=J34,"Match","MISMATCH")) | S34: =IF(P34="","",IF(P34=G34,"Match","MISMATCH")) -> Match | T34: =IF(Q34="","",IF(Q34=K34,"Match","MISMATCH")) -> Match | U34: Claude | V34: 2026-10-22 | W34: CORRECTED from ₹21.40L: that figure includes the 11.2 kW charger (CarWale lists both). Without charger: ₹20.65L.
A35: V034 | B35: Mahindra | C35: XEV 9S | D35: SUV | E35: 2026 | F35: Pack One Above | G35: 59 | H35: Pack One Above 59 kWh BaaS | I35: BaaS | J35: 1265000 | K35: 521 | L35: MIDC Part 1 + Part 2 | M35: S010 (price), S020 + S021 (battery, range) | N35: verified | O35: 1265000 | P35: 59 | Q35: 521 | R35: =IF(O35="","",IF(O35=J35,"Match","MISMATCH")) -> Match | S35: =IF(P35="","",IF(P35=G35,"Match","MISMATCH")) -> Match | T35: =IF(Q35="","",IF(Q35=K35,"Match","MISMATCH")) -> Match | U35: Claude | V35: 2026-10-22 | W35: Chassis price only. Battery on separate loan.; BaaS price looks odd, see Q028.; ₹12.65L doesn't fit: 59 kWh battery-included ₹21.40L - ₹8L = ₹13.40L. Likely copied from the 79 kWh line on Mahindra's BaaS page. See Q028.; Now consistent: ₹20.65L - ₹8L battery = ₹12.65L. Not a typo.
A36: V035 | B36: Mahindra | C36: XEV 9S | D36: SUV | E36: 2026 | F36: Pack One Above | G36: 79 | H36: Pack One Above 79 kWh | I36: battery included | J36: 2265000 | K36: 679 | L36: MIDC Part 1 + Part 2 | M36: S042 (price, chatbot), S020 + S021 (battery, range) | N36: corroborated | P36: 79 | Q36: 679 | R36: =IF(O36="","",IF(O36=J36,"Match","MISMATCH")) | S36: =IF(P36="","",IF(P36=G36,"Match","MISMATCH")) -> Match | T36: =IF(Q36="","",IF(Q36=K36,"Match","MISMATCH")) -> Match | U36: Claude | V36: 2026-10-22 | W36: Battery-included price not published. Dealer price list.; 7-seater price from chatbot; equals BaaS price + battery value (₹9L for 70 kWh, ₹10L for 79 kWh). Screenshot website to verify.; Corroborated: chatbot + CarDekho + V3Cars + ZigWheels agree.
A37: V036 | B37: Mahindra | C37: XEV 9S | D37: SUV | E37: 2026 | F37: Pack One Above | G37: 79 | H37: Pack One Above 79 kWh BaaS | I37: BaaS | J37: 1265000 | K37: 679 | L37: MIDC Part 1 + Part 2 | M37: S010 (price), S020 + S021 (battery, range) | N37: verified | O37: 1265000 | P37: 79 | Q37: 679 | R37: =IF(O37="","",IF(O37=J37,"Match","MISMATCH")) -> Match | S37: =IF(P37="","",IF(P37=G37,"Match","MISMATCH")) -> Match | T37: =IF(Q37="","",IF(Q37=K37,"Match","MISMATCH")) -> Match | U37: Claude | V37: 2026-10-22 | W37: Chassis price only. Battery on separate loan.; BaaS price looks odd, see Q028.; BaaS price lines up with the 7-seater battery-included price.
A38: V037 | B38: Mahindra | C38: XEV 9S | D38: SUV | E38: 2026 | F38: Pack Two Above | G38: 70 | H38: Pack Two Above 70 kWh (7-seater) | I38: battery included | J38: 2505000 | K38: 600 | L38: MIDC Part 1 + Part 2 | M38: S042 (price, chatbot), S020 + S021 (battery, range) | N38: corroborated | P38: 70 | Q38: 600 | R38: =IF(O38="","",IF(O38=J38,"Match","MISMATCH")) | S38: =IF(P38="","",IF(P38=G38,"Match","MISMATCH")) -> Match | T38: =IF(Q38="","",IF(Q38=K38,"Match","MISMATCH")) -> Match | U38: Claude | V38: 2026-10-22 | W38: Battery-included price not published. Dealer price list.; Available as 7- or 6-seater.; 7-seater price from chatbot; equals BaaS price + battery value (₹9L for 70 kWh, ₹10L for 79 kWh). Screenshot website to verify.; Corroborated: chatbot + CarDekho + V3Cars + ZigWheels agree.
A39: V038 | B39: Mahindra | C39: XEV 9S | D39: SUV | E39: 2026 | F39: Pack Two Above | G39: 70 | H39: Pack Two Above 70 kWh BaaS | I39: BaaS | J39: 1605000 | K39: 600 | L39: MIDC Part 1 + Part 2 | M39: S010 (price), S020 + S021 (battery, range) | N39: verified | O39: 1605000 | P39: 70 | Q39: 600 | R39: =IF(O39="","",IF(O39=J39,"Match","MISMATCH")) -> Match | S39: =IF(P39="","",IF(P39=G39,"Match","MISMATCH")) -> Match | T39: =IF(Q39="","",IF(Q39=K39,"Match","MISMATCH")) -> Match | U39: Claude | V39: 2026-10-22 | W39: Chassis price only. Battery on separate loan.; BaaS price looks odd, see Q028.; Available as 7- or 6-seater.; BaaS price lines up with the 7-seater battery-included price.
A40: V039 | B40: Mahindra | C40: XEV 9S | D40: SUV | E40: 2026 | F40: Pack Two Above | G40: 79 | H40: Pack Two Above 79 kWh (7-seater) | I40: battery included | J40: 2595000 | K40: 679 | L40: MIDC Part 1 + Part 2 | M40: S042 (price, chatbot), S020 + S021 (battery, range) | N40: corroborated | P40: 79 | Q40: 679 | R40: =IF(O40="","",IF(O40=J40,"Match","MISMATCH")) | S40: =IF(P40="","",IF(P40=G40,"Match","MISMATCH")) -> Match | T40: =IF(Q40="","",IF(Q40=K40,"Match","MISMATCH")) -> Match | U40: Claude | V40: 2026-10-22 | W40: Battery-included price not published. Dealer price list.; Available as 7- or 6-seater.; 7-seater price from chatbot; equals BaaS price + battery value (₹9L for 70 kWh, ₹10L for 79 kWh). Screenshot website to verify.; Corroborated: chatbot + CarDekho + V3Cars + ZigWheels agree.
A41: V040 | B41: Mahindra | C41: XEV 9S | D41: SUV | E41: 2026 | F41: Pack Two Above | G41: 79 | H41: Pack Two Above 79 kWh BaaS | I41: BaaS | J41: 1595000 | K41: 679 | L41: MIDC Part 1 + Part 2 | M41: S010 (price), S020 + S021 (battery, range) | N41: verified | O41: 1595000 | P41: 79 | Q41: 679 | R41: =IF(O41="","",IF(O41=J41,"Match","MISMATCH")) -> Match | S41: =IF(P41="","",IF(P41=G41,"Match","MISMATCH")) -> Match | T41: =IF(Q41="","",IF(Q41=K41,"Match","MISMATCH")) -> Match | U41: Claude | V41: 2026-10-22 | W41: Chassis price only. Battery on separate loan.; BaaS price looks odd, see Q028.; Available as 7- or 6-seater.; BaaS price lines up with the 7-seater battery-included price.
A42: V041 | B42: Mahindra | C42: XEV 9S | D42: SUV | E42: 2026 | F42: Pack Three | G42: 79 | H42: Pack Three 79 kWh (7-seater) | I42: battery included | J42: 2785000 | K42: 679 | L42: MIDC Part 1 + Part 2 | M42: S042 (price, chatbot), S020 + S021 (battery, range) | N42: corroborated | P42: 79 | Q42: 679 | R42: =IF(O42="","",IF(O42=J42,"Match","MISMATCH")) | S42: =IF(P42="","",IF(P42=G42,"Match","MISMATCH")) -> Match | T42: =IF(Q42="","",IF(Q42=K42,"Match","MISMATCH")) -> Match | U42: Claude | V42: 2026-10-22 | W42: Battery-included price not published. Dealer price list.; Available as 7- or 6-seater.; 7-seater price from chatbot; equals BaaS price + battery value (₹9L for 70 kWh, ₹10L for 79 kWh). Screenshot website to verify.; Corroborated: chatbot + CarDekho + V3Cars + ZigWheels agree.
A43: V042 | B43: Mahindra | C43: XEV 9S | D43: SUV | E43: 2026 | F43: Pack Three | G43: 79 | H43: Pack Three 79 kWh BaaS | I43: BaaS | J43: 1785000 | K43: 679 | L43: MIDC Part 1 + Part 2 | M43: S010 (price), S020 + S021 (battery, range) | N43: verified | O43: 1785000 | P43: 79 | Q43: 679 | R43: =IF(O43="","",IF(O43=J43,"Match","MISMATCH")) -> Match | S43: =IF(P43="","",IF(P43=G43,"Match","MISMATCH")) -> Match | T43: =IF(Q43="","",IF(Q43=K43,"Match","MISMATCH")) -> Match | U43: Claude | V43: 2026-10-22 | W43: Chassis price only. Battery on separate loan.; Available as 7- or 6-seater.; BaaS price lines up with the 7-seater battery-included price.
A44: V043 | B44: Mahindra | C44: XEV 9S | D44: SUV | E44: 2026 | F44: Pack Three Above | G44: 79 | H44: Pack Three Above 79 kWh (6-seater) | I44: battery included | J44: 3015000 | K44: 679 | L44: MIDC Part 1 + Part 2 | M44: S021 (price), S020 + S021 (battery, range) | N44: verified | P44: 79 | Q44: 679 | R44: =IF(O44="","",IF(O44=J44,"Match","MISMATCH")) | S44: =IF(P44="","",IF(P44=G44,"Match","MISMATCH")) -> Match | T44: =IF(Q44="","",IF(Q44=K44,"Match","MISMATCH")) -> Match | U44: Claude | V44: 2026-10-22 | W44: 6-seater, no charger. 7-seater price may differ, see Q027.; Available as 7- or 6-seater.; 7-seater version added as separate row (price not yet published).; Note: Mahindra page figure; check it excludes charger (One Above case did not).
A45: V044 | B45: Mahindra | C45: XEV 9S | D45: SUV | E45: 2026 | F45: Pack Three Above | G45: 79 | H45: Pack Three Above 79 kWh BaaS | I45: BaaS | J45: 1995000 | K45: 679 | L45: MIDC Part 1 + Part 2 | M45: S010 (price), S020 + S021 (battery, range) | N45: verified | O45: 1995000 | P45: 79 | Q45: 679 | R45: =IF(O45="","",IF(O45=J45,"Match","MISMATCH")) -> Match | S45: =IF(P45="","",IF(P45=G45,"Match","MISMATCH")) -> Match | T45: =IF(Q45="","",IF(Q45=K45,"Match","MISMATCH")) -> Match | U45: Claude | V45: 2026-10-22 | W45: Chassis price only. Battery on separate loan.; Available as 7- or 6-seater.; BaaS price lines up with the 7-seater battery-included price.
A46: V045 | B46: Mahindra | C46: XUV 3XO EV | D46: SUV | E46: 2026 | F46: AX5 | G46: 39.4 | H46: AX5 39.4 kWh | I46: battery included | J46: 1389000 | K46: 351 | L46: MIDC Part 1 + Part 2 | M46: S026 (price), S025 (battery, range) | N46: verified | O46: 1389000 | P46: 39.4 | Q46: 351 | R46: =IF(O46="","",IF(O46=J46,"Match","MISMATCH")) -> Match | S46: =IF(P46="","",IF(P46=G46,"Match","MISMATCH")) -> Match | T46: =IF(Q46="","",IF(Q46=K46,"Match","MISMATCH")) -> Match | U46: Claude | V46: 2026-10-22 | W46: BaaS not offered (BaaS covers Electric Origin models only, see Q033).
A47: V046 | B47: Mahindra | C47: XUV 3XO EV | D47: SUV | E47: 2026 | F47: AX7L | G47: 39.4 | H47: AX7L 39.4 kWh | I47: battery included | J47: 1496000 | K47: 351 | L47: MIDC Part 1 + Part 2 | M47: Aggregators (price), S025 (battery, range) | N47: corroborated | P47: 39.4 | Q47: 351 | R47: =IF(O47="","",IF(O47=J47,"Match","MISMATCH")) | S47: =IF(P47="","",IF(P47=G47,"Match","MISMATCH")) -> Match | T47: =IF(Q47="","",IF(Q47=K47,"Match","MISMATCH")) -> Match | U47: Claude | V47: 2026-10-22 | W47: Price ₹14.96L from CarDekho/Autocar, not yet seen on an official page.; BaaS not offered (BaaS covers Electric Origin models only, see Q033).; Corroborated: Autocar (₹13.89-14.96L range) and Team-BHP agree on ₹14.96L.
A48: V047 | B48: Tata | C48: Nexon.ev | D48: SUV | E48: 2026 | F48: Creative+ MR | G48: 30 | H48: Creative+ MR | I48: battery included | J48: 1249000 | K48: 275 | L48: MIDC Part 1 + Part 2 | M48: S040 (price), S032 (battery, range) | N48: verified | O48: 1249000 | P48: 30 | Q48: 275 | R48: =IF(O48="","",IF(O48=J48,"Match","MISMATCH")) -> Match | S48: =IF(P48="","",IF(P48=G48,"Match","MISMATCH")) -> Match | T48: =IF(Q48="","",IF(Q48=K48,"Match","MISMATCH")) -> Match | U48: Claude | V48: 2026-10-23
A49: V048 | B49: Tata | C49: Nexon.ev | D49: SUV | E49: 2026 | F49: Fearless MR | G49: 30 | H49: Fearless MR | I49: battery included | J49: 1329000 | K49: 275 | L49: MIDC Part 1 + Part 2 | M49: S040 (price), S032 (battery, range) | N49: verified | O49: 1329000 | P49: 30 | Q49: 275 | R49: =IF(O49="","",IF(O49=J49,"Match","MISMATCH")) -> Match | S49: =IF(P49="","",IF(P49=G49,"Match","MISMATCH")) -> Match | T49: =IF(Q49="","",IF(Q49=K49,"Match","MISMATCH")) -> Match | U49: Claude | V49: 2026-10-23
A50: V049 | B50: Tata | C50: Nexon.ev | D50: SUV | E50: 2026 | F50: Creative 45 | G50: 45 | H50: Creative 45 | I50: battery included | J50: 1434000 | K50: 489 | L50: MIDC Part 1 + Part 2 | M50: S040 (price), S032 (battery, range) | N50: verified | O50: 1434000 | P50: 45 | Q50: 489 | R50: =IF(O50="","",IF(O50=J50,"Match","MISMATCH")) -> Match | S50: =IF(P50="","",IF(P50=G50,"Match","MISMATCH")) -> Match | T50: =IF(Q50="","",IF(Q50=K50,"Match","MISMATCH")) -> Match | U50: Claude | V50: 2026-10-23
A51: V050 | B51: Tata | C51: Nexon.ev | D51: SUV | E51: 2026 | F51: Fearless 45 | G51: 45 | H51: Fearless 45 | I51: battery included | J51: 1534000 | K51: 489 | L51: MIDC Part 1 + Part 2 | M51: S040 (price), S032 (battery, range) | N51: verified | O51: 1534000 | P51: 45 | Q51: 489 | R51: =IF(O51="","",IF(O51=J51,"Match","MISMATCH")) -> Match | S51: =IF(P51="","",IF(P51=G51,"Match","MISMATCH")) -> Match | T51: =IF(Q51="","",IF(Q51=K51,"Match","MISMATCH")) -> Match | U51: Claude | V51: 2026-10-23
A52: V051 | B52: Tata | C52: Nexon.ev | D52: SUV | E52: 2026 | F52: Empowered 45 | G52: 45 | H52: Empowered 45 | I52: battery included | J52: 1634000 | K52: 489 | L52: MIDC Part 1 + Part 2 | M52: S040 (price), S032 (battery, range) | N52: verified | O52: 1634000 | P52: 45 | Q52: 489 | R52: =IF(O52="","",IF(O52=J52,"Match","MISMATCH")) -> Match | S52: =IF(P52="","",IF(P52=G52,"Match","MISMATCH")) -> Match | T52: =IF(Q52="","",IF(Q52=K52,"Match","MISMATCH")) -> Match | U52: Claude | V52: 2026-10-23
A53: V052 | B53: Tata | C53: Nexon.ev | D53: SUV | E53: 2026 | F53: Empowered+A 45 | G53: 45 | H53: Empowered+A 45 | I53: battery included | J53: 1769000 | K53: 489 | L53: MIDC Part 1 + Part 2 | M53: S040 (price), S032 (battery, range) | N53: verified | O53: 1769000 | P53: 45 | Q53: 489 | R53: =IF(O53="","",IF(O53=J53,"Match","MISMATCH")) -> Match | S53: =IF(P53="","",IF(P53=G53,"Match","MISMATCH")) -> Match | T53: =IF(Q53="","",IF(Q53=K53,"Match","MISMATCH")) -> Match | U53: Claude | V53: 2026-10-23 | W53: Also sold as #DARK and Red #DARK editions; prices may differ.
A54: V053 | B54: Tata | C54: Punch.ev | D54: SUV | E54: 2026 | F54: Smart 30 | G54: 30 | H54: Smart 30 | I54: battery included | J54: 979000 | K54: 365 | L54: MIDC Part 1 + Part 2 | M54: S040 (price), S031 (battery, range) | N54: verified | O54: 979000 | P54: 30 | Q54: 365 | R54: =IF(O54="","",IF(O54=J54,"Match","MISMATCH")) -> Match | S54: =IF(P54="","",IF(P54=G54,"Match","MISMATCH")) -> Match | T54: =IF(Q54="","",IF(Q54=K54,"Match","MISMATCH")) -> Match | U54: Claude | V54: 2026-10-23 | W54: Tata publishes 365-375 km as a band (brochure + FAQ). Lower figure used as the comparable number.
A55: V054 | B55: Tata | C55: Punch.ev | D55: SUV | E55: 2026 | F55: Smart+ 30 | G55: 30 | H55: Smart+ 30 | I55: battery included | J55: 1039000 | K55: 365 | L55: MIDC Part 1 + Part 2 | M55: S040 (price), S031 (battery, range) | N55: verified | O55: 1039000 | P55: 30 | Q55: 365 | R55: =IF(O55="","",IF(O55=J55,"Match","MISMATCH")) -> Match | S55: =IF(P55="","",IF(P55=G55,"Match","MISMATCH")) -> Match | T55: =IF(Q55="","",IF(Q55=K55,"Match","MISMATCH")) -> Match | U55: Claude | V55: 2026-10-23 | W55: Tata publishes 365-375 km as a band (brochure + FAQ). Lower figure used as the comparable number.
A56: V055 | B56: Tata | C56: Punch.ev | D56: SUV | E56: 2026 | F56: Smart+ 40 | G56: 40 | H56: Smart+ 40 | I56: battery included | J56: 1119000 | K56: 468 | L56: MIDC Part 1 + Part 2 | M56: S040 (price), S031 (battery, range) | N56: verified | O56: 1119000 | P56: 40 | Q56: 468 | R56: =IF(O56="","",IF(O56=J56,"Match","MISMATCH")) -> Match | S56: =IF(P56="","",IF(P56=G56,"Match","MISMATCH")) -> Match | T56: =IF(Q56="","",IF(Q56=K56,"Match","MISMATCH")) -> Match | U56: Claude | V56: 2026-10-23
A57: V056 | B57: Tata | C57: Punch.ev | D57: SUV | E57: 2026 | F57: Adventure 40 | G57: 40 | H57: Adventure 40 | I57: battery included | J57: 1194000 | K57: 468 | L57: MIDC Part 1 + Part 2 | M57: S040 (price), S031 (battery, range) | N57: verified | O57: 1194000 | P57: 40 | Q57: 468 | R57: =IF(O57="","",IF(O57=J57,"Match","MISMATCH")) -> Match | S57: =IF(P57="","",IF(P57=G57,"Match","MISMATCH")) -> Match | T57: =IF(Q57="","",IF(Q57=K57,"Match","MISMATCH")) -> Match | U57: Claude | V57: 2026-10-23
A58: V057 | B58: Tata | C58: Punch.ev | D58: SUV | E58: 2026 | F58: Empowered 40 | G58: 40 | H58: Empowered 40 | I58: battery included | J58: 1269000 | K58: 468 | L58: MIDC Part 1 + Part 2 | M58: S040 (price), S031 (battery, range) | N58: verified | O58: 1269000 | P58: 40 | Q58: 468 | R58: =IF(O58="","",IF(O58=J58,"Match","MISMATCH")) -> Match | S58: =IF(P58="","",IF(P58=G58,"Match","MISMATCH")) -> Match | T58: =IF(Q58="","",IF(Q58=K58,"Match","MISMATCH")) -> Match | U58: Claude | V58: 2026-10-23
A59: V058 | B59: Tata | C59: Punch.ev | D59: SUV | E59: 2026 | F59: Empowered+ S 40 | G59: 40 | H59: Empowered+ S 40 | I59: battery included | J59: 1299000 | K59: 468 | L59: MIDC Part 1 + Part 2 | M59: S040 (price), S031 (battery, range) | N59: verified | O59: 1299000 | P59: 40 | Q59: 468 | R59: =IF(O59="","",IF(O59=J59,"Match","MISMATCH")) -> Match | S59: =IF(P59="","",IF(P59=G59,"Match","MISMATCH")) -> Match | T59: =IF(Q59="","",IF(Q59=K59,"Match","MISMATCH")) -> Match | U59: Claude | V59: 2026-10-23
A60: V059 | B60: Tata | C60: Curvv.ev | D60: SUV coupé | E60: 2026 | F60: Accomplished X 55 | G60: 55 | H60: Accomplished X 55 | I60: battery included | J60: 1719000 | K60: 502 | L60: MIDC Part 1 + Part 2 | M60: S040 (price), S033 (battery, range) | N60: verified | O60: 1719000 | P60: 55 | Q60: 502 | R60: =IF(O60="","",IF(O60=J60,"Match","MISMATCH")) -> Match | S60: =IF(P60="","",IF(P60=G60,"Match","MISMATCH")) -> Match | T60: =IF(Q60="","",IF(Q60=K60,"Match","MISMATCH")) -> Match | U60: Claude | V60: 2026-10-23 | W60: Oct 2026 brochure lists 55 kWh only; older 45 kWh versions appear dropped.
A61: V060 | B61: Tata | C61: Curvv.ev | D61: SUV coupé | E61: 2026 | F61: Empowered X 55 | G61: 55 | H61: Empowered X 55 | I61: battery included | J61: 1939000 | K61: 502 | L61: MIDC Part 1 + Part 2 | M61: S040 (price), S033 (battery, range) | N61: verified | O61: 1939000 | P61: 55 | Q61: 502 | R61: =IF(O61="","",IF(O61=J61,"Match","MISMATCH")) -> Match | S61: =IF(P61="","",IF(P61=G61,"Match","MISMATCH")) -> Match | T61: =IF(Q61="","",IF(Q61=K61,"Match","MISMATCH")) -> Match | U61: Claude | V61: 2026-10-23 | W61: Also #DARK edition.
A62: V061 | B62: Tata | C62: Harrier.ev | D62: SUV | E62: 2026 | F62: Adventure 65 | G62: 65 | H62: Adventure 65 | I62: battery included | J62: 2179000 | K62: 538 | L62: MIDC Part 1 + Part 2 | M62: S040 (price), S034 (battery, range) | N62: verified | O62: 2179000 | P62: 65 | Q62: 538 | R62: =IF(O62="","",IF(O62=J62,"Match","MISMATCH")) -> Match | S62: =IF(P62="","",IF(P62=G62,"Match","MISMATCH")) -> Match | T62: =IF(Q62="","",IF(Q62=K62,"Match","MISMATCH")) -> Match | U62: Claude | V62: 2026-10-23
A63: V062 | B63: Tata | C63: Harrier.ev | D63: SUV | E63: 2026 | F63: Adventure S 65 | G63: 65 | H63: Adventure S 65 | I63: battery included | J63: 2229000 | K63: 538 | L63: MIDC Part 1 + Part 2 | M63: S040 (price), S034 (battery, range) | N63: verified | O63: 2229000 | P63: 65 | Q63: 538 | R63: =IF(O63="","",IF(O63=J63,"Match","MISMATCH")) -> Match | S63: =IF(P63="","",IF(P63=G63,"Match","MISMATCH")) -> Match | T63: =IF(Q63="","",IF(Q63=K63,"Match","MISMATCH")) -> Match | U63: Claude | V63: 2026-10-23
A64: V063 | B64: Tata | C64: Harrier.ev | D64: SUV | E64: 2026 | F64: Fearless+ 65 | G64: 65 | H64: Fearless+ 65 | I64: battery included | J64: 2429000 | K64: 538 | L64: MIDC Part 1 + Part 2 | M64: S040 (price), S034 (battery, range) | N64: verified | O64: 2429000 | P64: 65 | Q64: 538 | R64: =IF(O64="","",IF(O64=J64,"Match","MISMATCH")) -> Match | S64: =IF(P64="","",IF(P64=G64,"Match","MISMATCH")) -> Match | T64: =IF(Q64="","",IF(Q64=K64,"Match","MISMATCH")) -> Match | U64: Claude | V64: 2026-10-23
A65: V064 | B65: Tata | C65: Harrier.ev | D65: SUV | E65: 2026 | F65: Fearless+ 75 | G65: 75 | H65: Fearless+ 75 | I65: battery included | J65: 2529000 | K65: 627 | L65: MIDC Part 1 + Part 2 | M65: S040 (price), S034 (battery, range) | N65: verified | O65: 2529000 | P65: 75 | Q65: 627 | R65: =IF(O65="","",IF(O65=J65,"Match","MISMATCH")) -> Match | S65: =IF(P65="","",IF(P65=G65,"Match","MISMATCH")) -> Match | T65: =IF(Q65="","",IF(Q65=K65,"Match","MISMATCH")) -> Match | U65: Claude | V65: 2026-10-23
A66: V065 | B66: Tata | C66: Harrier.ev | D66: SUV | E66: 2026 | F66: Empowered 75 | G66: 75 | H66: Empowered 75 | I66: battery included | J66: 2779000 | K66: 627 | L66: MIDC Part 1 + Part 2 | M66: S040 (price), S034 (battery, range) | N66: verified | O66: 2779000 | P66: 75 | Q66: 627 | R66: =IF(O66="","",IF(O66=J66,"Match","MISMATCH")) -> Match | S66: =IF(P66="","",IF(P66=G66,"Match","MISMATCH")) -> Match | T66: =IF(Q66="","",IF(Q66=K66,"Match","MISMATCH")) -> Match | U66: Claude | V66: 2026-10-23 | W66: Stealth Edition available.
A67: V066 | B67: Tata | C67: Harrier.ev | D67: SUV | E67: 2026 | F67: Fearless+ QWD 75 | G67: 75 | H67: Fearless+ QWD 75 (AWD) | I67: battery included | J67: 2679000 | K67: 622 | L67: MIDC Part 1 + Part 2 | M67: S040 (price), S034 (battery, range) | N67: verified | O67: 2679000 | P67: 75 | Q67: 622 | R67: =IF(O67="","",IF(O67=J67,"Match","MISMATCH")) -> Match | S67: =IF(P67="","",IF(P67=G67,"Match","MISMATCH")) -> Match | T67: =IF(Q67="","",IF(Q67=K67,"Match","MISMATCH")) -> Match | U67: Claude | V67: 2026-10-23 | W67: Confirmed on Tata.ev site (sold as Fearless+ 75 AWD).
A68: V067 | B68: Tata | C68: Harrier.ev | D68: SUV | E68: 2026 | F68: Empowered QWD 75 | G68: 75 | H68: Empowered QWD 75 (AWD) | I68: battery included | J68: 2929000 | K68: 622 | L68: MIDC Part 1 + Part 2 | M68: S040 (price), S034 (battery, range) | N68: verified | O68: 2929000 | P68: 75 | Q68: 622 | R68: =IF(O68="","",IF(O68=J68,"Match","MISMATCH")) -> Match | S68: =IF(P68="","",IF(P68=G68,"Match","MISMATCH")) -> Match | T68: =IF(Q68="","",IF(Q68=K68,"Match","MISMATCH")) -> Match | U68: Claude | V68: 2026-10-23 | W68: Stealth Edition available.
A69: V068 | B69: Tata | C69: Sierra.ev | D69: SUV | E69: 2026 | F69: Pure 63 | G69: 63 | H69: Pure 63 | I69: battery included | J69: 1879000 | K69: 566 | L69: MIDC Part 1 + Part 2 | M69: S040 (price), S035 (battery, range) | N69: verified | O69: 1879000 | P69: 63 | Q69: 566 | R69: =IF(O69="","",IF(O69=J69,"Match","MISMATCH")) -> Match | S69: =IF(P69="","",IF(P69=G69,"Match","MISMATCH")) -> Match | T69: =IF(Q69="","",IF(Q69=K69,"Match","MISMATCH")) -> Match | U69: Claude | V69: 2026-10-23
A70: V069 | B70: Tata | C70: Sierra.ev | D70: SUV | E70: 2026 | F70: Pure S 63 | G70: 63 | H70: Pure S 63 | I70: battery included | J70: 1999000 | K70: 566 | L70: MIDC Part 1 + Part 2 | M70: S040 (price), S035 (battery, range) | N70: verified | O70: 1999000 | P70: 63 | Q70: 566 | R70: =IF(O70="","",IF(O70=J70,"Match","MISMATCH")) -> Match | S70: =IF(P70="","",IF(P70=G70,"Match","MISMATCH")) -> Match | T70: =IF(Q70="","",IF(Q70=K70,"Match","MISMATCH")) -> Match | U70: Claude | V70: 2026-10-23
A71: V070 | B71: Tata | C71: Sierra.ev | D71: SUV | E71: 2026 | F71: Adventure 63 | G71: 63 | H71: Adventure 63 | I71: battery included | J71: 2099000 | K71: 566 | L71: MIDC Part 1 + Part 2 | M71: S040 (price), S035 (battery, range) | N71: verified | O71: 2099000 | P71: 63 | Q71: 566 | R71: =IF(O71="","",IF(O71=J71,"Match","MISMATCH")) -> Match | S71: =IF(P71="","",IF(P71=G71,"Match","MISMATCH")) -> Match | T71: =IF(Q71="","",IF(Q71=K71,"Match","MISMATCH")) -> Match | U71: Claude | V71: 2026-10-23
A72: V071 | B72: Tata | C72: Sierra.ev | D72: SUV | E72: 2026 | F72: Adventure 75 | G72: 75 | H72: Adventure 75 | I72: battery included | J72: 2219000 | K72: 665 | L72: MIDC Part 1 + Part 2 | M72: S040 (price), S035 (battery, range) | N72: verified | O72: 2219000 | P72: 75 | Q72: 665 | R72: =IF(O72="","",IF(O72=J72,"Match","MISMATCH")) -> Match | S72: =IF(P72="","",IF(P72=G72,"Match","MISMATCH")) -> Match | T72: =IF(Q72="","",IF(Q72=K72,"Match","MISMATCH")) -> Match | U72: Claude | V72: 2026-10-23
A73: V072 | B73: Tata | C73: Sierra.ev | D73: SUV | E73: 2026 | F73: Empowered 63 | G73: 63 | H73: Empowered 63 | I73: battery included | J73: 2279000 | K73: 566 | L73: MIDC Part 1 + Part 2 | M73: S040 (price), S035 (battery, range) | N73: verified | O73: 2279000 | P73: 63 | Q73: 566 | R73: =IF(O73="","",IF(O73=J73,"Match","MISMATCH")) -> Match | S73: =IF(P73="","",IF(P73=G73,"Match","MISMATCH")) -> Match | T73: =IF(Q73="","",IF(Q73=K73,"Match","MISMATCH")) -> Match | U73: Claude | V73: 2026-10-23
A74: V073 | B74: Tata | C74: Sierra.ev | D74: SUV | E74: 2026 | F74: Empowered 75 | G74: 75 | H74: Empowered 75 | I74: battery included | J74: 2379000 | K74: 665 | L74: MIDC Part 1 + Part 2 | M74: S040 (price), S035 (battery, range) | N74: verified | O74: 2379000 | P74: 75 | Q74: 665 | R74: =IF(O74="","",IF(O74=J74,"Match","MISMATCH")) -> Match | S74: =IF(P74="","",IF(P74=G74,"Match","MISMATCH")) -> Match | T74: =IF(Q74="","",IF(Q74=K74,"Match","MISMATCH")) -> Match | U74: Claude | V74: 2026-10-23
A75: V074 | B75: Tata | C75: Sierra.ev | D75: SUV | E75: 2026 | F75: Empowered A 75 | G75: 75 | H75: Empowered A 75 | I75: battery included | J75: 2479000 | K75: 665 | L75: MIDC Part 1 + Part 2 | M75: S040 (price), S035 (battery, range) | N75: verified | O75: 2479000 | P75: 75 | Q75: 665 | R75: =IF(O75="","",IF(O75=J75,"Match","MISMATCH")) -> Match | S75: =IF(P75="","",IF(P75=G75,"Match","MISMATCH")) -> Match | T75: =IF(Q75="","",IF(Q75=K75,"Match","MISMATCH")) -> Match | U75: Claude | V75: 2026-10-23
A76: V075 | B76: Tata | C76: Sierra.ev | D76: SUV | E76: 2026 | F76: Empowered A QWD 75 | G76: 75 | H76: Empowered A QWD 75 (AWD) | I76: battery included | J76: 2599000 | K76: 624 | L76: MIDC Part 1 + Part 2 | M76: S040 (price), S035 (battery, range) | N76: verified | O76: 2599000 | P76: 75 | Q76: 624 | R76: =IF(O76="","",IF(O76=J76,"Match","MISMATCH")) -> Match | S76: =IF(P76="","",IF(P76=G76,"Match","MISMATCH")) -> Match | T76: =IF(Q76="","",IF(Q76=K76,"Match","MISMATCH")) -> Match | U76: Claude | V76: 2026-10-23
A77: V076 | B77: Tata | C77: Tiago.ev | D77: Hatchback | E77: 2026 | F77: Smart 19 | G77: 19.2 | H77: Smart 19 | I77: battery included | J77: 699000 | K77: 226 | L77: ARAI certified (cycle not stated) | M77: S040 (price), S038 (battery, range) | N77: verified | O77: 699000 | P77: 19.2 | Q77: 226 | R77: =IF(O77="","",IF(O77=J77,"Match","MISMATCH")) -> Match | S77: =IF(P77="","",IF(P77=G77,"Match","MISMATCH")) -> Match | T77: =IF(Q77="","",IF(Q77=K77,"Match","MISMATCH")) -> Match | U77: Claude | V77: 2026-10-23
A78: V077 | B78: Tata | C78: Tiago.ev | D78: Hatchback | E78: 2026 | F78: Pure+ 19 | G78: 19.2 | H78: Pure+ 19 | I78: battery included | J78: 864000 | K78: 226 | L78: ARAI certified (cycle not stated) | M78: S040 (price), S038 (battery, range) | N78: verified | O78: 864000 | P78: 19.2 | Q78: 226 | R78: =IF(O78="","",IF(O78=J78,"Match","MISMATCH")) -> Match | S78: =IF(P78="","",IF(P78=G78,"Match","MISMATCH")) -> Match | T78: =IF(Q78="","",IF(Q78=K78,"Match","MISMATCH")) -> Match | U78: Claude | V78: 2026-10-23
A79: V078 | B79: Tata | C79: Tiago.ev | D79: Hatchback | E79: 2026 | F79: Pure+ 24 | G79: 24 | H79: Pure+ 24 | I79: battery included | J79: 964000 | K79: 285 | L79: ARAI certified (cycle not stated) | M79: S040 (price), S038 (battery, range) | N79: verified | O79: 964000 | P79: 24 | Q79: 285 | R79: =IF(O79="","",IF(O79=J79,"Match","MISMATCH")) -> Match | S79: =IF(P79="","",IF(P79=G79,"Match","MISMATCH")) -> Match | T79: =IF(Q79="","",IF(Q79=K79,"Match","MISMATCH")) -> Match | U79: Claude | V79: 2026-10-23
A80: V079 | B80: Tata | C80: Tiago.ev | D80: Hatchback | E80: 2026 | F80: Creative+ 24 | G80: 24 | H80: Creative+ 24 | I80: battery included | J80: 1009000 | K80: 285 | L80: ARAI certified (cycle not stated) | M80: S040 (price), S038 (battery, range) | N80: verified | O80: 1009000 | P80: 24 | Q80: 285 | R80: =IF(O80="","",IF(O80=J80,"Match","MISMATCH")) -> Match | S80: =IF(P80="","",IF(P80=G80,"Match","MISMATCH")) -> Match | T80: =IF(Q80="","",IF(Q80=K80,"Match","MISMATCH")) -> Match | U80: Claude | V80: 2026-10-23 | W80: Tata site ₹10.09L; Autocar top price ₹9.99L was wrong/outdated.
A81: V080 | B81: Tata | C81: Tigor.ev | D81: Sedan | E81: 2026 | F81: XE | G81: 26 | H81: XE | I81: battery included | J81: 1249000 | K81: 315 | L81: ARAI certified (cycle not stated) | M81: S040 (price), S030 (battery, range) | N81: verified | O81: 1249000 | P81: 26 | Q81: 315 | R81: =IF(O81="","",IF(O81=J81,"Match","MISMATCH")) -> Match | S81: =IF(P81="","",IF(P81=G81,"Match","MISMATCH")) -> Match | T81: =IF(Q81="","",IF(Q81=K81,"Match","MISMATCH")) -> Match | U81: Claude | V81: 2026-10-23 | W81: Brochure Sep 2025; still on sale per Tata.ev site (Oct 2026).
A82: V081 | B82: Tata | C82: Tigor.ev | D82: Sedan | E82: 2026 | F82: XT | G82: 26 | H82: XT | I82: battery included | J82: 1299000 | K82: 315 | L82: ARAI certified (cycle not stated) | M82: S040 (price), S030 (battery, range) | N82: verified | O82: 1299000 | P82: 26 | Q82: 315 | R82: =IF(O82="","",IF(O82=J82,"Match","MISMATCH")) -> Match | S82: =IF(P82="","",IF(P82=G82,"Match","MISMATCH")) -> Match | T82: =IF(Q82="","",IF(Q82=K82,"Match","MISMATCH")) -> Match | U82: Claude | V82: 2026-10-23
A83: V082 | B83: Tata | C83: Tigor.ev | D83: Sedan | E83: 2026 | F83: XZ+ | G83: 26 | H83: XZ+ | I83: battery included | J83: 1349000 | K83: 315 | L83: ARAI certified (cycle not stated) | M83: S040 (price), S030 (battery, range) | N83: verified | O83: 1349000 | P83: 26 | Q83: 315 | R83: =IF(O83="","",IF(O83=J83,"Match","MISMATCH")) -> Match | S83: =IF(P83="","",IF(P83=G83,"Match","MISMATCH")) -> Match | T83: =IF(Q83="","",IF(Q83=K83,"Match","MISMATCH")) -> Match | U83: Claude | V83: 2026-10-23
A84: V083 | B84: Tata | C84: Tigor.ev | D84: Sedan | E84: 2026 | F84: XZ+ Lux | G84: 26 | H84: XZ+ Lux | I84: battery included | J84: 1375000 | K84: 315 | L84: ARAI certified (cycle not stated) | M84: S040 (price), S030 (battery, range) | N84: verified | O84: 1375000 | P84: 26 | Q84: 315 | R84: =IF(O84="","",IF(O84=J84,"Match","MISMATCH")) -> Match | S84: =IF(P84="","",IF(P84=G84,"Match","MISMATCH")) -> Match | T84: =IF(Q84="","",IF(Q84=K84,"Match","MISMATCH")) -> Match | U84: Claude | V84: 2026-10-23
A85: V084 | B85: Mahindra | C85: XEV 9S | D85: SUV | E85: 2026 | F85: Pack Two Above | G85: 70 | H85: Pack Two Above 70 kWh (6-seater) | I85: battery included | J85: 2525000 | K85: 600 | L85: MIDC Part 1 + Part 2 | M85: S042 (price, chatbot), S020 + S021 (battery, range) | N85: corroborated | P85: 70 | Q85: 600 | R85: =IF(O85="","",IF(O85=J85,"Match","MISMATCH")) | S85: =IF(P85="","",IF(P85=G85,"Match","MISMATCH")) -> Match | T85: =IF(Q85="","",IF(Q85=K85,"Match","MISMATCH")) -> Match | U85: Claude | V85: 2026-10-23 | W85: 6-seater (captain seats) price from chatbot: 7-seater + ₹20,000. Screenshot website to verify.; Corroborated: chatbot + CarDekho + V3Cars + ZigWheels agree.
A86: V085 | B86: Mahindra | C86: XEV 9S | D86: SUV | E86: 2026 | F86: Pack Two Above | G86: 79 | H86: Pack Two Above 79 kWh (6-seater) | I86: battery included | J86: 2615000 | K86: 679 | L86: MIDC Part 1 + Part 2 | M86: S042 (price, chatbot), S020 + S021 (battery, range) | N86: corroborated | P86: 79 | Q86: 679 | R86: =IF(O86="","",IF(O86=J86,"Match","MISMATCH")) | S86: =IF(P86="","",IF(P86=G86,"Match","MISMATCH")) -> Match | T86: =IF(Q86="","",IF(Q86=K86,"Match","MISMATCH")) -> Match | U86: Claude | V86: 2026-10-23 | W86: 6-seater (captain seats) price from chatbot: 7-seater + ₹20,000. Screenshot website to verify.; Corroborated: chatbot + CarDekho + V3Cars + ZigWheels agree.
A87: V086 | B87: Mahindra | C87: XEV 9S | D87: SUV | E87: 2026 | F87: Pack Three | G87: 79 | H87: Pack Three 79 kWh (6-seater) | I87: battery included | J87: 2805000 | K87: 679 | L87: MIDC Part 1 + Part 2 | M87: S042 (price, chatbot), S020 + S021 (battery, range) | N87: corroborated | P87: 79 | Q87: 679 | R87: =IF(O87="","",IF(O87=J87,"Match","MISMATCH")) | S87: =IF(P87="","",IF(P87=G87,"Match","MISMATCH")) -> Match | T87: =IF(Q87="","",IF(Q87=K87,"Match","MISMATCH")) -> Match | U87: Claude | V87: 2026-10-23 | W87: 6-seater (captain seats) price from chatbot: 7-seater + ₹20,000. Screenshot website to verify.; Corroborated: chatbot + CarDekho + V3Cars + ZigWheels agree.
A88: V087 | B88: Mahindra | C88: XEV 9S | D88: SUV | E88: 2026 | F88: Pack Three Above | G88: 79 | H88: Pack Three Above 79 kWh (7-seater) | I88: battery included | J88: 2995000 | K88: 679 | L88: MIDC Part 1 + Part 2 | M88: S053 (price: CarWale, V3Cars, evelectree agree), S020 (battery, range) | N88: corroborated | P88: 79 | Q88: 679 | R88: =IF(O88="","",IF(O88=J88,"Match","MISMATCH")) | S88: =IF(P88="","",IF(P88=G88,"Match","MISMATCH")) -> Match | T88: =IF(Q88="","",IF(Q88=K88,"Match","MISMATCH")) -> Match | U88: Claude | V88: 2026-10-23 | W88: 7-seater price not published. Not estimated (rule 2).; ₹29.95L = 6-seater minus ₹20,000.

Sheet Features
A1: variant_id | B1: variant_name (for reading only) | C1: feature | D1: value | E1: unit | F1: source_id | G1: status | H1: notes
A2: V001 | B2: One 59 kWh | C2: motor_torque_nm | D2: 360 | E2: Nm | F2: S009 | G2: verified | H2: Older BE 6 sources say 380 Nm; SPORTEQ brochure says 360
A3: V001 | B3: One 59 kWh | C3: drive_type | D3: RWD | F3: S009 | G3: verified
A4: V001 | B4: One 59 kWh | C4: dc_charge_time_20_80_min | D4: 20 | E4: min | F4: S009 | G4: verified
A5: V001 | B5: One 59 kWh | C5: airbags | D5: 6 | E5: count | F5: S009 | G5: verified
A6: V001 | B6: One 59 kWh | C6: boot_space_l | D6: 455 | E6: litres | F6: S009 | G6: verified
A7: V001 | B7: One 59 kWh | C7: frunk_l | D7: 45 | E7: litres | F7: S009 | G7: verified
A8: V001 | B8: One 59 kWh | C8: ground_clearance_mm | D8: 207 | E8: mm | F8: S009 | G8: verified
A9: V001 | B9: One 59 kWh | C9: length_mm | D9: 4371 | E9: mm | F9: S009 | G9: verified
A10: V001 | B10: One 59 kWh | C10: width_mm | D10: 1907 | E10: mm | F10: S009 | G10: verified
A11: V001 | B11: One 59 kWh | C11: height_mm | D11: 1627 | E11: mm | F11: S009 | G11: verified
A12: V001 | B12: One 59 kWh | C12: wheelbase_mm | D12: 2775 | E12: mm | F12: S009 | G12: verified
A13: V001 | B13: One 59 kWh | C13: turning_circle_m | D13: 10 | E13: m | F13: S009 | G13: verified
A14: V001 | B14: One 59 kWh | C14: battery_warranty | D14: Lifetime for first private owner; else 10 yrs / 2,00,000 km | F14: S009 | G14: verified
A15: V001 | B15: One 59 kWh | C15: realworld_range_maker_claim | D15: 400+ km | F15: S011 | G15: verified | H15: Mahindra's own test, not independent. Do not treat as real-world data.
A16: V001 | B16: One 59 kWh | C16: motor_power_kw | D16: 170 | E16: kW | F16: S009 | G16: verified
A17: V001 | B17: One 59 kWh | C17: dc_fast_charge_max_kw | D17: 140 | E17: kW | F17: S009 | G17: verified
A18: V001 | B18: One 59 kWh | C18: ac_charge_time_0_100_h_11kw | D18: 6 | E18: hours | F18: S009 | G18: verified
A19: V001 | B19: One 59 kWh | C19: ac_charge_time_0_100_h_7kw | D19: 8.7 | E19: hours | F19: S009 | G19: verified
A20: V001 | B20: One 59 kWh | C20: screen_setup | D20: Dual 31.24 cm | F20: S009 | G20: verified
A21: V001 | B21: One 59 kWh | C21: instrument_panel | D21: Halo | F21: S009 | G21: verified
A22: V001 | B22: One 59 kWh | C22: wheels | D22: R18 steel, aero covers | F22: S009 | G22: verified
A23: V001 | B23: One 59 kWh | C23: adas_level | D23: None listed | F23: S009 | G23: verified | H23: 'None listed' = not in brochure for this trim
A24: V001 | B24: One 59 kWh | C24: surround_camera | D24: Rear camera only | F24: S009 | G24: verified
A25: V001 | B25: One 59 kWh | C25: sunroof | D25: None | F25: S009 | G25: verified
A26: V001 | B26: One 59 kWh | C26: ventilated_front_seats | D26: no | F26: S009 | G26: verified
A27: V001 | B27: One 59 kWh | C27: powered_driver_seat_memory | D27: no | F27: S009 | G27: verified
A28: V001 | B28: One 59 kWh | C28: climate_control | D28: Single zone auto, rear AC vents | F28: S009 | G28: verified
A29: V001 | B29: One 59 kWh | C29: audio | D29: 6 speakers | F29: S009 | G29: verified
A30: V001 | B30: One 59 kWh | C30: hud | D30: no | F30: S009 | G30: verified
A31: V001 | B31: One 59 kWh | C31: auto_park_assist | D31: no | F31: S009 | G31: verified
A32: V001 | B32: One 59 kWh | C32: adaptive_suspension | D32: no | F32: S009 | G32: verified
A33: V001 | B33: One 59 kWh | C33: power_tailgate | D33: no | F33: S009 | G33: verified
A34: V001 | B34: One 59 kWh | C34: knee_airbag | D34: no | F34: S009 | G34: verified
A35: V001 | B35: One 59 kWh | C35: interior_theme | D35: Sage Green & Grey | F35: S009 | G35: verified
A36: V001 | B36: One 59 kWh | C36: chipset | D36: Snapdragon 8155 | F36: S009 | G36: verified
A37: V001 | B37: One 59 kWh | C37: seating | D37: 5 | E37: count | F37: S014 | G37: pending | H37: Mahindra chatbot only. Confirm with dealer or manual.
A38: V001 | B38: One 59 kWh | C38: wall_charger_7kw_price_inr | D38: 50000 | E38: ₹ | F38: S014 | G38: pending | H38: Mahindra chatbot only. Charger price excludes installation.
A39: V001 | B39: One 59 kWh | C39: wall_charger_11kw_price_inr | D39: 75000 | E39: ₹ | F39: S014 | G39: pending | H39: Mahindra chatbot only. Charger price excludes installation.
A40: V001 | B40: One 59 kWh | C40: tyre_size | D40: 245/60 R18 | F40: S012 | G40: pending | H40: From original BE 6 manual (Feb 2025). Likely unchanged on SPORTEQ, but confirm with SPORTEQ manual.
A41: V001 | B41: One 59 kWh | C41: spare_tyre | D41: Temporary spare T135/80 R18 | F41: S012 | G41: pending | H41: From original BE 6 manual (Feb 2025). Likely unchanged on SPORTEQ, but confirm with SPORTEQ manual.
A42: V001 | B42: One 59 kWh | C42: tyre_pressure_psi | D42: 36 | E42: psi | F42: S012 | G42: pending | H42: From original BE 6 manual (Feb 2025). Likely unchanged on SPORTEQ, but confirm with SPORTEQ manual.
A43: V001 | B43: One 59 kWh | C43: onboard_ac_charger_kw | D43: 11 | E43: kW | F43: S012 | G43: pending | H43: From original BE 6 manual (Feb 2025). Likely unchanged on SPORTEQ, but confirm with SPORTEQ manual.
A44: V001 | B44: One 59 kWh | C44: hv_battery_nominal_voltage_v | D44: 307 | E44: V | F44: S012 | G44: pending | H44: From original BE 6 manual (Feb 2025). Likely unchanged on SPORTEQ, but confirm with SPORTEQ manual.
A45: V001 | B45: One 59 kWh | C45: motor_type | D45: IPMSM | F45: S012 | G45: pending | H45: From original BE 6 manual (Feb 2025). Likely unchanged on SPORTEQ, but confirm with SPORTEQ manual.
A46: V001 | B46: One 59 kWh | C46: charge_port | D46: CCS2 | F46: S012 | G46: pending | H46: From original BE 6 manual (Feb 2025). Likely unchanged on SPORTEQ, but confirm with SPORTEQ manual.
A47: V001 | B47: One 59 kWh | C47: transmission | D47: Single speed | F47: S012 | G47: pending | H47: From original BE 6 manual (Feb 2025). Likely unchanged on SPORTEQ, but confirm with SPORTEQ manual.
A48: V002 | B48: One 59 kWh BaaS | C48: motor_torque_nm | D48: 360 | E48: Nm | F48: S009 | G48: verified | H48: Older BE 6 sources say 380 Nm; SPORTEQ brochure says 360
A49: V002 | B49: One 59 kWh BaaS | C49: drive_type | D49: RWD | F49: S009 | G49: verified
A50: V002 | B50: One 59 kWh BaaS | C50: dc_charge_time_20_80_min | D50: 20 | E50: min | F50: S009 | G50: verified
A51: V002 | B51: One 59 kWh BaaS | C51: airbags | D51: 6 | E51: count | F51: S009 | G51: verified
A52: V002 | B52: One 59 kWh BaaS | C52: boot_space_l | D52: 455 | E52: litres | F52: S009 | G52: verified
A53: V002 | B53: One 59 kWh BaaS | C53: frunk_l | D53: 45 | E53: litres | F53: S009 | G53: verified
A54: V002 | B54: One 59 kWh BaaS | C54: ground_clearance_mm | D54: 207 | E54: mm | F54: S009 | G54: verified
A55: V002 | B55: One 59 kWh BaaS | C55: length_mm | D55: 4371 | E55: mm | F55: S009 | G55: verified
A56: V002 | B56: One 59 kWh BaaS | C56: width_mm | D56: 1907 | E56: mm | F56: S009 | G56: verified
A57: V002 | B57: One 59 kWh BaaS | C57: height_mm | D57: 1627 | E57: mm | F57: S009 | G57: verified
A58: V002 | B58: One 59 kWh BaaS | C58: wheelbase_mm | D58: 2775 | E58: mm | F58: S009 | G58: verified
A59: V002 | B59: One 59 kWh BaaS | C59: turning_circle_m | D59: 10 | E59: m | F59: S009 | G59: verified
A60: V002 | B60: One 59 kWh BaaS | C60: battery_warranty | D60: Lifetime for first private owner; else 10 yrs / 2,00,000 km | F60: S009 | G60: verified
A61: V002 | B61: One 59 kWh BaaS | C61: realworld_range_maker_claim | D61: 400+ km | F61: S011 | G61: verified | H61: Mahindra's own test, not independent. Do not treat as real-world data.
A62: V002 | B62: One 59 kWh BaaS | C62: motor_power_kw | D62: 170 | E62: kW | F62: S009 | G62: verified
A63: V002 | B63: One 59 kWh BaaS | C63: dc_fast_charge_max_kw | D63: 140 | E63: kW | F63: S009 | G63: verified
A64: V002 | B64: One 59 kWh BaaS | C64: ac_charge_time_0_100_h_11kw | D64: 6 | E64: hours | F64: S009 | G64: verified
A65: V002 | B65: One 59 kWh BaaS | C65: ac_charge_time_0_100_h_7kw | D65: 8.7 | E65: hours | F65: S009 | G65: verified
A66: V002 | B66: One 59 kWh BaaS | C66: screen_setup | D66: Dual 31.24 cm | F66: S009 | G66: verified
A67: V002 | B67: One 59 kWh BaaS | C67: instrument_panel | D67: Halo | F67: S009 | G67: verified
A68: V002 | B68: One 59 kWh BaaS | C68: wheels | D68: R18 steel, aero covers | F68: S009 | G68: verified
A69: V002 | B69: One 59 kWh BaaS | C69: adas_level | D69: None listed | F69: S009 | G69: verified | H69: 'None listed' = not in brochure for this trim
A70: V002 | B70: One 59 kWh BaaS | C70: surround_camera | D70: Rear camera only | F70: S009 | G70: verified
A71: V002 | B71: One 59 kWh BaaS | C71: sunroof | D71: None | F71: S009 | G71: verified
A72: V002 | B72: One 59 kWh BaaS | C72: ventilated_front_seats | D72: no | F72: S009 | G72: verified
A73: V002 | B73: One 59 kWh BaaS | C73: powered_driver_seat_memory | D73: no | F73: S009 | G73: verified
A74: V002 | B74: One 59 kWh BaaS | C74: climate_control | D74: Single zone auto, rear AC vents | F74: S009 | G74: verified
A75: V002 | B75: One 59 kWh BaaS | C75: audio | D75: 6 speakers | F75: S009 | G75: verified
A76: V002 | B76: One 59 kWh BaaS | C76: hud | D76: no | F76: S009 | G76: verified
A77: V002 | B77: One 59 kWh BaaS | C77: auto_park_assist | D77: no | F77: S009 | G77: verified
A78: V002 | B78: One 59 kWh BaaS | C78: adaptive_suspension | D78: no | F78: S009 | G78: verified
A79: V002 | B79: One 59 kWh BaaS | C79: power_tailgate | D79: no | F79: S009 | G79: verified
A80: V002 | B80: One 59 kWh BaaS | C80: knee_airbag | D80: no | F80: S009 | G80: verified
A81: V002 | B81: One 59 kWh BaaS | C81: interior_theme | D81: Sage Green & Grey | F81: S009 | G81: verified
A82: V002 | B82: One 59 kWh BaaS | C82: chipset | D82: Snapdragon 8155 | F82: S009 | G82: verified
A83: V002 | B83: One 59 kWh BaaS | C83: seating | D83: 5 | E83: count | F83: S014 | G83: pending | H83: Mahindra chatbot only. Confirm with dealer or manual.
A84: V002 | B84: One 59 kWh BaaS | C84: wall_charger_7kw_price_inr | D84: 50000 | E84: ₹ | F84: S014 | G84: pending | H84: Mahindra chatbot only. Charger price excludes installation.
A85: V002 | B85: One 59 kWh BaaS | C85: wall_charger_11kw_price_inr | D85: 75000 | E85: ₹ | F85: S014 | G85: pending | H85: Mahindra chatbot only. Charger price excludes installation.
A86: V002 | B86: One 59 kWh BaaS | C86: tyre_size | D86: 245/60 R18 | F86: S012 | G86: pending | H86: From original BE 6 manual (Feb 2025). Likely unchanged on SPORTEQ, but confirm with SPORTEQ manual.
A87: V002 | B87: One 59 kWh BaaS | C87: spare_tyre | D87: Temporary spare T135/80 R18 | F87: S012 | G87: pending | H87: From original BE 6 manual (Feb 2025). Likely unchanged on SPORTEQ, but confirm with SPORTEQ manual.
A88: V002 | B88: One 59 kWh BaaS | C88: tyre_pressure_psi | D88: 36 | E88: psi | F88: S012 | G88: pending | H88: From original BE 6 manual (Feb 2025). Likely unchanged on SPORTEQ, but confirm with SPORTEQ manual.
A89: V002 | B89: One 59 kWh BaaS | C89: onboard_ac_charger_kw | D89: 11 | E89: kW | F89: S012 | G89: pending | H89: From original BE 6 manual (Feb 2025). Likely unchanged on SPORTEQ, but confirm with SPORTEQ manual.
A90: V002 | B90: One 59 kWh BaaS | C90: hv_battery_nominal_voltage_v | D90: 307 | E90: V | F90: S012 | G90: pending | H90: From original BE 6 manual (Feb 2025). Likely unchanged on SPORTEQ, but confirm with SPORTEQ manual.
A91: V002 | B91: One 59 kWh BaaS | C91: motor_type | D91: IPMSM | F91: S012 | G91: pending | H91: From original BE 6 manual (Feb 2025). Likely unchanged on SPORTEQ, but confirm with SPORTEQ manual.
A92: V002 | B92: One 59 kWh BaaS | C92: charge_port | D92: CCS2 | F92: S012 | G92: pending | H92: From original BE 6 manual (Feb 2025). Likely unchanged on SPORTEQ, but confirm with SPORTEQ manual.
A93: V002 | B93: One 59 kWh BaaS | C93: transmission | D93: Single speed | F93: S012 | G93: pending | H93: From original BE 6 manual (Feb 2025). Likely unchanged on SPORTEQ, but confirm with SPORTEQ manual.
A94: V003 | B94: Two 59 kWh | C94: motor_torque_nm | D94: 360 | E94: Nm | F94: S009 | G94: verified | H94: Older BE 6 sources say 380 Nm; SPORTEQ brochure says 360
A95: V003 | B95: Two 59 kWh | C95: drive_type | D95: RWD | F95: S009 | G95: verified
A96: V003 | B96: Two 59 kWh | C96: dc_charge_time_20_80_min | D96: 20 | E96: min | F96: S009 | G96: verified
A97: V003 | B97: Two 59 kWh | C97: airbags | D97: 6 | E97: count | F97: S009 | G97: verified
A98: V003 | B98: Two 59 kWh | C98: boot_space_l | D98: 455 | E98: litres | F98: S009 | G98: verified
A99: V003 | B99: Two 59 kWh | C99: frunk_l | D99: 45 | E99: litres | F99: S009 | G99: verified
A100: V003 | B100: Two 59 kWh | C100: ground_clearance_mm | D100: 207 | E100: mm | F100: S009 | G100: verified
...

Sheet Sources
A1: source_id | B1: what it is | C1: source_type | D1: url | E1: date_checked | F1: saved_file | G1: what it supports
A2: S001 | B2: TimesDrive: BE 6 Sporteq variant-wise pricing (news) | C2: secondary | D2: https://www.timesdrive.in/news/mahindra-be-6-sporteq-edition-launched-in-india-at-rs-11-45-lakh-with-baas-check-variant-wise-pricing-article-155668115 | E2: 2026-10-22 | G2: Full list of 12 variant names and ex-showroom prices
A3: S002 | B3: Gaadify: BE 6 Sporteq launch article (news) | C3: secondary | D3: https://gaadify.com/2026-mahindra-be-6-sporteq-launched-with-new-dashboard-and-triple-screen-setup/ | E3: 2026-10-22 | G3: Described BaaS as '+ ₹3.75/km'. WRONG: Mahindra says it is a loan, not per-km (S010)
A4: S003 | B4: Gaadify: BE 6 Sporteq One variant detailed (news) | C4: secondary | D4: https://gaadify.com/mahindra-be-6-sporteq-one-variant-detailed-price-features-specs-and-images/ | E4: 2026-10-22 | G4: 59 kWh claimed 573 km (MIDC P1+P2)
A5: S004 | B5: 91wheels: BE 6 Sporteq launch news (aggregator) | C5: secondary | D5: https://www.91wheels.com/news/mahindra-be-6-sporteq-launched-at-rs-1945-lakh-know-more | E5: 2026-10-22 | G5: Says 59 kWh = 548 km, 79 kWh = 683 km. Conflicts with S003.
A6: S005 | B6: Spinny blog: BE 6 Sporteq launch (aggregator) | C6: secondary | D6: https://www.spinny.com/blog/mahindra-be-6-sporteq-launched-at-rs-19-45-lakh/ | E6: 2026-10-22 | G6: DC fast charge 140/160/180 kW; BaaS only on One and Two 59 kWh; Launch Edition paint
A7: S006 | B7: CarDekho: which variant gets which battery (news) | C7: secondary | D7: https://www.cardekho.com/india-car-news/2026-mahindra-be-6-sporteq-which-variant-gets-what-battery-pack-detailed-36521.htm | E7: 2026-10-22 | G7: Trim-to-battery mapping
A8: S007 | B8: Mahindra Book Now / variant selection page | C8: OFFICIAL | D8: https://www.mahindraelectricsuv.com/own-online/variant-selection?pid=MBE6 | F8: (save PDF) | G8: TO DO: battery-included prices for all variants except One
A9: S009 | B9: Mahindra BE 6 SPORTEQ brochure, version V5 dated 12.10.2026 | C9: OFFICIAL | D9: (uploaded file) | E9: 2026-10-22 | F9: BE6_SPORTEQ_BROCHURE.pdf | G9: Battery, range, motor, charging, dimensions, warranty, all variant features. Has NO prices.
A10: S010 | B10: Mahindra BaaS FAQ page (official) | C10: OFFICIAL | D10: https://www.mahindraelectricsuv.com/be-6-sporteq/baas-faq.html | E10: 2026-10-22 | F10: Mahindra_BaaS_FAQs___Battery-as-a-Service_for_EVs.pdf | G10: BaaS prices for ALL BE 6 / XEV 9S / XEV 9e variants; BaaS is a dual loan, not pay-per-km
A11: S011 | B11: Mahindra BE 6 SPORTEQ page, FAQ section (official) | C11: OFFICIAL | D11: https://www.mahindraelectricsuv.com/esuv/be6sporteq.html | E11: 2026-10-22 | F11: (save as PDF) | G11: One 59 kWh price ₹19.45L; ranges 573/651/708; real-world 400+/450+/500+ km
A12: S012 | B12: BE 6 Quick Reference Vehicle Manual, issue Feb 2025 (official) | C12: OFFICIAL (older model) | D12: https://www.mahindraelectricsuv.com/on/demandware.static/-/Library-Sites-eSUVSharedLibrary/default/dw12dff5e3/ImportantDocs/Vehicle%20Manual_BE6.pdf | E12: 2026-10-22 | F12: Vehicle_Manual_BE6.pdf | G12: Original BE 6, NOT SPORTEQ: only 59/79 kWh, 380 Nm. Used only for tyres, onboard charger, voltage. No seating, weights or service schedule.
A13: S013 | B13: Mahindra e-Verito owner's manual | C13: REJECTED | E13: 2026-10-22 | F13: Mahindra_Owners_Manual_E_Verito1.pdf | G13: Wrong vehicle (old electric sedan). Do not use.
A14: S014 | B14: Mahindra website AI chatbot (answers pasted by Madhu) | C14: official channel, AI | D14: mahindraelectricsuv.com chatbot | E14: 2026-10-22 | F14: (screenshots) | G14: Prices for 9 battery-included variants match S001. Seating 5. Wall charger ₹50k / ₹75k. RANGES WRONG (557/600/683): rejected.
A15: S015 | B15: Mahindra XEV 9e brochure R1 20260428, version V31 (official) | C15: OFFICIAL | D15: mahindraelectricsuv.com XEV 9e page > Download Brochure | E15: 2026-10-22 | F15: XEV9e_BROCHURE_R1_20260428.pdf | G15: Variants (Pack One/Two/Three Select/Three), battery, range, motor, dimensions, charging, full feature table. No Cineluxe, no prices.
A16: S016 | B16: Mahindra XEV 9e model page incl. FAQ, saved 22 Oct 2026 (official) | C16: OFFICIAL | D16: https://www.mahindraelectricsuv.com/esuv/xev-9e/MXV9.html | E16: 2026-10-22 | F16: Mahindra_XEV_9e_eSUV_-FAQs.pdf | G16: Pack One price ₹21.90L; 6 trim+battery combos incl. Cineluxe 79; ranges 522/656; real-world 400+/500+; 5-seater
A17: S017 | B17: XEV 9e Warranty & Service Information Guide, issue Mar 2025, release Apr 2026 (official) | C17: OFFICIAL | D17: mahindraelectricsuv.com/importantdocs.html | E17: 2026-10-22 | F17: XEV9e_Warranty_Service.pdf | G17: Vehicle 3 yrs/unlimited km; battery lifetime; motor 8 yrs/1.6L km; battery SOH guarantee; service every 10,000 km; RSA 3 yrs
A18: S018 | B18: XEV 9e detailed Vehicle Manual (HTML print), issue Mar 2025 (official) | C18: OFFICIAL (older) | D18: booking.mahindra.com XEV9e-OM.html | E18: 2026-10-22 | F18: Vehicle_Manual_XEV_9E.pdf | G18: Tyre pressure 36 psi, onboard charger 11 kW, voltage 307/409 V, optional R20 tyres. No seating or kerb weight.
A19: S019 | B19: Mahindra XEV 9e Cineluxe page incl. FAQ, saved 22 Oct 2026 (official) | C19: OFFICIAL | D19: https://www.mahindraelectricsuv.com/esuv/xev-9e/cineluxe.html | E19: 2026-10-22 | F19: Mahindra_XEV_9e_Cineluxe_Edition_-_Price__Range___Colours.pdf | G19: Cineluxe ₹29.35L; BaaS ₹19.35L; 79 kWh, 656 km, 180 kW DC; wall charger 11.2 kW ₹75,000 / 7.2 kW ₹60,000; portable 3.3 kW
A20: S020 | B20: Mahindra XEV 9S brochure R20_V1, version V8, file dated Aug 2026 (official) | C20: OFFICIAL | D20: mahindraelectricsuv.com XEV 9S page > Download Brochure | E20: 2026-10-22 | F20: XEV9S_BROCHURE.pdf | G20: 4 trims, 59/70/79 kWh, ranges 521/600/679, dimensions, 6/7 seats, openable sunroof all variants, full feature table. No prices.
A21: S021 | B21: Mahindra XEV 9S model page incl. FAQ, saved 22 Oct 2026 (official) | C21: OFFICIAL | D21: mahindraelectricsuv.com XEV 9S page | E21: 2026-10-22 | F21: Mahindra_XEV_9S_7-Seater_eSUV_.pdf | G21: Pack One Above 59 ₹21.40L; Three Above 79 6-seater ₹30.15L (+₹75k charger); real-world 400+/450+/500+; 7.2 kW charger ₹60,000
A22: S022 | B22: XEV 9S Warranty & Service Information Guide, issue Dec 2025, release Apr 2026 (official) | C22: OFFICIAL | D22: mahindraelectricsuv.com/importantdocs.html | E22: 2026-10-22 | F22: XEV9S_WSIG.pdf | G22: Same warranty terms as XEV 9e; service every 10,000 km; 3 labour-free services
A23: S023 | B23: XEV 9S Owner's Manual (HTML print), issue Jan 2026 (official) | C23: OFFICIAL | D23: mvault-cloudfront.mahindra.com XEV 9S HTML | E23: 2026-10-22 | F23: Owner_s_Manual_XEV_9S.pdf | G23: Power 170/180/210 kW, voltage 307/358/409 V, onboard 11 kW, tyre 235/60 R18, 36 psi. No kerb weight.
A24: S024 | B24: Autocar India XEV 9S specifications page (independent test) | C24: secondary | D24: https://www.autocarindia.com/cars/mahindra/xev-9s/specifications | E24: 2026-10-22 | F24: (save as PDF) | G24: Tested range, 79 kWh: 477 km highway, 478 km city
A25: S025 | B25: Mahindra XUV 3XO EV brochure R3, version V2, dated Jun 2026 (official) | C25: OFFICIAL | D25: auto.mahindra.com XUV 3XO EV page | E25: 2026-10-22 | F25: 29-06-MM-3XO-EV-BROCHURE_R3.pdf | G25: AX5 / AX7L, 39.4 kWh, MIDC P1+P2 351 km (P1 only 456 km), real-world 285 km, 50 kW DC, battery warranty 8 yrs/1.6L km
... A60: S037 | B60: Sierra.ev launch prices (CarDekho / evindia news, Jun-Oct 2026) | C60: secondary | D60: https://www.cardekho.com/news/general/tata-sierra-ev-launched-at-rs-1879-lakh-find-full-prices-variants-design-features-and-specifications-here-36229.htm | E60: 2026-10-23 | F60: (save as PDF) | G60: 8 persona prices ₹18.79L to ₹25.99L
A61: S008 | B61: Earlier ChatGPT summary | C61: not a source | G61: Said 79 kWh = 708 km. AI output, cannot verify anything on its own.

Sheet Open_Questions
A1: q_id | B1: variants | C1: field | D1: value A (source) | E1: value B (source) | F1: what to do | G1: state
A2: Q001 | B2: 59 kWh rows | C2: claimed_range_km (59 kWh) | D2: 573 km (S003, S009, S011) | E2: 548 km (S004) | F2: SETTLED: 573 km. Brochure and website agree. | G2: closed
A3: Q002 | B3: 79 kWh rows | C3: claimed_range_km (79 kWh) | D3: 708 km (S009, S011) | E3: 683 km (S004) | F3: SETTLED: 708 km. Brochure and website agree. | G3: closed
A4: Q003 | B4: 70 kWh rows | C4: claimed_range_km (70 kWh) | D4: 652 km (S009, brochure V5 12.10.2026) | E4: 651 km (S011, website FAQ) | F4: SETTLED by decision: use the website figure, 651 km (Madhu, 23 Oct 2026). 1 km difference; brochure figure kept in this note. | G4: closed
A5: Q004 | B5: All | C5: Variant count | D5: 7 / 8 / 12 depending on source | F5: Now 20 rows: 10 trim+battery combos x (battery included, BaaS). BaaS is on ALL variants (S010). | G5: closed
A6: Q005 | B6: Battery-included rows except One | C6: Ex-showroom prices | D6: News (S001) and Mahindra chatbot (S014) agree on all 9 | F6: SETTLED: corroborated (Autocar, TimesDrive, Cars24, chatbot agree) | G6: closed
A7: Q006 | B7: BaaS rows | C7: How BaaS works | D7: News: 'price + ₹3.75/km' (S002) | E7: Mahindra: dual loan, battery owned, no per-km charge (S010) | F7: SETTLED: it's a loan. ₹3.75/km is marketing math (₹6,975 EMI / 60 km x 31 days). | G7: closed
A8: Q007 | B8: All | C8: Wall charger cost | D8: 7.2 kW ₹50,000 / 11.2 kW ₹75,000, installation extra (S014 chatbot) | F8: Confirm with dealer and get installation cost | G8: open
A9: Q008 | B9: FE Four rows | C9: Ventilated + memory seats on FE Four | D9: Brochure: both 'only in THREE' | E9: Chatbot: ventilated in Three, powered seat in Three+ (contradicts brochure, dodged question) | F9: Ask dealer. Chatbot not reliable here. | G9: open
A10: Q009 | B10: All | C10: Seating capacity, kerb weight, Bharat NCAP | D10: Seating 5 (S014 chatbot) | E10: Kerb weight: chatbot has no data | F10: SETTLED: seating from model pages; crash ratings in bncap_* fields. Kerb weight moved to Q071. | G10: closed
A11: Q014 | B11: All | C11: Range from chatbot | D11: 557 / 600 / 683 km (S014) | E11: 573 / 652 / 708 km (S009 brochure, S011 website) | F11: Chatbot is serving old pre-SPORTEQ figures. REJECTED. Do not use chatbot for range. | G11: closed
A12: Q015 | B12: BE 6 | C12: Vehicle warranty + service interval | D12: Chatbot: 'shared at delivery' | E12: XEV 9e guide says 3 yrs + 10,000 km service | F12: Download the BE 6 Warranty & Service Guide from importantdocs page; likely same as XEV 9e but confirm | G12: open
A13: Q016 | B13: XEV 9e battery-included rows | C13: Ex-showroom prices | D13: SETTLED: all official (S051) except Pack Two 79 kWh ₹26.50L (corroborated) | G13: closed
A14: Q017 | B14: XEV 9e Pack Two 59 + Pack Three Select BaaS | C14: BaaS price | D14: BaaS page: 'all variants' | E14: But no price listed for these two | F14: Ask dealer | G14: open
A15: Q018 | B15: XEV 9e Cineluxe | C15: Full feature list | D15: Cineluxe page (S019): price, battery, audio, adaptive suspension, screens, satin paints | E15: Doesn't say if it has Pack Three's HUD, L2+ ADAS, 360 camera, ventilated seats | F15: Ask dealer, or 'View specs' button on Cineluxe page | G15: open
A16: Q025 | B16: All models | C16: 7.2 kW wall charger price | D16: ₹60,000 (S019, official Cineluxe page) | E16: ₹50,000 (S014, Mahindra chatbot, for BE 6) | F16: SETTLED for XEV 9e/9S: ₹60,000 on two official Mahindra pages. BE 6 assumed same, not confirmed. | G16: closed
A17: Q026 | B17: All models | C17: Portable charger power | D17: 3.3 kW (S019 Cineluxe page, S021 XEV 9S page) | E17: 3.0 kW (S015, S018, S023 manuals); 3.2 kW (S009 BE 6 + S020 XEV 9S brochures) | F17: Same 13A charger, three numbers. Minor; ask dealer. | G17: open
A18: Q027 | B18: XEV 9S | C18: Seating changes price | D18: 6-seater = 7-seater + ₹20,000 (S042) | F18: SETTLED: seating is now part of the row key; 6- and 7-seater rows split | G18: closed
A19: Q054 | B19: XEV 9e Pack Two 59 kWh | C19: Price + BaaS | D19: Price ₹24.90L now official (S051) | E19: BaaS price not published (chatbot's ₹16.50L is the 79 kWh figure) | F19: Price SETTLED; BaaS left blank | G19: closed
A20: Q055 | B20: XEV 9e Pack Two 79 / Pack Three Select | C20: Availability | D20: Chatbot: 'not available' | E20: Mahindra page + every aggregator list both with prices | F20: SETTLED: both on sale. Chatbot wrong. | G20: closed
A21: Q028x | B21: XEV 9S One Above 59 | C21: Price + BaaS | D21: ₹21.40L on Mahindra page includes 11.2 kW charger (CarWale) | E21: Without charger ₹20.65L; BaaS ₹12.65L = ₹20.65L - ₹8L | F21: SETTLED | G21: closed
A22: Q028 | B22: XEV 9S BaaS | C22: Odd BaaS prices | D22: Two Above 70 BaaS > 79 BaaS: NOT a typo. 7-seater prices (S042) minus ₹9L / ₹10L battery give exactly ₹16.05L / ₹15.95L. | E22: One Above 59 BaaS ₹12.65L: still doesn't fit (should be ~₹13.40L) | F22: SETTLED (see Q028x): not a typo | G22: closed
A23: Q029 | B23: XEV 9S | C23: Battery value pattern | D23: ₹10.20L gap on Three Above was the 6-seater: captain seats cost ₹20,000 extra (S042) | E23: With 7-seater prices, battery adds ₹9L (70) / ₹10L (79) as on other Mahindras | F23: SETTLED, except One Above 59 (see Q028) | G23: closed
A24: Q030 | B24: XEV 9S battery-included rows | C24: Prices | D24: Chatbot gave 7- and 6-seater prices (S042); consistent with BaaS page | E24: Three Above 7-seater not published | F24: SETTLED: corroborated via aggregators + chatbot + BaaS arithmetic | G24: closed
A25: Q031 | B25: XEV 9S | C25: Kerb weight + Bharat NCAP | D25: Not in manual, brochure or guide | F25: SETTLED for NCAP (not tested, S046). Kerb weight moved to Q071. | G25: closed
A26: Q032 | B26: XUV400 | C26: Is it still sold new? | D26: Autocar (Mar-Apr 2026): on sale | E26: Other report: replaced by XUV 3XO EV. Only brochure found is Feb 2024. | F26: Check auto.mahindra.com for a current XUV400 page with prices. If none, mark discontinued. | G26: open
A27: Q033 | B27: XUV 3XO EV | C27: BaaS availability | D27: Mahindra BaaS page covers Electric Origin SUVs only | F27: Ask dealer; assume not offered | G27: open
A28: Q034 | B28: XUV 3XO EV | C28: 34.43 kWh battery | D28: Manual (S027) lists 39.4 and 34.43 kWh | E28: Brochure (S025) and press: 39.4 kWh only | F28: Smaller pack likely not sold (carried from XUV400). Ask dealer. | G28: open
A29: Q035 | B29: XUV 3XO EV | C29: Charger included | D29: Brochure spec: portable 13A up to 3.0 kW | E29: Brochure AX5 list: 3.3 kW wall-mounted unit; manual: 3.3 kW EVSE | F29: Confirm what comes in the box | G29: open
A30: Q036 | B30: XUV 3XO EV AX7L | C30: Ex-showroom price | D30: ₹14.96L (CarDekho, Autocar) | E30: No official page seen yet | F30: SETTLED: corroborated ₹14.96L (Autocar, Team-BHP) | G30: closed
A31: Q038 | B31: All | C31: Rough-road fields still missing | D31: Laden clearance, angles, battery IP rating, underbody protection, tyre type, kerb weight | F31: Add to dealer WhatsApp; check Team-BHP / Autocar road tests for laden clearance and scraping reports | G31: open
A32: Q039 | B32: Tigor.ev | C32: Still on sale? | D32: Tata.ev site lists prices Oct 2026 (S040) | F32: SETTLED: on sale, ₹12.49-13.75L | G32: closed
A33: Q048 | B33: Tigor.ev | C33: Brochure vs website features | D33: Website (Oct 2026) adds rear camera, 8 speakers, cruise on XZ+ | E33: Brochure is Sep 2025 | F33: Website is newer; used website. Minor. | G33: closed
A34: Q040 | B34: Punch.ev 30 | C34: MIDC range | D34: Brochure + Tata FAQ both publish '365-375 km' (a band) | E34: Tata gives no single figure | F34: SETTLED: recorded 365 km (lower, conservative) as comparable number; band kept in Features | G34: closed
A35: Q041 | B35: Harrier.ev | C35: Fearless+ QWD 75 | D35: Tata.ev site lists 'Fearless+ 75 AWD' at ₹26.79L | F35: SETTLED: it is sold | G35: closed
A36: Q049 | B36: Harrier.ev | C36: 'ACFC' versions | D36: Each Harrier.ev variant has an ACFC version at +₹50,000 | E36: ACFC = includes 7.2 kW AC fast charger wall box | F36: Treated as a charger option on the same row, not a separate variant | G36: closed
A37: Q042 | B37: Sierra.ev | C37: Persona-wise features | D37: Mapped from Tata.ev website (S040) | F37: SETTLED | G37: closed
A38: Q051 | B38: Curvv.ev Accomplished X | C38: Wall charger included? | D38: Brochure: 7.2 kW wall box included (footnote Ω) | E38: Website: listed only on Empowered X | F38: Ask dealer; matters for ₹50k ownership cost | G38: open
A39: Q052 | B39: Tiago.ev Creative+ 24 | C39: Price | D39: Autocar: ₹9.99L | E39: Tata.ev site: ₹10.09L | F39: SETTLED: site wins | G39: closed
A40: Q053 | B40: Tiago.ev Smart 19 / Pure+, Tigor.ev (all) | C40: ESP | D40: Tiago.ev: listed only on Creative+ 24. Tigor.ev: lists CSC, not ESP | E40: Every other Mahindra and Tata lists ESP on all variants | F40: Safety point for recommendations; confirm with dealer | G40: open
A41: Q056 | B41: XUV 3XO EV, Nexon.ev, Sierra.ev, Tigor.ev, Tiago.ev | C41: Body type | D41: Not stated by makers | E41: Filled from Autocar (secondary) per Madhu's rule: maker's wording first, else Autocar | F41: SETTLED. Replace with maker wording if found later. | G41: closed
A42: Q057 | B42: BE 6 SPORTEQ | C42: Does the Jan 2025 BE 6 crash rating cover SPORTEQ? | D42: Portal lists 'BE 6, January 2025 - Onwards' | E42: SPORTEQ is a 2026 update (new 70 kWh, new interior) | F42: Open 'Ratings Applicability' tab on the BE 6 result page | G42: open
